Workbook
Name Slicer_DATACENTER_STAGE: #N/A
Name Slicer_DATACENTER_STAGE1: #N/A
Name Slicer_state_code7: #N/A

Sheet US 30d Comparison
A1: DATA_CENTER_STAGE | B1: q_current | C1: s_current_power_capacity_mw | D1: s_current_square_footage | E1: q_30d_ago | F1: s_30d_ago_power_capacity_mw | G1: s_30d_ago_square_footage | H1: q_delta_30d | I1: s_delta_30d_power_capacity_mw | J1: s_delta_30d_square_footage | K1: updated_at
A2: Active | B2: 2050 | C2: 50265.115 | D2: 306666979 | E2: 2026 | F2: 49052.965 | G2: 303768469 | H2: 24 | I2: 1212.15 | J2: 2898510 | K2: 46233
A3: Announcement | B3: 3905 | C3: 357584.73 | D3: 700591051 | E3: 3631 | F3: 316114.57 | G3: 655804736 | H3: 274 | I3: 41470.16 | J3: 44786315 | K3: 46233
A4: Cancelled | B4: 7 | C4: 391 | D4: 530800 | E4: 19 | F4: 1024.96 | G4: 3470800 | H4: -12 | I4: -633.96 | J4: -2940000 | K4: 46233
A5: Construction | B5: 807 | C5: 68103.12 | D5: 218578023 | E5: 766 | F5: 62649.99 | G5: 205722196 | H5: 41 | I5: 5453.13 | J5: 12855827 | K5: 46233
A6: Delayed | B6: 92 | C6: 8901.64 | D6: 19160437 | E6: 84 | F6: 7180.64 | G6: 18915437 | H6: 8 | I6: 1721 | J6: 245000 | K6: 46233
A7: Land Bank | B7: 60 | C7: 2379.52 | D7: 4050000 | E7: 54 | F7: 2379.52 | G7: 4050000 | H7: 6 | I7: 0 | J7: 0 | K7: 46233
A8: Not Approved/Withdrawn | B8: 630 | C8: 33493.04 | D8: 126567351 | E8: 552 | F8: 29942.05 | G8: 116738087 | H8: 78 | I8: 3550.99 | J8: 9829264 | K8: 46233

Sheet US Data Centers Dataset
A1: ATERIO_DATACENTER_UNIQUE_ID | B1: DATA_CENTER_BUILDING_NAME | C1: DATA_CENTER_SCATTER_PLOT_NAME | D1: PROVIDER_NAME | E1: DATACENTER_STAGE | F1: STATE_CODE | G1: STATE_NAME | H1: TOT_FACILITY_SPACE_SQFT | I1: TOT_DATACENTER_SPACE_SQFT | J1: TOT_POWER_MW | K1: RECORD_UPDATED_DATE | L1: UPDATED_AT
A2: 1f0a736d-3fa7-4fb1-9237-a287e7429e85 | B2: Prineville Data Center Building 2 | D2: Apple Inc. | E2: Active | F2: OR | G2: Oregon | H2: 300000 | I2: 300000 | J2: 29.703 | K2: 45535 | L2: 2026-07-31
A3: 84a56dcf-7a7e-4e43-8d56-e6263200220e | B3: Prineville Data Center Building 1 | D3: Apple Inc. | E3: Active | F3: OR | G3: Oregon | H3: 300000 | I3: 300000 | J3: 29.703 | K3: 45535 | L3: 2026-07-31
A4: 57014f52-9864-40ee-8050-a1b938138fa7 | B4: Prineville Data Center Building 3 | D4: Apple Inc. | E4: Active | F4: OR | G4: Oregon | H4: 270000 | I4: 270000 | J4: 29.213 | K4: 45535 | L4: 2026-07-31
A5: 0426f94e-6b7f-49de-adff-f04211eba271 | B5: Reno Data Center Building 1 | D5: Apple Inc. | E5: Active | F5: NV | G5: Nevada | H5: 450000 | I5: 450000 | J5: 54.562 | K5: 45535 | L5: 2026-07-31
A6: 67fd4c73-e93a-4c46-976b-cf671bd608a3 | B6: Reno Data Center Building 2 | D6: Apple Inc. | E6: Active | F6: NV | G6: Nevada | H6: 420000 | I6: 420000 | J6: 45.542 | K6: 45535 | L6: 2026-07-31
A7: 176c4ae3-2d4d-4e3d-9543-4e83564b6cf1 | B7: Reno Data Center Building 3 | D7: Apple Inc. | E7: Active | F7: NV | G7: Nevada | H7: 420000 | I7: 420000 | J7: 45.542 | K7: 45535 | L7: 2026-07-31
A8: d6eaaa00-82b5-11f0-884c-a193525c71ad | B8: Thornton Labs - Butte | D8: Company Not Disclosed | E8: Active | F8: MT | G8: Montana | K8: 45900 | L8: 2026-07-31
A9: cbeb1340-c641-11f0-8416-4dd1bc094c6c | B9: Atlas Power Butte Data Center | D9: Company Not Disclosed | E9: Active | F9: MT | G9: Montana | J9: 75 | K9: 45991 | L9: 2026-07-31
A10: 404bd811-f564-4444-b14d-f9b57bfe18df | B10: Mesa Data Center Building 1 | C10: Mesa Data Center Building 1 Mesa, Apple Campus Apple Inc. | D10: Apple Inc. | E10: Active | F10: AZ | G10: Arizona | H10: 1332000 | I10: 1332000 | J10: 85.294 | K10: 45535 | L10: 2026-07-31
A11: 00371327-8827-4ad4-8197-b3b4fa7fe7c6 | B11: Waukee IA Data Center Building 1 | D11: Apple Inc. | E11: Active | F11: IA | G11: Iowa | H11: 290000 | I11: 290000 | J11: 29.871 | K11: 45535 | L11: 2026-07-31
A12: d4e0fe10-5ec1-11f1-9ac0-c161a6bf6c99 | B12: 1831 Chesnut Data Center | D12: Company Not Disclosed | E12: Active | F12: MO | G12: Missouri | I12: 53000 | J12: 4.7324 | K12: 46203 | L12: 2026-07-31
A13: ed291889-2684-4ed4-8070-2cdacf25cf3d | B13: Chicago Data Center | D13: IT Solutions Group | E13: Active | F13: IL | G13: Illinois | I13: 120000 | J13: 8.62 | K13: 45535 | L13: 2026-07-31
A14: 4cfaa9b0-7a0f-11f1-b634-bd9fd4e3b265 | B14: i74 Wired business campus | D14: Company Not Disclosed | E14: Active | F14: OH | G14: Ohio | I14: 65000 | J14: 2 | K14: 46234 | L14: 2026-07-31
A15: 50bc18e0-55fc-11f1-8fed-dd9b759592d6 | B15: Strategic Datasphere Data Center | D15: Company Not Disclosed | E15: Active | F15: GA | G15: Georgia | I15: 165000 | J15: 5.4 | K15: 46173 | L15: 2026-07-31
A16: 020947e0-76ef-11f1-882c-4deedad4e203 | B16: Georgia Technology Center | D16: Company Not Disclosed | E16: Active | F16: GA | G16: Georgia | J16: 4.8 | K16: 46234 | L16: 2026-07-31
A17: b2f93a27-5612-43b9-826e-af1ef0e6b788 | B17: Statesboro Edge Data Center | D17: EdgePresence | E17: Active | F17: GA | G17: Georgia | H17: 360 | I17: 360 | J17: 0.1 | K17: 45535 | L17: 2026-07-31
A18: f61feb50-da3e-4797-b538-ef6337578bbf | B18: JAX2 Edge Data Center | D18: EdgePresence | E18: Active | F18: FL | G18: Florida | H18: 160 | I18: 160 | J18: 0.52375 | K18: 45535 | L18: 2026-07-31
A19: e8e1dddc-94b9-4a49-973b-b196d3edd098 | B19: Orlando Data Center | D19: IT Solutions Group | E19: Active | F19: FL | G19: Florida | I19: 130000 | J19: 10.1215 | K19: 45535 | L19: 2026-07-31
A20: 34d5dde0-cb47-4230-95a3-e009a989e5e9 | B20: Maiden Data Center Building 3 | D20: Apple Inc. | E20: Active | F20: NC | G20: North Carolina | H20: 180000 | I20: 180000 | J20: 13.9395 | K20: 45535 | L20: 2026-07-31
A21: 6c9bee4f-2d88-4f75-917c-ac75e2122009 | B21: Maiden Data Center Building 1 | D21: Apple Inc. | E21: Active | F21: NC | G21: North Carolina | H21: 420000 | I21: 420000 | J21: 46.49 | K21: 45535 | L21: 2026-07-31
A22: 826fd604-fd83-47db-a472-a793c7d372e7 | B22: Maiden Data Center Building 4 | D22: Apple Inc. | E22: Active | F22: NC | G22: North Carolina | H22: 220000 | I22: 220000 | J22: 21.933 | K22: 45535 | L22: 2026-07-31
A23: bfa07a33-552a-4dda-a5cf-c72bf0e01b7f | B23: Maiden Data Center Building 2 | D23: Apple Inc. | E23: Active | F23: NC | G23: North Carolina | H23: 200000 | I23: 200000 | J23: 17.236 | K23: 45535 | L23: 2026-07-31
A24: aa8d6670-34d4-11f0-a9e1-c9350c8c3578 | B24: Albion Data Center | D24: Company Not Disclosed | E24: Active | F24: NY | G24: New York | H24: 130000 | I24: 130000 | J24: 1 | K24: 45808 | L24: 2026-07-31
A25: 3c85e73a-2005-4de0-995b-511fb6c131b0 | B25: PTP Data Center 1 | D25: Company Not Disclosed | E25: Active | F25: VA | G25: Virginia | H25: 250000 | I25: 250000 | J25: 32.5 | K25: 45716 | L25: 2026-07-31
A26: 6a6a7eb9-2758-4fcd-aa73-845eb8f32664 | B26: PTP Data Center 2 | D26: Company Not Disclosed | E26: Active | F26: VA | G26: Virginia | H26: 250000 | I26: 250000 | J26: 32.5 | K26: 45716 | L26: 2026-07-31
A27: ea5ddd62-abb0-493e-98b5-c8b28d9763ad | B27: Asburn Data Center | D27: Atlantic.net | E27: Active | F27: VA | G27: Virginia | J27: 2 | K27: 45535 | L27: 2026-07-31
A28: 27594a60-794a-11f1-bcaf-0fe1f28909ae | B28: Roble Road Data Center | D28: Company Not Disclosed | E28: Active | F28: PA | G28: Pennsylvania | I28: 46800 | J28: 40 | K28: 46234 | L28: 2026-07-31
A29: 8c5ae027-536d-44f4-97fe-aeb2890013e0 | B29: Union Station Data Center | D29: Iron Rails Data Centers | E29: Active | F29: NY | G29: New York | I29: 97000 | J29: 4 | K29: 45535 | L29: 2026-07-31
A30: b0cedd74-da2d-40a7-bf0e-8ca9bf0b0307 | B30: 701 River Street Data Center | D30: Iron Rails Data Centers | E30: Active | F30: NY | G30: New York | K30: 45535 | L30: 2026-07-31
A31: b8942abb-9203-4445-a98b-99f81540c911 | B31: Seattle South Hill Campus | D31: Centeris | E31: Active | F31: WA | G31: Washington | H31: 150000 | I31: 150000 | J31: 40 | K31: 45535 | L31: 2026-07-31
A32: e5796f90-851e-11f1-a8ec-c382bf3e166b | B32: Kubach Rd Data Center | D32: NorthPoint Development | E32: Active | F32: PA | G32: Pennsylvania | I32: 124190 | J32: 13.2 | K32: 46234 | L32: 2026-07-31
A33: cc811930-6367-11f1-a926-fdddf37ad9ea | B33: Bitdeer Data Center Phase 2A | D33: Bitdeer | E33: Active | F33: OH | G33: Ohio | J33: 74 | K33: 46203 | L33: 2026-07-31
A34: 788dfa44-c732-4585-ba92-208143d5d8e2 | B34: Bitdeer Data Center Phase 1 | D34: Bitdeer | E34: Active | F34: OH | G34: Ohio | J34: 47 | K34: 45688 | L34: 2026-07-31
A35: b59a195f-876d-48ed-b2c7-d3d61ccf43f3 | B35: Data Center 5 | D35: Global[X]Digital | E35: Active | F35: OK | G35: Oklahoma | J35: 53 | K35: 46234 | L35: 2026-07-31
A36: ae23081e-ffff-476f-9b1d-badaadbfb759 | B36: Data Center 1 | D36: Global[X]Digital | E36: Active | F36: OK | G36: Oklahoma | J36: 53 | K36: 46234 | L36: 2026-07-31
A37: 705a882e-e4ff-4652-9cad-76ad1cb42c8f | B37: Data Center 4 | D37: Global[X]Digital | E37: Active | F37: OK | G37: Oklahoma | J37: 53 | K37: 46234 | L37: 2026-07-31
A38: 788fa154-761d-408e-b6c7-3416284929d0 | B38: Data Center 3 | D38: Global[X]Digital | E38: Active | F38: OK | G38: Oklahoma | J38: 53 | K38: 46234 | L38: 2026-07-31
A39: 08031536-2d56-4621-ae8b-3f6b75e0decb | B39: Data Center 2 | D39: Global[X]Digital | E39: Active | F39: OK | G39: Oklahoma | J39: 53 | K39: 46234 | L39: 2026-07-31
A40: 967d3e81-e6e1-44ac-93d0-710ff23d44af | B40: Data Center 6 | D40: Global[X]Digital | E40: Active | F40: OK | G40: Oklahoma | J40: 53 | K40: 46234 | L40: 2026-07-31
A41: d29b6390-1cc5-11f1-a62f-195ab6965f0e | B41: Greenidge Bidcoin Mining | D41: Greenidge Generation Holdings Inc | E41: Active | F41: NY | G41: New York | J41: 60 | K41: 46112 | L41: 2026-07-31
A42: 47f63a60-1c95-11f1-a186-d1d5b2ca4e6e | B42: Project Sycamore | D42: JPMorganChase | E42: Active | F42: NY | G42: New York | I42: 279044 | J42: 25 | K42: 46112 | L42: 2026-07-31
A43: 79425200-61e0-4c29-bc3c-9b447e2240e2 | B43: Riot Rockdale DC 1 | D43: Riot Platforms, Inc. | E43: Active | F43: TX | G43: Texas | J43: 100 | K43: 46173 | L43: 2026-07-31
A44: f091382a-fa84-4e13-99ca-163a218d77f5 | B44: Dallas Facility | D44: Sungard Availability Services | E44: Active | F44: TX | G44: Texas | H44: 75000 | I44: 35000 | J44: 3 | K44: 45535 | L44: 2026-07-31
A45: 44034c83-c1ac-4345-b767-75af4dc4196a | B45: Carlstadt 777 Facility | D45: Sungard Availability Services | E45: Active | F45: NJ | G45: New Jersey | H45: 326000 | I45: 37278 | J45: 16 | K45: 45535 | L45: 2026-07-31
A46: 1ead58ba-5af9-427a-b35c-49afb509a0bf | B46: Marlborough 250 Facility | D46: Sungard Availability Services | E46: Active | F46: MA | G46: Massachusetts | H46: 62000 | I46: 23000 | J46: 3 | K46: 45535 | L46: 2026-07-31
A47: 02573965-7f3a-4a74-af1c-beb5ba32ca20 | B47: Crypto Data Center 1 | D47: Ardent Data Centers | E47: Active | F47: TX | G47: Texas | I47: 37813 | J47: 35 | K47: 46173 | L47: 2026-07-31
A48: 121bdeb7-1063-4af1-91ad-5abea5b23403 | B48: Crypto Data Center 2 | D48: Ardent Data Centers | E48: Active | F48: TX | G48: Texas | I48: 37813 | J48: 35 | K48: 46173 | L48: 2026-07-31
A49: 765d9b6d-0af3-461e-b021-42a89f454468 | B49: Pittsburgh Data Center | D49: Ardent Data Centers | E49: Active | F49: PA | G49: Pennsylvania | H49: 41000 | I49: 41000 | J49: 5 | K49: 45565 | L49: 2026-07-31
A50: db5ef542-ac2d-48f3-8e1c-d56eb9c6cd9d | B50: Amazon AWS IAD - John Marshall 2 Building 1 | D50: Black Chamber | E50: Active | F50: VA | G50: Virginia | H50: 255000 | I50: 255000 | J50: 60 | K50: 45596 | L50: 2026-07-31
A51: a2cc340a-5cd2-4356-9244-649614b679bf | B51: Bluebird Underground Data Center | D51: Bluebird Data Centers | E51: Active | F51: MO | G51: Missouri | H51: 125000 | I51: 125000 | J51: 6 | K51: 45535 | L51: 2026-07-31
A52: 4db0ccaf-94b6-4d19-8c46-52b95d9d4d1a | B52: Bluebird Quad Cities Data Center | D52: Bluebird Data Centers | E52: Active | F52: IA | G52: Iowa | H52: 53000 | I52: 53000 | J52: 4 | K52: 45535 | L52: 2026-07-31
A53: 91d25e5b-b7e3-43e4-8e32-34b0937ad273 | B53: Colocation Data Center Texas | D53: Carter Funds | E53: Active | F53: TX | G53: Texas | H53: 47000 | I53: 47000 | J53: 5.90185 | K53: 45657 | L53: 2026-07-31
A54: a7d65e2b-ab66-448a-a51b-89794405c577 | B54: Enterprise Data Center Collierville | D54: Carter Funds | E54: Active | F54: TN | G54: Tennessee | H54: 86000 | I54: 86000 | J54: 6.5446 | K54: 45657 | L54: 2026-07-31
A55: 4e2f9e00-4a3d-11f1-8336-9117771308f1 | B55: Carter Funds Louisville Data Center | D55: Carter Funds | E55: Active | F55: KY | G55: Kentucky | I55: 102500 | J55: 1 | K55: 46173 | L55: 2026-07-31
A56: ac5f0e80-4a3c-11f1-9a10-45db1407e806 | B56: Carter Funds Simpsonville Data Center | D56: Carter Funds | E56: Active | F56: KY | G56: Kentucky | I56: 102500 | J56: 1 | K56: 46173 | L56: 2026-07-31
A57: 8e15a947-87d7-4d54-ab98-566fba92a5cf | B57: Enterprise Data Center 1 NoVa | D57: Carter Funds | E57: Active | F57: VA | G57: Virginia | H57: 97800 | I57: 97800 | J57: 8.4977 | K57: 45657 | L57: 2026-07-31
A58: 13c82a0f-ee57-451e-95c7-ac716a6a8f3a | B58: Enterprise Data Center 2 NoVa | D58: Carter Funds | E58: Active | F58: CT | G58: Connecticut | H58: 228000 | I58: 228000 | J58: 15 | K58: 45657 | L58: 2026-07-31
A59: 8c390be1-7270-4601-a956-c09bf8d5c1cb | B59: Lynnwood, WA | D59: Chirisa Technology Parks | E59: Active | F59: WA | G59: Washington | H59: 17000 | I59: 17000 | J59: 15 | K59: 45565 | L59: 2026-07-31
A60: 5096fdde-f0b7-433b-9256-9b08b2e49efe | B60: Chicago, IL YL0-1/YLO-2 | D60: Chirisa Technology Parks | E60: Active | F60: IL | G60: Illinois | H60: 200000 | I60: 200000 | J60: 28 | K60: 45535 | L60: 2026-07-31
A61: 99b62384-25c8-4e59-9fce-dd9decfae414 | B61: CTP-01 Richmond - AI Data Center | D61: Chirisa Technology Parks | E61: Active | F61: VA | G61: Virginia | H61: 250000 | I61: 250000 | J61: 28 | K61: 45535 | L61: 2026-07-31
A62: 8c092674-9ed2-4857-921b-e786c8f3ee57 | B62: CTP-02 Richmond | D62: Chirisa Technology Parks | E62: Active | F62: VA | G62: Virginia | H62: 142000 | I62: 142000 | J62: 60 | K62: 45565 | L62: 2026-07-31
A63: 4ebe57b5-9c88-4e64-88e9-00cb6de5a9ab | B63: PNJ-01 Data Center | D63: Chirisa Technology Parks | E63: Active | F63: NJ | G63: New Jersey | H63: 41000 | I63: 41000 | J63: 25 | K63: 45565 | L63: 2026-07-31
A64: ddf6e828-8ce0-439f-980c-91842b233682 | B64: MCC1 Northern Virginia | D64: CloudHQ | E64: Active | F64: VA | G64: Virginia | H64: 460000 | I64: 460000 | J64: 55 | K64: 45535 | L64: 2026-07-31
A65: 90737f01-5a27-4e1c-bf2f-52e02082fbcd | B65: MCC2 Northern Virginia | D65: CloudHQ | E65: Active | F65: VA | G65: Virginia | H65: 350000 | I65: 350000 | J65: 60 | K65: 45535 | L65: 2026-07-31
A66: 95dd45c0-c9b1-46e9-974c-985cb32ad501 | B66: MCC6A Northern Virginia | D66: CloudHQ | E66: Active | F66: VA | G66: Virginia | H66: 125000 | I66: 125000 | J66: 12 | K66: 45535 | L66: 2026-07-31
A67: c832d21b-09a2-409a-b715-5c69bff394d0 | B67: LC4 Northern Virginia | D67: CloudHQ | E67: Active | F67: VA | G67: Virginia | H67: 1580560 | I67: 1580560 | J67: 180 | K67: 45535 | L67: 2026-07-31
A68: 8d645170-e505-4ac6-9813-608000c3fcca | B68: LC1 Northern Virginia | D68: CloudHQ | E68: Active | F68: VA | G68: Virginia | H68: 998400 | I68: 998400 | J68: 144 | K68: 45535 | L68: 2026-07-31
... A95: de33bee3-0389-4f53-aaac-319e66915a17 | B95: AI Data Center Building 9 | D95: Crusoe | E95: Active | F95: TX | G95: Texas | H95: 125000 | I95: 125000 | J95: 37.5 | K95: 45688 | L95: 2026-07-31
A96: 151cf420-84ed-11f0-97c2-e96684c69a2c | B96: Fargo Great Plains | D96: Dakota Carrier Network | E96: Active | F96: ND | G96: North Dakota | H96: 23180 | K96: 45900 | L96: 2026-07-31
A97: a03b26b4-6677-4a09-921d-da0b046ab185 | B97: Minneapolis Data Center | D97: Data Holdings (Stack 41) | E97: Active | F97: MN | G97: Minnesota | H97: 473500 | I97: 473500 | J97: 13 | K97: 45535 | L97: 2026-07-31
A98: 1b60dcca-a250-4292-b1f9-b755a7c33023 | B98: Pioneer Park I Data Center | D98: DataNovaX | E98: Active | F98: TX | G98: Texas | H98: 37000 | I98: 37000 | J98: 6 | K98: 45626 | L98: 2026-07-31
A99: 0815ef40-30d8-481c-92b6-44475ac820f4 | B99: NEP Real Estate Data Center 1 Phase 1 | D99: DataOne | E99: Active | F99: NJ | G99: New Jersey | J99: 50 | K99: 45747 | L99: 2026-07-31
A100: a2f05a2e-fa7f-4a6f-b541-c55567645351 | B100: La Marque Data center | D100: Dataprana | E100: Active | F100: TX | G100: Texas | J100: 30 | K100: 45657 | L100: 2026-07-31
A101: 52c76000-48af-11f0-acb2-03596e304807 | B101: 100 Digital Crossroad Data Center | D101: Digital Crossroad | E101: Active | F101: IN | G101: Indiana | H101: 105000 | I101: 72000 | J101: 20 | K101: 45838 | L101: 2026-07-31
A102: 3e4f7b3f-9fd5-4213-b014-6630b0b7311d | B102: Disney NC Data Center | D102: Disney | E102: Active | F102: NC | G102: North Carolina | H102: 98400 | I102: 98400 | J102: 6.0484 | K102: 45626 | L102: 2026-07-31
A103: 126424fc-ce6e-4414-9080-64aee0f2541e | B103: EC101 Los Angeles | D103: Edge Centers | E103: Active | F103: CA | G103: California | H103: 22000 | I103: 22000 | J103: 1 | K103: 45535 | L103: 2026-07-31
A104: 70b5bf12-1c8f-4f36-a405-52c647243203 | B104: EC103 Columbia | D104: Edge Centers | E104: Active | F104: MO | G104: Missouri | H104: 22000 | I104: 22000 | J104: 1 | K104: 45535 | L104: 2026-07-31
A105: 5b9e4f80-1da0-46bf-ac3f-9d78e0baf530 | B105: EC102 St Louis | D105: Edge Centers | E105: Active | F105: MO | G105: Missouri | H105: 22000 | I105: 22000 | J105: 1 | K105: 45535 | L105: 2026-07-31
A106: a721e6e7-bf63-4d6f-866a-38eec1096807 | B106: SV01 Silicon Valley Data Center | D106: Edgecore | E106: Active | F106: CA | G106: California | H106: 255198 | I106: 255198 | J106: 36 | K106: 45565 | L106: 2026-07-31
A107: 96a66846-6cc0-4624-ba4b-f6752a843919 | B107: PH02 Phoenix Edgecore Datacenter | D107: Edgecore | E107: Active | F107: AZ | G107: Arizona | H107: 868431 | I107: 868431 | J107: 108 | K107: 45565 | L107: 2026-07-31
A108: 153887a8-970b-4e50-8b9c-b2068c02d9aa | B108: PH01 Phoenix Edgecore Datacenter | D108: Edgecore | E108: Active | F108: AZ | G108: Arizona | H108: 200880 | I108: 200880 | J108: 26 | K108: 45565 | L108: 2026-07-31
A109: eaf5d220-3cf8-11f0-9eae-cbd192019700 | B109: FirstDigital Tucson | D109: FirstDigital Telecom | E109: Active | F109: AZ | G109: Arizona | K109: 45808 | L109: 2026-07-31
A110: f0fa8e30-8cef-11f0-a0e1-e994509decd2 | B110: H5 Colo Dallas | D110: H5 Colo | E110: Active | F110: TX | G110: Texas | H110: 55000 | I110: 55000 | J110: 17 | K110: 45930 | L110: 2026-07-31
A111: d4baa000-8378-11f0-9c98-5b4de06b5a42 | B111: Salt Creek Data Center | D111: Hut8 | E111: Active | F111: TX | G111: Texas | J111: 63 | K111: 45900 | L111: 2026-07-31
A112: 5d0e8a30-837d-11f0-9c98-5b4de06b5a42 | B112: King Mountain (JV) Data Center | C112: King Mountain (JV) Data Center Hut8 | D112: Hut8 | E112: Active | F112: TX | G112: Texas | J112: 280 | K112: 45900 | L112: 2026-07-31
A113: 29a58110-8375-11f0-9c98-5b4de06b5a42 | B113: Vega Data Center | C113: Vega Data Center Hut8 | D113: Hut8 | E113: Active | F113: TX | G113: Texas | H113: 162000 | J113: 205 | K113: 45900 | L113: 2026-07-31
A114: 586be8c0-82af-11f0-884c-a193525c71ad | B114: Hyperscale Data: Montana | D114: HyperScale Data | E114: Active | F114: MT | G114: Montana | J114: 10 | K114: 45900 | L114: 2026-07-31
A115: cb9813e0-fdfd-11f0-9f4b-83bc9db5afd7 | B115: Hyperscale Data - Michigan Data Center (Phase 1) | D115: HyperScale Data | E115: Active | F115: MI | G115: Michigan | H115: 617000 | I115: 100000 | J115: 30 | K115: 46053 | L115: 2026-07-31
A116: 7ce441e0-fb98-11f0-a215-13c0e4d6b0a7 | B116: Quantum Data Center 1 | D116: IonQ, Inc. | E116: Active | F116: MD | G116: Maryland | H116: 23000 | K116: 46053 | L116: 2026-07-31
A117: d68e1770-0387-11f0-96d2-f9c60eb67c8b | B117: Fort Stockton Clean Data Center | D117: Lancium | E117: Active | F117: TX | G117: Texas | I117: 100000 | J117: 25 | K117: 45747 | L117: 2026-07-31
A118: 9c61468f-fdcc-4f0e-993c-812c7b9103c8 | B118: Windstream Portland | D118: Windstream | E118: Active | F118: OR | G118: Oregon | K118: 45535 | L118: 2026-07-31
A119: fdef0d95-a444-4761-b9ff-e843c9382c8b | B119: Windstream Los Angeles | D119: Windstream | E119: Active | F119: CA | G119: California | K119: 45535 | L119: 2026-07-31
A120: 403d2e56-b203-4f89-9355-8f1860488a33 | B120: Windstream Phoenix | D120: Windstream | E120: Active | F120: AZ | G120: Arizona | I120: 15000 | J120: 0.89325 | K120: 45535 | L120: 2026-07-31
A121: 769ff4a5-65b2-4d46-a08e-f3dfa3d4dd6f | B121: Windstream Colorado Springs | D121: Windstream | E121: Active | F121: CO | G121: Colorado | I121: 14615 | J121: 1.25895 | K121: 45535 | L121: 2026-07-31
A122: d02d1fff-8900-4413-951f-5faf5593dcd7 | B122: Windstream Hobbs | D122: Windstream | E122: Active | F122: NM | G122: New Mexico | I122: 43000 | J122: 4.2107 | K122: 45535 | L122: 2026-07-31
A123: 71fa6fb3-f5ab-4624-b359-b11eb23685c3 | B123: Windstream Laredo | D123: Windstream | E123: Active | F123: TX | G123: Texas | I123: 3650 | J123: 0.4813 | K123: 45535 | L123: 2026-07-31
A124: 93f3cda5-cb23-4c70-b77b-127b43e5955c | B124: Windstream San Antonio | D124: Windstream | E124: Active | F124: TX | G124: Texas | K124: 45535 | L124: 2026-07-31
A125: f5de295e-b4bc-4d1e-9082-2902f57d35c6 | B125: Windstream Oklahoma City | D125: Windstream | E125: Active | F125: OK | G125: Oklahoma | K125: 45535 | L125: 2026-07-31
A126: 1fc3bea7-a2fa-49b9-82c3-87a0fe3ebcd6 | B126: Windstream Dallas | D126: Windstream | E126: Active | F126: TX | G126: Texas | K126: 45535 | L126: 2026-07-31
...

Sheet Data - Main KPIs
A1: 0. Maximum Updated Date
A3: 0.0 Updated Date Label (From Pipeline job date)
A4: Row Labels
A5: 2026-07-31
A7: 0.1 General (Recorded Date)
A8: LATEST_DATE | B8: LATEST INDEX
A9: 46234 | B9: 24
A11: 0.2 By Stage
A12: Row Labels | B12: LATEST_DATE | C12: LATEST INDEX | D12: INDEX STAGE | E12: FINAL ROW
A13: Active | B13: 46234 | C13: 22 | D13: 1 | E13: =C13-1 -> 21
A14: Announcement | B14: 46234 | C14: 24 | D14: 2 | E14: =E13+1+C14 -> 46
A15: Cancelled | B15: 46112 | C15: 6 | D15: 3 | E15: =E14+1+C15 -> 53
A16: Construction | B16: 46234 | C16: 24 | D16: 4 | E16: =E15+1+C16 -> 78
A17: Delayed | B17: 45961 | C17: 12 | D17: 5 | E17: =E16+1+C17 -> 91
A18: Not Approved/Withdrawn | B18: 46234 | C18: 23 | D18: 6 | E18: =E17+1+C18 -> 115
A22: Row Labels | B22: # Facilities
A23: Active | B23: 2050
A24: Announcement | B24: 3905
A25: Cancelled | B25: 7
A26: Construction | B26: 807
A27: Delayed | B27: 92
A28: Not Approved/Withdrawn | B28: 630
A30: Row Labels | B30: # Facilities
A31: Active | B31: 50265.133
A32: Announcement | B32: 357584.84
A33: Cancelled | B33: 390.9975
A34: Construction | B34: 68103.116
A35: Delayed | B35: 8901.6833
A36: Not Approved/Withdrawn | B36: 33493.113
A38: Row Labels | B38: # Facilities
A39: Active | B39: 306666979
A40: Announcement | B40: 700591051
A41: Cancelled | B41: 530800
A42: Construction | B42: 218578023
A43: Delayed | B43: 19160437
A44: Not Approved/Withdrawn | B44: 126567351
A46: 1. Main KPIs
A48: DATACENTER_STAGE | B48: (All)
A50: Row Labels | B50: TOTAL | C50: TOTAL ACCUM | D50: SUM POWER MWH | E50: SUM POWER MWH ACCUM | F50: AVG POWER MWH | G50: AVG POWER MWH ACCUM | H50: SUM SPACE SQFT | I50: SUM SPACE SQFT ACCUM | J50: AVG SPACE SQFT | K50: AVG SPACE SQFT ACCUM
A51: 45535 | B51: 1751 | C51: 1751 | D51: 41219.709 | E51: 41219.709 | F51: 24.801269 | G51: 24.801269 | H51: 275522711 | I51: 275522711 | J51: 168001.65 | K51: 168001.65
A52: 45565 | B52: 402 | C52: 2153 | D52: 24670.159 | E52: 65889.868 | F52: 63.912329 | G52: 88.713598 | H52: 93219524 | I52: 368742235 | J52: 270201.52 | K52: 438203.17
A53: 45596 | B53: 158 | C53: 2311 | D53: 7932.1703 | E53: 73822.038 | F53: 50.20361 | G53: 138.91721 | H53: 34677921 | I53: 403420156 | J53: 220878.48 | K53: 659081.65
A54: 45626 | B54: 273 | C54: 2584 | D54: 16494.62 | E54: 90316.658 | F54: 60.419852 | G54: 199.33706 | H54: 69135009 | I54: 472555165 | J54: 265903.88 | K54: 924985.53
A55: 45657 | B55: 179 | C55: 2763 | D55: 11870.606 | E55: 102187.26 | F55: 67.446627 | G55: 266.78369 | H55: 50940228 | I55: 523495393 | J55: 299648.4 | K55: 1224633.9
A56: 45688 | B56: 249 | C56: 3012 | D56: 15503.897 | E56: 117691.16 | F56: 67.999548 | G56: 334.78323 | H56: 67854906 | I56: 591350299 | J56: 323118.6 | K56: 1547752.5
A57: 45716 | B57: 177 | C57: 3189 | D57: 10879.102 | E57: 128570.26 | F57: 65.933954 | G57: 400.71719 | H57: 23436879 | I57: 614787178 | J57: 205586.66 | K57: 1753339.2
A58: 45747 | B58: 190 | C58: 3379 | D58: 15690.712 | E58: 144260.98 | F58: 82.582695 | G58: 483.29988 | H58: 51784736 | I58: 666571914 | J58: 319658.86 | K58: 2072998.1
A59: 45777 | B59: 159 | C59: 3538 | D59: 15743.166 | E59: 160004.14 | F59: 104.25938 | G59: 587.55926 | H59: 44847006 | I59: 711418920 | J59: 373725.05 | K59: 2446723.1
A60: 45808 | B60: 169 | C60: 3707 | D60: 12869.777 | E60: 172873.92 | F60: 81.454286 | G60: 669.01355 | H60: 52925605 | I60: 764344525 | J60: 430289.47 | K60: 2877012.6
A61: 45838 | B61: 228 | C61: 3935 | D61: 23827.023 | E61: 196700.94 | F61: 105.89788 | G61: 774.91142 | H61: 64916504 | I61: 829261029 | J61: 301937.23 | K61: 3178949.8
A62: 45869 | B62: 230 | C62: 4165 | D62: 18165.548 | E62: 214866.49 | F62: 90.375862 | G62: 865.28729 | H62: 54901729 | I62: 884162758 | J62: 406679.47 | K62: 3585629.3
... A74: 46234 | B74: 404 | C74: 7491 | D74: 38784.653 | E74: 518738.88 | F74: 117.52925 | G74: 2120.1748 | H74: 49953717 | I74: 1372094641 | J74: 288749.81 | K74: 7530431.1
A75: Grand Total | B75: 7491 | D75: 518738.88 | F75: 75.662031 | H75: 1372094641 | J75: 267569.16
A81: 1.1. Calculating Growth Rates
A82: LATEST UPDATED | B82: TOTAL | C82: SUM POWER MWH | D82: AVG POWER MWH | E82: SUM SQFT | F82: AVG SQFT | G82: TOTAL ADD | H82: SUM POWER MWH ADD | I82: AVG POWER MWH ADD | J82: SUM SQFT ADD | K82: AVG SQFT ADD | L82: GR TOTAL | M82: GR SUM POWER MWH | N82: GR AVG POWER MWH | O82: GR SUM SQFT | P82: GR AVG SQFT
A83: =$A$5 -> 2026-07-31 | B83: =(OFFSET(A51,$B$9-1,2)) -> 7491 | C83: =(OFFSET(A51,$B$9-1,4)) -> 518738.88 | D83: =(OFFSET(A51,$B$9-1,6)) -> 2120.1748 | E83: =(OFFSET(A51,$B$9-1,8)) -> 1372094641 | F83: =(OFFSET(A51,$B$9-1,10)) -> 7530431.1 | G83: =(OFFSET(A51,$B$9-1,1)) -> 404 | H83: =(OFFSET(A51,$B$9-1,3)) -> 38784.653 | I83: =(OFFSET(A51,$B$9-1,5)) -> 117.52925 | J83: =(OFFSET(A51,$B$9-1,7)) -> 49953717 | K83: =(OFFSET(A51,$B$9-1,9)) -> 288749.81 | L83: =(OFFSET(A51,$B$9-1,2) - OFFSET(A51,$B$9-2,2))/OFFSET(A51,$B$9-2,2) -> 0.057005785 | M83: =(OFFSET(A51,$B$9-1,4) - OFFSET(A51,$B$9-2,4))/OFFSET(A51,$B$9-2,4) -> 0.080809065 | N83: =(OFFSET(A51,$B$9-1,6) - OFFSET(A51,$B$9-2,6))/OFFSET(A51,$B$9-2,6) -> 0.058686996 | O83: =(OFFSET(A51,$B$9-1,8) - OFFSET(A51,$B$9-2,8))/OFFSET(A51,$B$9-2,8) -> 0.037782445 | P83: =(OFFSET(A51,$B$9-1,10) - OFFSET(A51,$B$9-2,10))/OFFSET(A51,$B$9-2,10) -> 0.039873311
A88: 2. Main KPIS By Stage
A90: DATACENTER_STAGE | B90: RECORD_UPDATED_DATE | C90: TOTAL | D90: TOTAL ACCUM | E90: SUM POWER MWH | F90: SUM POWER MWH ACCUM | G90: AVG POWER MWH | H90: AVG POWER MWH ACCUM | I90: SUM SPACE SQFT | J90: SUM SPACE SQFT ACCUM | K90: AVG SPACE SQFT | L90: AVG SPACE SQFT ACCUM
A91: Active | B91: 45535 | C91: 1592 | D91: 1592 | E91: 31493.423 | F91: 31493.423 | G91: 20.953708 | H91: 20.953708 | I91: 226653593 | J91: 226653593 | K91: 151607.75 | L91: 151607.75
A92: Active | B92: 45565 | C92: 123 | D92: 1715 | E92: 6159.0718 | F92: 37652.495 | G92: 50.073755 | H92: 71.027463 | I92: 28452799 | J92: 255106392 | K92: 239099.15 | L92: 390706.91
A93: Active | B93: 45596 | C93: 66 | D93: 1781 | E93: 2698.8161 | F93: 40351.311 | G93: 40.891153 | H93: 111.91862 | I93: 12938937 | J93: 268045329 | K93: 196044.5 | L93: 586751.41
A94: Active | B94: 45626 | C94: 86 | D94: 1867 | E94: 4116.2683 | F94: 44467.58 | G94: 47.863585 | H94: 159.7822 | I94: 17185707 | J94: 285231036 | K94: 202184.79 | L94: 788936.19
A95: Active | B95: 45657 | C95: 19 | D95: 1886 | E95: 674.39235 | F95: 45141.972 | G95: 35.494334 | H95: 195.27654 | I95: 2949481 | J95: 288180517 | K95: 173498.88 | L95: 962435.08
A96: Active | B96: 45688 | C96: 9 | D96: 1895 | E96: 419.9725 | F96: 45561.944 | G96: 46.663611 | H96: 241.94015 | I96: 2942000 | J96: 291122517 | K96: 420285.71 | L96: 1382720.8
A97: Active | B97: 45716 | C97: 36 | D97: 1931 | E97: 261.3994 | F97: 45823.344 | G97: 7.2610944 | H97: 249.20124 | I97: 2112793 | J97: 293235310 | K97: 58688.694 | L97: 1441409.5
A98: Active | B98: 45747 | C98: 16 | D98: 1947 | E98: 824.454 | F98: 46647.798 | G98: 51.528375 | H98: 300.72962 | I98: 3749000 | J98: 296984310 | K98: 249933.33 | L98: 1691342.8
A99: Active | B99: 45777 | C99: 2 | D99: 1949 | E99: 82 | F99: 46729.798 | G99: 41 | H99: 341.72962 | I99: 380301 | J99: 297364611 | K99: 190150.5 | L99: 1881493.3
A100: Active | B100: 45808 | C100: 11 | D100: 1960 | E100: 12.30485 | F100: 46742.103 | G100: 2.0508083 | H100: 343.78042 | I100: 153668 | J100: 297518279 | K100: 30733.6 | L100: 1912226.9
A101: Active | B101: 45838 | C101: 6 | D101: 1966 | E101: 266 | F101: 47008.103 | G101: 44.333333 | H101: 388.11376 | I101: 860200 | J101: 298378479 | K101: 143366.67 | L101: 2055593.6
A102: Active | B102: 45869 | C102: 4 | D102: 1970 | E102: 127.2909 | F102: 47135.394 | G102: 31.822725 | H102: 419.93648 | I102: 440610 | J102: 298819089 | K102: 110152.5 | L102: 2165746.1
... A112: Active | B112: 46234 | C112: 18 | D112: 2050 | E112: 748.86 | F112: 50265.133 | G112: 41.603333 | H112: 964.26753 | I112: 1546690 | J112: 306666979 | K112: 171854.44 | L112: 3986118.7
A113: Active Total | C113: 2050 | E113: 50265.133 | G113: 25.843256 | I113: 306666979 | K113: 161149.23
A114: Announcement | B114: 45535 | C114: 70 | D114: 70 | E114: 4414.0764 | F114: 4414.0764 | G114: 63.058234 | H114: 63.058234 | I114: 20808650 | J114: 20808650 | K114: 358769.83 | L114: 358769.83
A115: Announcement | B115: 45565 | C115: 119 | D115: 189 | E115: 9350.8034 | F115: 13764.88 | G115: 79.244097 | H115: 142.30233 | I115: 25606150 | J115: 46414800 | K115: 301248.82 | L115: 660018.65
A116: Announcement | B116: 45596 | C116: 21 | D116: 210 | E116: 1406.5627 | F116: 15171.443 | G116: 66.979176 | H116: 209.28151 | I116: 5011000 | J116: 51425800 | K116: 250550 | L116: 910568.65
A117: Announcement | B117: 45626 | C117: 112 | D117: 322 | E117: 7017.4905 | F117: 22188.933 | G117: 62.656165 | H117: 271.93767 | I117: 29941359 | J117: 81367159 | K117: 296449.1 | L117: 1207017.8
A118: Announcement | B118: 45657 | C118: 98 | D118: 420 | E118: 5596.987 | F118: 27785.92 | G118: 58.915653 | H118: 330.85333 | I118: 27664394 | J118: 109031553 | K118: 297466.6 | L118: 1504484.4
A119: Announcement | B119: 45688 | C119: 156 | D119: 576 | E119: 10911.998 | F119: 38697.918 | G119: 72.26489 | H119: 403.11822 | I119: 46608635 | J119: 155640188 | K119: 321438.86 | L119: 1825923.2
A120: Announcement | B120: 45716 | C120: 94 | D120: 670 | E120: 7871.305 | F120: 46569.223 | G120: 93.706012 | H120: 496.82423 | I120: 9388600 | J120: 165028788 | K120: 268245.71 | L120: 2094168.9
A121: Announcement | B121: 45747 | C121: 135 | D121: 805 | E121: 11603.751 | F121: 58172.974 | G121: 85.953711 | H121: 582.77794 | I121: 37173258 | J121: 202202046 | K121: 312380.32 | L121: 2406549.2
A122: Announcement | B122: 45777 | C122: 108 | D122: 913 | E122: 11107.839 | F122: 69280.813 | G122: 104.79093 | H122: 687.56887 | I122: 30388068 | J122: 232590114 | K122: 361762.71 | L122: 2768312
A123: Announcement | B123: 45808 | C123: 67 | D123: 980 | E123: 6393.1914 | F123: 75674.005 | G123: 103.11599 | H123: 790.68486 | I123: 14208570 | J123: 246798684 | K123: 489950.69 | L123: 3258262.7
A124: Announcement | B124: 45838 | C124: 135 | D124: 1115 | E124: 17664.935 | F124: 93338.939 | G124: 133.82526 | H124: 924.51012 | I124: 44190537 | J124: 290989221 | K124: 356375.3 | L124: 3614638
A125: Announcement | B125: 45869 | C125: 138 | D125: 1253 | E125: 10848.264 | F125: 104187.2 | G125: 86.786115 | H125: 1011.2962 | I125: 37363244 | J125: 328352465 | K125: 410585.1 | L125: 4025223
... A137: Announcement | B137: 46234 | C137: 348 | D137: 3905 | E137: 36519.192 | F137: 357584.84 | G137: 129.96154 | H137: 2305.6249 | I137: 45056937 | J137: 700591051 | K137: 308609.16 | L137: 7924720.2
A138: Announcement Total | C138: 3905 | E138: 357584.84 | G138: 101.06977 | I138: 700591051 | K138: 330623.43
A139: Cancelled | B139: 45535 | C139: 2 | D139: 2 | E139: 57.57 | F139: 57.57 | G139: 28.785 | H139: 28.785 | I139: 395800 | J139: 395800 | K139: 197900 | L139: 197900
A140: Cancelled | B140: 45657 | C140: 1 | D140: 3 | E140: 53.4275 | F140: 110.9975 | G140: 53.4275 | H140: 82.2125 | J140: 395800 | L140: 197900
A141: Cancelled | B141: 45688 | C141: 1 | D141: 4 | E141: 20 | F141: 130.9975 | G141: 20 | H141: 102.2125 | J141: 395800 | L141: 197900
A142: Cancelled | B142: 45777 | C142: 1 | D142: 5 | E142: 60 | F142: 190.9975 | G142: 60 | H142: 162.2125 | J142: 395800 | L142: 197900
A143: Cancelled | B143: 45838 | C143: 1 | D143: 6 | E143: 200 | F143: 390.9975 | G143: 200 | H143: 362.2125 | I143: 135000 | J143: 530800 | K143: 135000 | L143: 332900
A144: Cancelled | B144: 46112 | C144: 1 | D144: 7 | F144: 390.9975 | H144: 362.2125 | J144: 530800 | L144: 332900
A145: Cancelled Total | C145: 7 | E145: 390.9975 | G145: 65.16625 | I145: 530800 | K145: 176933.33
A146: Construction | B146: 45535 | C146: 77 | D146: 77 | E146: 4691.1944 | F146: 4691.1944 | G146: 60.924603 | H146: 60.924603 | I146: 24313668 | J146: 24313668 | K146: 324182.24 | L146: 324182.24
A147: Construction | B147: 45565 | C147: 111 | D147: 188 | E147: 6811.3739 | F147: 11502.568 | G147: 66.129844 | H147: 127.05445 | I147: 30756575 | J147: 55070243 | K147: 310672.47 | L147: 634854.71
A148: Construction | B148: 45596 | C148: 35 | D148: 223 | E148: 2608.7915 | F148: 14111.36 | G148: 74.5369 | H148: 201.59135 | I148: 11223060 | J148: 66293303 | K148: 320658.86 | L148: 955513.57
A149: Construction | B149: 45626 | C149: 68 | D149: 291 | E149: 4945.0063 | F149: 19056.366 | G149: 72.720681 | H149: 274.31203 | I149: 19942503 | J149: 86235806 | K149: 297649.3 | L149: 1253162.9
A150: Construction | B150: 45657 | C150: 39 | D150: 330 | E150: 4173.0028 | F150: 23229.369 | G150: 107.00007 | H150: 381.3121 | I150: 11990643 | J150: 98226449 | K150: 315543.24 | L150: 1568706.1
A151: Construction | B151: 45688 | C151: 43 | D151: 373 | E151: 2765.166 | F151: 25994.535 | G151: 64.306186 | H151: 445.61829 | I151: 11252271 | J151: 109478720 | K151: 296112.39 | L151: 1864818.5
A152: Construction | B152: 45716 | C152: 18 | D152: 391 | E152: 1465.817 | F152: 27460.352 | G152: 86.224529 | H152: 531.84281 | I152: 5338088 | J152: 114816808 | K152: 333630.5 | L152: 2198449
...

Sheet Data - DC by Project Stage
A1: 1. Facilities By US State
A2: DATACENTER_STAGE | B2: Active
A4: STATE_NAME | B4: # Facilities
A5: Virginia | B5: 334
A6: Texas | B6: 229
A7: California | B7: 167
A8: Ohio | B8: 113
A9: Oregon | B9: 100
A10: Arizona | B10: 85
A11: Illinois | B11: 79
A12: Washington | B12: 70
A13: Georgia | B13: 68
A14: Iowa | B14: 63
A61: 2. Facilities By Data Center Provider
A62: DATACENTER_STAGE | B62: Active
A64: PROVIDER_NAME | B64: TOTAL
A65: Amazon AWS | B65: 217
A66: Microsoft | B66: 122
A67: Digital Realty | B67: 107
A68: Facebook | B68: 104
A69: Lumen | B69: 97
A70: Google | B70: 86
A71: Equinix | B71: 74
A72: Cogent Communications | B72: 72
A73: QTS Data Centers | B73: 62
A74: DataBank | B74: 60
A82: 3. Power Comsumption By US State
A83: DATACENTER_STAGE | B83: Active
A85: STATE_NAME | B85: Total Power Consumption (MWh)
A86: Virginia | B86: 11745.472
A87: Texas | B87: 5952.2695
A88: Oregon | B88: 3934.1564
A89: Ohio | B89: 3777.4462
A90: Arizona | B90: 2941.423
A91: Georgia | B91: 2251.714
A92: Iowa | B92: 2062.4316
A93: Illinois | B93: 1751.3629
A94: California | B94: 1713.5105
A95: Tennessee | B95: 1340.4882
A101: 4. Power Comsumption By Data Center Provider
A102: DATACENTER_STAGE | B102: Active
A104: PROVIDER_NAME | B104: Total Power Consumption (MWh)
A105: Amazon AWS | B105: 10091.454
A106: Microsoft | B106: 5526.8735
A107: Google | B107: 5374.8036
A108: Facebook | B108: 4827.6657
A109: QTS Data Centers | B109: 2542.8186
A110: Digital Realty | B110: 2470.2791
A111: CyrusOne | B111: 1319.203
A112: Switch Data Centers | B112: 1126.053
A113: Aligned Data Centers | B113: 930
A114: xAI | B114: 927.76
A126: 5. Square Footage By US State
A127: DATACENTER_STAGE | B127: Active
A129: STATE_NAME | B129: Total SqFt Area
A130: Virginia | B130: 66207916
A131: Texas | B131: 30508721
A132: Oregon | B132: 20688975
A133: Ohio | B133: 18013805
A134: Arizona | B134: 17759760
A135: Georgia | B135: 15328398
A136: California | B136: 15261482
A137: Illinois | B137: 14773470
A138: Iowa | B138: 14411782
A139: Washington | B139: 9204870
A143: 5. Square Footage By US State
A144: DATACENTER_STAGE | B144: Active
A146: PROVIDER_NAME | B146: Total SqFt Area
A147: Facebook | B147: 45781150
A148: Amazon AWS | B148: 39433294
A149: Microsoft | B149: 25644330
A150: Digital Realty | B150: 23673863
A151: Google | B151: 21893569
A152: QTS Data Centers | B152: 15682300
A153: CyrusOne | B153: 11185291
A154: Equinix | B154: 7258523
A155: Switch Data Centers | B155: 6758683
A156: Centersquare | B156: 5995325

Sheet Data - ISO vs Data Centers
A4: BAL_AUTH_NAME | B4: BAL_AUTH_ABBR | C4: ENERGY DEMAND ISO | D4: DATA CENTERS POWER CAPACITY | E4: DATA CENTER ENERGY COVERAGE
A5: California Independent System Operator | B5: CISO | C5: 32929.167 | D5: 2369.1729 | E5: 0.071947551
A6: Electric Reliability Council of Texas | B6: ERCO | C6: 70928.542 | D6: 4639.3784 | E6: 0.065409189
A7: Midcontinent Independent System Operator | B7: MISO | C7: 88382.667 | D7: 4700.7741 | E7: 0.053186607
A8: New York Independent System Operator | B8: NYIS | C8: 16594.333 | D8: 287.3527 | E8: 0.017316315
A9: PJM Interconnection | B9: PJM | C9: 107546.92 | D9: 18140.567 | E9: 0.16867584
A10: Southwest Power Pool | B10: SWPP | C10: 24419.958 | D10: 1670.0983 | E10: 0.06839071
A11: ISO New England | B11: ISNE | C11: 13149.042 | D11: 227.8655 | E11: 0.017329438
A16: BAL_AUTH_ABBR | B16: Q_SUBREGION_CODE | D16: CISO
A17: MISO | B17: 5 | D17: ERCO
A18: PJM | B18: 19 | D18: SPP
A19: CISO | B19: 3 | D19: MISO
A20: ERCO | B20: 7 | D20: PJM
A21: ISNE | B21: 8 | D21: NYIS
A22: NYIS | B22: 7 | D22: ISNE
A23: SWPP | B23: 9
A24: Grand Total | B24: 58
A26: BAL_AUTH_ABBR | B26: CISO
A28: SUBREGION CODE | B28: SUBREGION NAME | C28: TOTAL DATA CENTERS | D28: ISO/RTO ENERGY DEMAND | E28: DATA CENTER POWER CAPACITY | F28: DATA CENTER ENERGY COVERAGE
A29: PGAE | B29: Pacific Gas and Electric | C29: 106 | D29: 13109.75 | E29: 1295.9584 | F29: 0.098854543
A30: SCE | B30: Southern California Edison - CISO | C30: 66 | D30: 16830.5 | E30: 1046.4699 | F30: 0.062176997
A31: SDGE | B31: San Diego Gas and Electric - CISO | C31: 10 | D31: 2988.9167 | E31: 26.7446 | F31: 0.0089479243
A32: Grand Total | C32: 182 | D32: 32929.167 | E32: 2369.1729 | F32: 0.071947551
A34: BAL_AUTH_ABBR | B34: ERCO
A36: SUBREGION CODE | B36: SUBREGION NAME | C36: TOTAL DATA CENTERS | D36: ISO/RTO ENERGY DEMAND | E36: DATA CENTER POWER CAPACITY | F36: DATA CENTER ENERGY COVERAGE
A37: COAS | B37: ERCO - Coast | C37: 28 | D37: 18370.708 | E37: 438.0347 | F37: 0.023844192
A38: EAST | B38: ERCO - East | C38: 2 | D38: 2397.6667 | E38: 8.33045 | F38: 0.0034743987
A39: FWES | B39: ERCO - Far West | C39: 7 | D39: 7811.3333 | E39: 374.9927 | F39: 0.048006235
A40: NCEN | B40: ERCO - North Central | C40: 101 | D40: 22414.5 | E40: 2128.0661 | F40: 0.094941493
A41: SCEN | B41: ERCO - South Central | C41: 54 | D41: 11986.875 | E41: 1477.3542 | F41: 0.12324765
A42: SOUT | B42: ERCO - South | C42: 8 | D42: 5743.9583 | E42: 108.6002 | F42: 0.018906857
A43: NRTH | B43: ERCO - North | C43: 3 | D43: 2203.5 | E43: 104 | F43: 0.04719764
A44: Grand Total | C44: 203 | D44: 70928.542 | E44: 4639.3784 | F44: 0.065409189
A46: BAL_AUTH_ABBR | B46: SWPP
A48: SUBREGION CODE | B48: SUBREGION NAME | C48: TOTAL DATA CENTERS | D48: ISO/RTO ENERGY DEMAND | E48: DATA CENTER POWER CAPACITY | F48: DATA CENTER ENERGY COVERAGE
A49: GRDA | B49: Grand River Dam Authority - SWPP | C49: 11 | D49: 1443.25 | E49: 507.605 | F49: 0.35170968
A50: INDN | B50: Independence Power - SWPP | C50: 8 | D50: 172.04167 | E50: 62.64575 | F50: 0.36413127
A51: LES | B51: Lincoln Electric System - SWPP | C51: 3 | D51: 681.79167 | E51: 97 | F51: 0.1422722
A52: MPS | B52: KCP&L Greater Missouri Operations - SWPP | C52: 2 | D52: 1457.75 | E52: 4.4621 | F52: 0.0030609501
A53: OKGE | B53: Oklahoma Gas and Electric Co. - SWPP | C53: 11 | D53: 6403.5417 | E53: 33.16225 | F53: 0.0051787357
A54: OPPD | B54: Omaha Public Power District - SWPP | C54: 24 | D54: 2745.875 | E54: 905.9635 | F54: 0.32993618
A55: SPRM | B55: City of Springfield - SWPP | C55: 1 | D55: 573.91667 | E55: 6 | F55: 0.010454479
A56: SPS | B56: Southwestern Public Service Company - SWPP | C56: 2 | D56: 5810.4167 | E56: 14.9579 | F56: 0.0025743248
A57: WR | B57: Westar Energy - SWPP | C57: 8 | D57: 5131.375 | E57: 38.3018 | F57: 0.0074642372
A58: Grand Total | C58: 70 | D58: 24419.958 | E58: 1670.0983 | F58: 0.06839071
A60: BAL_AUTH_ABBR | B60: MISO
A62: SUBREGION CODE | B62: SUBREGION NAME | C62: TOTAL DATA CENTERS | D62: ISO/RTO ENERGY DEMAND | E62: DATA CENTER POWER CAPACITY | F62: DATA CENTER ENERGY COVERAGE
A63: 0001 | B63: Zone 1 - MISO | C63: 32 | D63: 14687.75 | E63: 332.6843 | F63: 0.02265046
A64: 0006 | B64: Zone 6 - MISO | C64: 31 | D64: 11591.875 | E64: 965.29605 | F64: 0.083273504
A65: 0027 | B65: Zones 2 and 7 - MISO | C65: 47 | D65: 21713.125 | E65: 588.0715 | F65: 0.027083688
A66: 0035 | B66: Zones 3 and 5 - MISO | C66: 76 | D66: 13138.167 | E66: 2433.9226 | F66: 0.18525588
A67: 8910 | B67: Zones 8, 9 and 10 - MISO | C67: 22 | D67: 27251.75 | E67: 380.7997 | F67: 0.013973404
A68: Grand Total | C68: 208 | D68: 88382.667 | E68: 4700.7741 | F68: 0.053186607
A70: BAL_AUTH_ABBR | B70: PJM
A72: SUBREGION CODE | B72: SUBREGION NAME | C72: TOTAL DATA CENTERS | D72: ISO/RTO ENERGY DEMAND | E72: DATA CENTER POWER CAPACITY | F72: DATA CENTER ENERGY COVERAGE
A73: AE | B73: Atlantic Electric zone - PJM | C73: 1 | D73: 1554.5417 | E73: 50 | F73: 0.032163821
A74: AEP | B74: American Electric Power zone - PJM | C74: 81 | D74: 18996 | E74: 3094.1463 | F74: 0.1628841
A75: AP | B75: Allegheny Power zone - PJM | C75: 4 | D75: 6302.4167 | E75: 22 | F75: 0.0034907245
A76: ATSI | B76: American Transmission Systems, Inc. zone - PJM | C76: 10 | D76: 9307.2917 | E76: 21.11825 | F76: 0.0022690006
A77: BC | B77: Baltimore Gas null zone - PJM | C77: 11 | D77: 4094.75 | E77: 43.2071 | F77: 0.010551829
A78: CE | B78: Commonwealth Edison zone - PJM | C78: 78 | D78: 12643.667 | E78: 1715.3629 | F78: 0.13566974
A79: DAY | B79: Dayton Power null zone - PJM | C79: 13 | D79: 2353.75 | E79: 572.53 | F79: 0.24324164
A80: DEOK | B80: Duke Energy Ohio/Kentucky zone - PJM | C80: 15 | D80: 3543.7083 | E80: 69.68945 | F80: 0.019665684
A81: DOM | B81: Dominion Virginia Power zone - PJM | C81: 332 | D81: 18413.125 | E81: 11603.472 | F81: 0.63017397
A82: DPL | B82: Delmarva Power null zone - PJM | C82: 6 | D82: 2428.6667 | E82: 17.4699 | F82: 0.0071932061
A83: DUQ | B83: Duquesne Lighting Company zone - PJM | C83: 12 | D83: 1737.5 | E83: 25.7066 | F83: 0.014795165
A84: EKPC | B84: East Kentucky Power Cooperative zone - PJM | C84: 9 | D84: 1940 | E84: 19.76295 | F84: 0.010187088
... A91: RECO | B91: Rockland Electric (East) zone - PJM | C91: 10 | D91: 203.83333 | E91: 104.8881 | F91: 0.51457776
A92: Grand Total | C92: 650 | D92: 107546.92 | E92: 18140.567 | F92: 0.16867584
A93: BAL_AUTH_ABBR | B93: NYIS
A95: SUBREGION CODE | B95: SUBREGION NAME | C95: TOTAL DATA CENTERS | D95: ISO/RTO ENERGY DEMAND | E95: DATA CENTER POWER CAPACITY | F95: DATA CENTER ENERGY COVERAGE
A96: ZONA | B96: West - NYIS | C96: 8 | D96: 1783.0833 | E96: 80.4266 | F96: 0.045105351
A97: ZONB | B97: Genesee - NYIS | C97: 3 | D97: 1175.0417 | E97: 2.9164 | F97: 0.0024819545
A98: ZONF | B98: Capital - NYIS | C98: 11 | D98: 1441.7083 | E98: 13.5962 | F98: 0.0094306176
A99: ZONG | B99: Hudson Valley - NYIS | C99: 1 | D99: 1223.375 | E99: 10 | F99: 0.0081741085
A100: ZONH & ZONI | B100: Millwood & Dunwoodie - NYIS | C100: 4 | D100: 1089.5417 | E100: 33.2112 | F100: 0.030481808
A101: ZONJ | B101: New York City - NYIS | C101: 16 | D101: 6954.0833 | E101: 141.2023 | F101: 0.020304948
A102: ZONK | B102: Long Island - NYIS | C102: 1 | D102: 2927.5 | E102: 6 | F102: 0.0020495303
A103: Grand Total | C103: 44 | D103: 16594.333 | E103: 287.3527 | F103: 0.017316315
A105: BAL_AUTH_ABBR | B105: ISNE
A107: SUBREGION CODE | B107: SUBREGION NAME | C107: TOTAL DATA CENTERS | D107: ISO/RTO ENERGY DEMAND | E107: DATA CENTER POWER CAPACITY | F107: DATA CENTER ENERGY COVERAGE
A108: 4001 | B108: ISNE - Maine | C108: 4 | D108: 1130.9167 | E108: 5 | F108: 0.0044211922
A109: 4002 | B109: ISNE - New Hampshire | C109: 6 | D109: 1298.5417 | E109: 2.6314 | F109: 0.0020264271
A110: 4003 | B110: ISNE - Vermont | C110: 1 | D110: 449.83333 | F110: 0
A111: 4004 | B111: ISNE - Connecticut | C111: 7 | D111: 3061.6667 | E111: 53.5032 | F111: 0.017475188
A112: 4005 | B112: ISNE - Rhode Island | C112: 3 | D112: 937.08333 | E112: 2.25 | F112: 0.0024010671
A113: 4006 | B113: ISNE - Southeast Mass. | C113: 3 | D113: 1708.9583 | E113: 40 | F113: 0.023406071
A114: 4007 | B114: ISNE - Western/Central Mass. | C114: 4 | D114: 1748.7917 | E114: 21.73705 | F114: 0.012429754
A115: 4008 | B115: ISNE - Northeast Mass. | C115: 16 | D115: 2813.25 | E115: 102.74385 | F115: 0.036521408
A116: Grand Total | C116: 44 | D116: 13149.042 | E116: 227.8655 | F116: 0.017329438

Sheet US Overview Dashboard
B7: KPIs | AA7: US Data Center developments, August 2026 | AT7: Data Centers Facilities across the US | BL7: US States Overview | CF7: Data Centers across ISOs/RTOs
B9: Main indicators about US Data Centers | AA9: ` | AT9: Distribution of the Data Center Facilities across the US based on the latest snapshot. | BL9: Top 10 US States based on their Data Center's inventory, facility size and energy consumption. | CF9: Data Center Power Distribution by ISO/RTO, Energy and Coverage
G11: ='Data - Main KPIs'!$C$223 -> 3905 | I11: Facilities | N11: ='Data - Main KPIs'!$D$223 -> 357584.84 | P11: GW | U11: ='Data - Main KPIs'!$F$223 -> 700591051 | W11: M SqFt
I12: ='Data - Main KPIs'!$D$462 -> 0.075461305 | P12: ='Data - Main KPIs'!$E$462 -> 0.13118712 | W12: ='Data - Main KPIs'!$F$462 -> 0.068292149
I13: vs previous 30 days | P13: vs previous 30 days | W13: vs previous 30 days
G16: ='Data - Main KPIs'!$C$227 -> 630 | I16: Facilities | N16: ='Data - Main KPIs'!$D$227 -> 33493.113 | P16: GW | U16: ='Data - Main KPIs'!$F$227 -> 126567351 | W16: M SqFt
G20: ='Data - Main KPIs'!$C$225 -> 807 | I20: Facilities | N20: ='Data - Main KPIs'!$D$225 -> 68103.116 | P20: GW | U20: ='Data - Main KPIs'!$F$225 -> 218578023 | W20: M SqFt
I21: ='Data - Main KPIs'!$D$464 -> 0.053524804 | P21: ='Data - Main KPIs'!$E$464 -> 0.087041195 | W21: ='Data - Main KPIs'!$F$464 -> 0.062491201
I22: vs previous 30 days | P22: vs previous 30 days | W22: vs previous 30 days
G25: ='Data - Main KPIs'!$C$226 -> 92 | I25: Facilities | N25: ='Data - Main KPIs'!$D$226 -> 8901.6833 | P25: GW | U25: ='Data - Main KPIs'!$F$226 -> 19160437 | W25: M SqFt
G29: ='Data - Main KPIs'!$C$224 -> 7 | I29: Facilities | N29: ='Data - Main KPIs'!$D$224 -> 390.9975 | P29: GW | U29: ='Data - Main KPIs'!$F$224 -> 530800 | W29: M SqFt
G33: ='Data - Main KPIs'!$C$222 -> 2050 | I33: Facilities | N33: ='Data - Main KPIs'!$D$222 -> 50265.133 | P33: GW | U33: ='Data - Main KPIs'!$F$222 -> 306666979 | W33: M SqFt
I34: ='Data - Main KPIs'!$D$461 -> 0.011846002 | P34: ='Data - Main KPIs'!$E$461 -> 0.024711044 | W34: ='Data - Main KPIs'!$F$461 -> 0.0095418396
I35: vs previous 30 days | P35: vs previous 30 days | W35: vs previous 30 days
B37: ="Latest Update: 2026-08-01" -> Latest Update: 2026-08-01
B39: Evolution of Data Centers Facilities
B41: What is the influence in the latest from new data centers projects announced and under construction
CF57: Data Centers across ISOs/RTOs Subregions (Load Zones)
CF58: Data Center Power Distribution by ISO/RTO Load Zones, Energy and Coverage
CF64: SUBREGION CODE | CG64: SUBREGION NAME | CH64: TOTAL DATA CENTERS | CI64: ISO/RTO ENERGY DEMAND | CJ64: DATA CENTER POWER CAPACITY | CK64: DATA CENTER ENERGY COVERAGE | CN64: SUBREGION CODE | CO64: SUBREGION NAME | CP64: TOTAL DATA CENTERS | CQ64: ISO/RTO ENERGY DEMAND | CR64: DATA CENTER POWER CAPACITY | CS64: DATA CENTER ENERGY COVERAGE
CF65: ='Data - ISO vs Data Centers'!A29 -> PGAE | CG65: ='Data - ISO vs Data Centers'!B29 -> Pacific Gas and Electric | CH65: ='Data - ISO vs Data Centers'!C29 -> 106 | CI65: ='Data - ISO vs Data Centers'!D29 -> 13109.75 | CJ65: ='Data - ISO vs Data Centers'!E29 -> 1295.9584 | CK65: ='Data - ISO vs Data Centers'!F29 -> 0.098854543 | CN65: ='Data - ISO vs Data Centers'!A40 -> NCEN | CO65: ='Data - ISO vs Data Centers'!B40 -> ERCO - North Central | CP65: ='Data - ISO vs Data Centers'!C40 -> 101 | CQ65: ='Data - ISO vs Data Centers'!D40 -> 22414.5 | CR65: ='Data - ISO vs Data Centers'!E40 -> 2128.0661 | CS65: ='Data - ISO vs Data Centers'!F40 -> 0.094941493
B66: Evolution of U.S. Data Center Development Momentum | CF66: ='Data - ISO vs Data Centers'!A30 -> SCE | CG66: ='Data - ISO vs Data Centers'!B30 -> Southern California Edison - CISO | CH66: ='Data - ISO vs Data Centers'!C30 -> 66 | CI66: ='Data - ISO vs Data Centers'!D30 -> 16830.5 | CJ66: ='Data - ISO vs Data Centers'!E30 -> 1046.4699 | CK66: ='Data - ISO vs Data Centers'!F30 -> 0.062176997 | CN66: ='Data - ISO vs Data Centers'!A41 -> SCEN | CO66: ='Data - ISO vs Data Centers'!B41 -> ERCO - South Central | CP66: ='Data - ISO vs Data Centers'!C41 -> 54 | CQ66: ='Data - ISO vs Data Centers'!D41 -> 11986.875 | CR66: ='Data - ISO vs Data Centers'!E41 -> 1477.3542 | CS66: ='Data - ISO vs Data Centers'!F41 -> 0.12324765
CF67: ='Data - ISO vs Data Centers'!A31 -> SDGE | CG67: ='Data - ISO vs Data Centers'!B31 -> San Diego Gas and Electric - CISO | CH67: ='Data - ISO vs Data Centers'!C31 -> 10 | CI67: ='Data - ISO vs Data Centers'!D31 -> 2988.9167 | CJ67: ='Data - ISO vs Data Centers'!E31 -> 26.7446 | CK67: ='Data - ISO vs Data Centers'!F31 -> 0.0089479243 | CN67: ='Data - ISO vs Data Centers'!A37 -> COAS | CO67: ='Data - ISO vs Data Centers'!B37 -> ERCO - Coast | CP67: ='Data - ISO vs Data Centers'!C37 -> 28 | CQ67: ='Data - ISO vs Data Centers'!D37 -> 18370.708 | CR67: ='Data - ISO vs Data Centers'!E37 -> 438.0347 | CS67: ='Data - ISO vs Data Centers'!F37 -> 0.023844192
B68: Monthly trends in constructions and announcements activity by facilities and total power capacity since 2021 | CH68: =SUM(CH65:CH67) -> 182 | CI68: =SUM(CI65:CI67) -> 32929.167 | CJ68: =SUM(CJ65:CJ67) -> 2369.1729 | CK68: =CJ68/CI68 -> 0.071947551 | CN68: ='Data - ISO vs Data Centers'!A43 -> NRTH | CO68: ='Data - ISO vs Data Centers'!B43 -> ERCO - North | CP68: ='Data - ISO vs Data Centers'!C43 -> 3 | CQ68: ='Data - ISO vs Data Centers'!D43 -> 2203.5 | CR68: ='Data - ISO vs Data Centers'!E43 -> 104 | CS68: ='Data - ISO vs Data Centers'!F43 -> 0.04719764
CN69: ='Data - ISO vs Data Centers'!A42 -> SOUT | CO69: ='Data - ISO vs Data Centers'!B42 -> ERCO - South | CP69: ='Data - ISO vs Data Centers'!C42 -> 8 | CQ69: ='Data - ISO vs Data Centers'!D42 -> 5743.9583 | CR69: ='Data - ISO vs Data Centers'!E42 -> 108.6002 | CS69: ='Data - ISO vs Data Centers'!F42 -> 0.018906857
CN70: ='Data - ISO vs Data Centers'!A38 -> EAST | CO70: ='Data - ISO vs Data Centers'!B38 -> ERCO - East | CP70: ='Data - ISO vs Data Centers'!C38 -> 2 | CQ70: ='Data - ISO vs Data Centers'!D38 -> 2397.6667 | CR70: ='Data - ISO vs Data Centers'!E38 -> 8.33045 | CS70: ='Data - ISO vs Data Centers'!F38 -> 0.0034743987
CN71: ='Data - ISO vs Data Centers'!A39 -> FWES | CO71: ='Data - ISO vs Data Centers'!B39 -> ERCO - Far West | CP71: ='Data - ISO vs Data Centers'!C39 -> 7 | CQ71: ='Data - ISO vs Data Centers'!D39 -> 7811.3333 | CR71: ='Data - ISO vs Data Centers'!E39 -> 374.9927 | CS71: ='Data - ISO vs Data Centers'!F39 -> 0.048006235
CP72: =SUM(CP65:CP71) -> 203 | CQ72: =SUM(CQ65:CQ71) -> 70928.542 | CR72: =SUM(CR65:CR71) -> 4639.3784 | CS72: =CR72/CQ72 -> 0.065409189
BL76: Data Center's Provider Overview (Self-Built)
BL78: Top 10 provider based on their Data Center's inventory, facility size and energy consumption.
CF79: SUBREGION CODE | CG79: SUBREGION NAME | CH79: TOTAL DATA CENTERS | CI79: ISO/RTO ENERGY DEMAND | CJ79: DATA CENTER POWER CAPACITY | CK79: DATA CENTER ENERGY COVERAGE | CN79: SUBREGION CODE | CO79: SUBREGION NAME | CP79: TOTAL DATA CENTERS | CQ79: ISO/RTO ENERGY DEMAND | CR79: DATA CENTER POWER CAPACITY | CS79: DATA CENTER ENERGY COVERAGE
CF80: ='Data - ISO vs Data Centers'!A54 -> OPPD | CG80: ='Data - ISO vs Data Centers'!B54 -> Omaha Public Power District - SWPP | CH80: ='Data - ISO vs Data Centers'!C54 -> 24 | CI80: ='Data - ISO vs Data Centers'!D54 -> 2745.875 | CJ80: ='Data - ISO vs Data Centers'!E54 -> 905.9635 | CK80: ='Data - ISO vs Data Centers'!F54 -> 0.32993618 | CN80: ='Data - ISO vs Data Centers'!A66 -> 0035 | CO80: ='Data - ISO vs Data Centers'!B66 -> Zones 3 and 5 - MISO | CP80: ='Data - ISO vs Data Centers'!C66 -> 76 | CQ80: ='Data - ISO vs Data Centers'!D66 -> 13138.167 | CR80: ='Data - ISO vs Data Centers'!E66 -> 2433.9226 | CS80: ='Data - ISO vs Data Centers'!F66 -> 0.18525588
CF81: ='Data - ISO vs Data Centers'!A49 -> GRDA | CG81: ='Data - ISO vs Data Centers'!B49 -> Grand River Dam Authority - SWPP | CH81: ='Data - ISO vs Data Centers'!C49 -> 11 | CI81: ='Data - ISO vs Data Centers'!D49 -> 1443.25 | CJ81: ='Data - ISO vs Data Centers'!E49 -> 507.605 | CK81: ='Data - ISO vs Data Centers'!F49 -> 0.35170968 | CN81: ='Data - ISO vs Data Centers'!A65 -> 0027 | CO81: ='Data - ISO vs Data Centers'!B65 -> Zones 2 and 7 - MISO | CP81: ='Data - ISO vs Data Centers'!C65 -> 47 | CQ81: ='Data - ISO vs Data Centers'!D65 -> 21713.125 | CR81: ='Data - ISO vs Data Centers'!E65 -> 588.0715 | CS81: ='Data - ISO vs Data Centers'!F65 -> 0.027083688
CF82: ='Data - ISO vs Data Centers'!A57 -> WR | CG82: ='Data - ISO vs Data Centers'!B57 -> Westar Energy - SWPP | CH82: ='Data - ISO vs Data Centers'!C57 -> 8 | CI82: ='Data - ISO vs Data Centers'!D57 -> 5131.375 | CJ82: ='Data - ISO vs Data Centers'!E57 -> 38.3018 | CK82: ='Data - ISO vs Data Centers'!F57 -> 0.0074642372 | CN82: ='Data - ISO vs Data Centers'!A63 -> 0001 | CO82: ='Data - ISO vs Data Centers'!B63 -> Zone 1 - MISO | CP82: ='Data - ISO vs Data Centers'!C63 -> 32 | CQ82: ='Data - ISO vs Data Centers'!D63 -> 14687.75 | CR82: ='Data - ISO vs Data Centers'!E63 -> 332.6843 | CS82: ='Data - ISO vs Data Centers'!F63 -> 0.02265046
CF83: ='Data - ISO vs Data Centers'!A53 -> OKGE | CG83: ='Data - ISO vs Data Centers'!B53 -> Oklahoma Gas and Electric Co. - SWPP | CH83: ='Data - ISO vs Data Centers'!C53 -> 11 | CI83: ='Data - ISO vs Data Centers'!D53 -> 6403.5417 | CJ83: ='Data - ISO vs Data Centers'!E53 -> 33.16225 | CK83: ='Data - ISO vs Data Centers'!F53 -> 0.0051787357 | CN83: ='Data - ISO vs Data Centers'!A67 -> 8910 | CO83: ='Data - ISO vs Data Centers'!B67 -> Zones 8, 9 and 10 - MISO | CP83: ='Data - ISO vs Data Centers'!C67 -> 22 | CQ83: ='Data - ISO vs Data Centers'!D67 -> 27251.75 | CR83: ='Data - ISO vs Data Centers'!E67 -> 380.7997 | CS83: ='Data - ISO vs Data Centers'!F67 -> 0.013973404
CF84: ='Data - ISO vs Data Centers'!A50 -> INDN | CG84: ='Data - ISO vs Data Centers'!B50 -> Independence Power - SWPP | CH84: ='Data - ISO vs Data Centers'!C50 -> 8 | CI84: ='Data - ISO vs Data Centers'!D50 -> 172.04167 | CJ84: ='Data - ISO vs Data Centers'!E50 -> 62.64575 | CK84: ='Data - ISO vs Data Centers'!F50 -> 0.36413127 | CN84: ='Data - ISO vs Data Centers'!A64 -> 0006 | CO84: ='Data - ISO vs Data Centers'!B64 -> Zone 6 - MISO | CP84: ='Data - ISO vs Data Centers'!C64 -> 31 | CQ84: ='Data - ISO vs Data Centers'!D64 -> 11591.875 | CR84: ='Data - ISO vs Data Centers'!E64 -> 965.29605 | CS84: ='Data - ISO vs Data Centers'!F64 -> 0.083273504
CF85: ='Data - ISO vs Data Centers'!A56 -> SPS | CG85: ='Data - ISO vs Data Centers'!B56 -> Southwestern Public Service Company - SWPP | CH85: ='Data - ISO vs Data Centers'!C56 -> 2 | CI85: ='Data - ISO vs Data Centers'!D56 -> 5810.4167 | CJ85: ='Data - ISO vs Data Centers'!E56 -> 14.9579 | CK85: ='Data - ISO vs Data Centers'!F56 -> 0.0025743248 | CP85: =SUM(CP80:CP84) -> 208 | CQ85: =SUM(CQ80:CQ84) -> 88382.667 | CR85: =SUM(CR80:CR84) -> 4700.7741 | CS85: =CR85/CQ85 -> 0.053186607
CF86: ='Data - ISO vs Data Centers'!A55 -> SPRM | CG86: ='Data - ISO vs Data Centers'!B55 -> City of Springfield - SWPP | CH86: ='Data - ISO vs Data Centers'!C55 -> 1 | CI86: ='Data - ISO vs Data Centers'!D55 -> 573.91667 | CJ86: ='Data - ISO vs Data Centers'!E55 -> 6 | CK86: ='Data - ISO vs Data Centers'!F55 -> 0.010454479
CF87: ='Data - ISO vs Data Centers'!A52 -> MPS | CG87: ='Data - ISO vs Data Centers'!B52 -> KCP&L Greater Missouri Operations - SWPP | CH87: ='Data - ISO vs Data Centers'!C52 -> 2 | CI87: ='Data - ISO vs Data Centers'!D52 -> 1457.75 | CJ87: ='Data - ISO vs Data Centers'!E52 -> 4.4621 | CK87: ='Data - ISO vs Data Centers'!F52 -> 0.0030609501
CF88: ='Data - ISO vs Data Centers'!A51 -> LES | CG88: ='Data - ISO vs Data Centers'!B51 -> Lincoln Electric System - SWPP | CH88: ='Data - ISO vs Data Centers'!C51 -> 3 | CI88: ='Data - ISO vs Data Centers'!D51 -> 681.79167 | CJ88: ='Data - ISO vs Data Centers'!E51 -> 97 | CK88: ='Data - ISO vs Data Centers'!F51 -> 0.1422722
CH89: =SUM(CH80:CH88) -> 70 | CI89: =SUM(CI80:CI88) -> 24419.958 | CJ89: =SUM(CJ80:CJ88) -> 1670.0983 | CK89: =CJ89/CI89 -> 0.06839071
CF95: SUBREGION CODE | CG95: SUBREGION NAME | CH95: TOTAL DATA CENTERS | CI95: ISO/RTO ENERGY DEMAND | CJ95: DATA CENTER POWER CAPACITY | CK95: DATA CENTER ENERGY COVERAGE | CN95: SUBREGION CODE | CO95: SUBREGION NAME | CP95: TOTAL DATA CENTERS | CQ95: ISO/RTO ENERGY DEMAND | CR95: DATA CENTER POWER CAPACITY | CS95: DATA CENTER ENERGY COVERAGE
CF96: ='Data - ISO vs Data Centers'!A80 -> DEOK | CG96: ='Data - ISO vs Data Centers'!B80 -> Duke Energy Ohio/Kentucky zone - PJM | CH96: ='Data - ISO vs Data Centers'!C80 -> 15 | CI96: ='Data - ISO vs Data Centers'!D80 -> 3543.7083 | CJ96: ='Data - ISO vs Data Centers'!E80 -> 69.68945 | CK96: ='Data - ISO vs Data Centers'!F80 -> 0.019665684 | CN96: ='Data - ISO vs Data Centers'!A101 -> ZONJ | CO96: ='Data - ISO vs Data Centers'!B101 -> New York City - NYIS | CP96: ='Data - ISO vs Data Centers'!C101 -> 16 | CQ96: ='Data - ISO vs Data Centers'!D101 -> 6954.0833 | CR96: ='Data - ISO vs Data Centers'!E101 -> 141.2023 | CS96: ='Data - ISO vs Data Centers'!F101 -> 0.020304948
CF97: ='Data - ISO vs Data Centers'!A77 -> BC | CG97: ='Data - ISO vs Data Centers'!B77 -> Baltimore Gas null zone - PJM | CH97: ='Data - ISO vs Data Centers'!C77 -> 11 | CI97: ='Data - ISO vs Data Centers'!D77 -> 4094.75 | CJ97: ='Data - ISO vs Data Centers'!E77 -> 43.2071 | CK97: ='Data - ISO vs Data Centers'!F77 -> 0.010551829 | CN97: ='Data - ISO vs Data Centers'!A100 -> ZONH & ZONI | CO97: ='Data - ISO vs Data Centers'!B100 -> Millwood & Dunwoodie - NYIS | CP97: ='Data - ISO vs Data Centers'!C100 -> 4 | CQ97: ='Data - ISO vs Data Centers'!D100 -> 1089.5417 | CR97: ='Data - ISO vs Data Centers'!E100 -> 33.2112 | CS97: ='Data - ISO vs Data Centers'!F100 -> 0.030481808
CF98: ='Data - ISO vs Data Centers'!A73 -> AE | CG98: ='Data - ISO vs Data Centers'!B73 -> Atlantic Electric zone - PJM | CH98: ='Data - ISO vs Data Centers'!C73 -> 1 | CI98: ='Data - ISO vs Data Centers'!D73 -> 1554.5417 | CJ98: ='Data - ISO vs Data Centers'!E73 -> 50 | CK98: ='Data - ISO vs Data Centers'!F73 -> 0.032163821 | CN98: ='Data - ISO vs Data Centers'!A98 -> ZONF | CO98: ='Data - ISO vs Data Centers'!B98 -> Capital - NYIS | CP98: ='Data - ISO vs Data Centers'!C98 -> 11 | CQ98: ='Data - ISO vs Data Centers'!D98 -> 1441.7083 | CR98: ='Data - ISO vs Data Centers'!E98 -> 13.5962 | CS98: ='Data - ISO vs Data Centers'!F98 -> 0.0094306176
CF99: ='Data - ISO vs Data Centers'!A87 -> PEP | CG99: ='Data - ISO vs Data Centers'!B87 -> Potomac Electric Power zone - PJM | CH99: ='Data - ISO vs Data Centers'!C87 -> 6 | CI99: ='Data - ISO vs Data Centers'!D87 -> 3799.9583 | CJ99: ='Data - ISO vs Data Centers'!E87 -> 18.747 | CK99: ='Data - ISO vs Data Centers'!F87 -> 0.0049334751 | CN99: ='Data - ISO vs Data Centers'!A99 -> ZONG | CO99: ='Data - ISO vs Data Centers'!B99 -> Hudson Valley - NYIS | CP99: ='Data - ISO vs Data Centers'!C99 -> 1 | CQ99: ='Data - ISO vs Data Centers'!D99 -> 1223.375 | CR99: ='Data - ISO vs Data Centers'!E99 -> 10 | CS99: ='Data - ISO vs Data Centers'!F99 -> 0.0081741085
CF100: ='Data - ISO vs Data Centers'!A78 -> CE | CG100: ='Data - ISO vs Data Centers'!B78 -> Commonwealth Edison zone - PJM | CH100: ='Data - ISO vs Data Centers'!C78 -> 78 | CI100: ='Data - ISO vs Data Centers'!D78 -> 12643.667 | CJ100: ='Data - ISO vs Data Centers'!E78 -> 1715.3629 | CK100: ='Data - ISO vs Data Centers'!F78 -> 0.13566974 | CN100: ='Data - ISO vs Data Centers'!A96 -> ZONA | CO100: ='Data - ISO vs Data Centers'!B96 -> West - NYIS | CP100: ='Data - ISO vs Data Centers'!C96 -> 8 | CQ100: ='Data - ISO vs Data Centers'!D96 -> 1783.0833 | CR100: ='Data - ISO vs Data Centers'!E96 -> 80.4266 | CS100: ='Data - ISO vs Data Centers'!F96 -> 0.045105351
B101: Facility Size vs Power Capacity by Project Stage | CF101: ='Data - ISO vs Data Centers'!A88 -> PL | CG101: ='Data - ISO vs Data Centers'!B88 -> Pennsylvania Power zone - PJM | CH101: ='Data - ISO vs Data Centers'!C88 -> 2 | CI101: ='Data - ISO vs Data Centers'!D88 -> 5119.4583 | CJ101: ='Data - ISO vs Data Centers'!E88 -> 100.5 | CK101: ='Data - ISO vs Data Centers'!F88 -> 0.019630983 | CN101: ='Data - ISO vs Data Centers'!A102 -> ZONK | CO101: ='Data - ISO vs Data Centers'!B102 -> Long Island - NYIS | CP101: ='Data - ISO vs Data Centers'!C102 -> 1 | CQ101: ='Data - ISO vs Data Centers'!D102 -> 2927.5 | CR101: ='Data - ISO vs Data Centers'!E102 -> 6 | CS101: ='Data - ISO vs Data Centers'!F102 -> 0.0020495303
B102: Understanding the relationship between the energy consumption and the size of the facility. | CF102: ='Data - ISO vs Data Centers'!A79 -> DAY | CG102: ='Data - ISO vs Data Centers'!B79 -> Dayton Power null zone - PJM | CH102: ='Data - ISO vs Data Centers'!C79 -> 13 | CI102: ='Data - ISO vs Data Centers'!D79 -> 2353.75 | CJ102: ='Data - ISO vs Data Centers'!E79 -> 572.53 | CK102: ='Data - ISO vs Data Centers'!F79 -> 0.24324164 | CN102: ='Data - ISO vs Data Centers'!A97 -> ZONB | CO102: ='Data - ISO vs Data Centers'!B97 -> Genesee - NYIS | CP102: ='Data - ISO vs Data Centers'!C97 -> 3 | CQ102: ='Data - ISO vs Data Centers'!D97 -> 1175.0417 | CR102: ='Data - ISO vs Data Centers'!E97 -> 2.9164 | CS102: ='Data - ISO vs Data Centers'!F97 -> 0.0024819545
CF103: ='Data - ISO vs Data Centers'!A85 -> ME | CG103: ='Data - ISO vs Data Centers'!B85 -> Metropolitan Edison zone - PJM | CH103: ='Data - ISO vs Data Centers'!C85 -> 11 | CI103: ='Data - ISO vs Data Centers'!D85 -> 1943 | CJ103: ='Data - ISO vs Data Centers'!E85 -> 60.30065 | CK103: ='Data - ISO vs Data Centers'!F85 -> 0.031034817 | CP103: =SUM(CP96:CP102) -> 44 | CQ103: =SUM(CQ96:CQ102) -> 16594.333 | CR103: =SUM(CR96:CR102) -> 287.3527 | CS103: =CR103/CQ103 -> 0.017316315
CF104: ='Data - ISO vs Data Centers'!A84 -> EKPC | CG104: ='Data - ISO vs Data Centers'!B84 -> East Kentucky Power Cooperative zone - PJM | CH104: ='Data - ISO vs Data Centers'!C84 -> 9 | CI104: ='Data - ISO vs Data Centers'!D84 -> 1940 | CJ104: ='Data - ISO vs Data Centers'!E84 -> 19.76295 | CK104: ='Data - ISO vs Data Centers'!F84 -> 0.010187088
CF105: ='Data - ISO vs Data Centers'!A76 -> ATSI | CG105: ='Data - ISO vs Data Centers'!B76 -> American Transmission Systems, Inc. zone - PJM | CH105: ='Data - ISO vs Data Centers'!C76 -> 10 | CI105: ='Data - ISO vs Data Centers'!D76 -> 9307.2917 | CJ105: ='Data - ISO vs Data Centers'!E76 -> 21.11825 | CK105: ='Data - ISO vs Data Centers'!F76 -> 0.0022690006
CF106: ='Data - ISO vs Data Centers'!A82 -> DPL | CG106: ='Data - ISO vs Data Centers'!B82 -> Delmarva Power null zone - PJM | CH106: ='Data - ISO vs Data Centers'!C82 -> 6 | CI106: ='Data - ISO vs Data Centers'!D82 -> 2428.6667 | CJ106: ='Data - ISO vs Data Centers'!E82 -> 17.4699 | CK106: ='Data - ISO vs Data Centers'!F82 -> 0.0071932061
CF107: ='Data - ISO vs Data Centers'!A74 -> AEP | CG107: ='Data - ISO vs Data Centers'!B74 -> American Electric Power zone - PJM | CH107: ='Data - ISO vs Data Centers'!C74 -> 81 | CI107: ='Data - ISO vs Data Centers'!D74 -> 18996 | CJ107: ='Data - ISO vs Data Centers'!E74 -> 3094.1463 | CK107: ='Data - ISO vs Data Centers'!F74 -> 0.1628841
CF108: ='Data - ISO vs Data Centers'!A75 -> AP | CG108: ='Data - ISO vs Data Centers'!B75 -> Allegheny Power zone - PJM | CH108: ='Data - ISO vs Data Centers'!C75 -> 4 | CI108: ='Data - ISO vs Data Centers'!D75 -> 6302.4167 | CJ108: ='Data - ISO vs Data Centers'!E75 -> 22 | CK108: ='Data - ISO vs Data Centers'!F75 -> 0.0034907245
CF109: ='Data - ISO vs Data Centers'!A83 -> DUQ | CG109: ='Data - ISO vs Data Centers'!B83 -> Duquesne Lighting Company zone - PJM | CH109: ='Data - ISO vs Data Centers'!C83 -> 12 | CI109: ='Data - ISO vs Data Centers'!D83 -> 1737.5 | CJ109: ='Data - ISO vs Data Centers'!E83 -> 25.7066 | CK109: ='Data - ISO vs Data Centers'!F83 -> 0.014795165
CF110: ='Data - ISO vs Data Centers'!A81 -> DOM | CG110: ='Data - ISO vs Data Centers'!B81 -> Dominion Virginia Power zone - PJM | CH110: ='Data - ISO vs Data Centers'!C81 -> 332 | CI110: ='Data - ISO vs Data Centers'!D81 -> 18413.125 | CJ110: ='Data - ISO vs Data Centers'!E81 -> 11603.472 | CK110: ='Data - ISO vs Data Centers'!F81 -> 0.63017397
CF111: ='Data - ISO vs Data Centers'!A86 -> PE | CG111: ='Data - ISO vs Data Centers'!B86 -> PECO Energy zone - PJM | CH111: ='Data - ISO vs Data Centers'!C86 -> 10 | CI111: ='Data - ISO vs Data Centers'!D86 -> 5151.0833 | CJ111: ='Data - ISO vs Data Centers'!E86 -> 63.1792 | CK111: ='Data - ISO vs Data Centers'!F86 -> 0.012265226
CH112: =SUM(CH96:CH111) -> 601 | CI112: =SUM(CI96:CI111) -> 99328.917 | CJ112: =SUM(CJ96:CJ111) -> 17497.192 | CK112: =CJ112/CI112 -> 0.17615406
CF118: SUBREGION CODE | CG118: SUBREGION NAME | CH118: TOTAL DATA CENTERS | CI118: ISO/RTO ENERGY DEMAND | CJ118: DATA CENTER POWER CAPACITY | CK118: DATA CENTER ENERGY COVERAGE
CF119: ='Data - ISO vs Data Centers'!A115 -> 4008 | CG119: ='Data - ISO vs Data Centers'!B115 -> ISNE - Northeast Mass. | CH119: ='Data - ISO vs Data Centers'!C115 -> 16 | CI119: ='Data - ISO vs Data Centers'!D115 -> 2813.25 | CJ119: ='Data - ISO vs Data Centers'!E115 -> 102.74385 | CK119: ='Data - ISO vs Data Centers'!F115 -> 0.036521408
CF120: ='Data - ISO vs Data Centers'!A113 -> 4006 | CG120: ='Data - ISO vs Data Centers'!B113 -> ISNE - Southeast Mass. | CH120: ='Data - ISO vs Data Centers'!C113 -> 3 | CI120: ='Data - ISO vs Data Centers'!D113 -> 1708.9583 | CJ120: ='Data - ISO vs Data Centers'!E113 -> 40 | CK120: ='Data - ISO vs Data Centers'!F113 -> 0.023406071
CF121: ='Data - ISO vs Data Centers'!A111 -> 4004 | CG121: ='Data - ISO vs Data Centers'!B111 -> ISNE - Connecticut | CH121: ='Data - ISO vs Data Centers'!C111 -> 7 | CI121: ='Data - ISO vs Data Centers'!D111 -> 3061.6667 | CJ121: ='Data - ISO vs Data Centers'!E111 -> 53.5032 | CK121: ='Data - ISO vs Data Centers'!F111 -> 0.017475188
CF122: ='Data - ISO vs Data Centers'!A114 -> 4007 | CG122: ='Data - ISO vs Data Centers'!B114 -> ISNE - Western/Central Mass. | CH122: ='Data - ISO vs Data Centers'!C114 -> 4 | CI122: ='Data - ISO vs Data Centers'!D114 -> 1748.7917 | CJ122: ='Data - ISO vs Data Centers'!E114 -> 21.73705 | CK122: ='Data - ISO vs Data Centers'!F114 -> 0.012429754
CF123: ='Data - ISO vs Data Centers'!A112 -> 4005 | CG123: ='Data - ISO vs Data Centers'!B112 -> ISNE - Rhode Island | CH123: ='Data - ISO vs Data Centers'!C112 -> 3 | CI123: ='Data - ISO vs Data Centers'!D112 -> 937.08333 | CJ123: ='Data - ISO vs Data Centers'!E112 -> 2.25 | CK123: ='Data - ISO vs Data Centers'!F112 -> 0.0024010671
CF124: ='Data - ISO vs Data Centers'!A109 -> 4002 | CG124: ='Data - ISO vs Data Centers'!B109 -> ISNE - New Hampshire | CH124: ='Data - ISO vs Data Centers'!C109 -> 6 | CI124: ='Data - ISO vs Data Centers'!D109 -> 1298.5417 | CJ124: ='Data - ISO vs Data Centers'!E109 -> 2.6314 | CK124: ='Data - ISO vs Data Centers'!F109 -> 0.0020264271
CF125: ='Data - ISO vs Data Centers'!A108 -> 4001 | CG125: ='Data - ISO vs Data Centers'!B108 -> ISNE - Maine | CH125: ='Data - ISO vs Data Centers'!C108 -> 4 | CI125: ='Data - ISO vs Data Centers'!D108 -> 1130.9167 | CJ125: ='Data - ISO vs Data Centers'!E108 -> 5 | CK125: ='Data - ISO vs Data Centers'!F108 -> 0.0044211922
CF126: ='Data - ISO vs Data Centers'!A110 -> 4003 | CG126: ='Data - ISO vs Data Centers'!B110 -> ISNE - Vermont | CH126: ='Data - ISO vs Data Centers'!C110 -> 1 | CI126: ='Data - ISO vs Data Centers'!D110 -> 449.83333 | CJ126: ='Data - ISO vs Data Centers'!E110 -> 0 | CK126: ='Data - ISO vs Data Centers'!F110 -> 0
CH127: =SUM(CH119:CH126) -> 44 | CI127: =SUM(CI119:CI126) -> 13149.042 | CJ127: =SUM(CJ119:CJ126) -> 227.8655 | CK127: =CJ127/CI127 -> 0.017329438
B148: For additional information visit aterio.io

Sheet Data Sample
A1: ATERIO_DATA_CENTER_UID | B1: DATA_CENTER_BUILDING_NAME | C1: ATERIO_DATA_CENTER_CAMPUS_UID | D1: DATA_CENTER_CAMPUS_NAME | E1: DATA_CENTER_STAGE | F1: FLG_AI_FACILITY | G1: FLG_BTM_ONSITE_POWER_GENERATION | H1: TOT_PROJECT_COST | I1: ATERIO_PROVIDER_UID | J1: PROVIDER_NAME | K1: PROVIDER_URL | L1: PROVIDER_PUBLIC_PRIVATE | M1: PROVIDER_TICKER_NAME | N1: PROVIDER_BLOOMBERG_TICKER_NAME | O1: STOCK_EXCHANGE_PROVIDER_NAME | P1: PROVIDER_BACKED_BY | Q1: CONSTRUCTION_EQUIPMENT_PROVIDER_COMPANIES | R1: PROJECT_FINANCING_COMPANIES | S1: END_USER_COMPANIES | T1: FULL_ADDRESS | U1: ZIP_CODE | V1: COUNTY_FIPS_CODE | W1: COUNTY_NAME | X1: CITY_NAME | Y1: PLACE_FIPS_CODE | Z1: STATE_CODE | AA1: STATE_NAME | AB1: COUNTRY_CODE | AC1: COUNTRY_NAME | AD1: LOCATION_LATITUDE | AE1: LOCATION_LONGITUDE | AF1: SITE_ACREAGE | AG1: TOT_FACILITY_SPACE_SQFT | AH1: TOT_DATACENTER_SPACE_SQFT | AI1: PROV_PUB_TOT_POWER_CAPACITY_MW | AJ1: ATERIO_EST_TOT_POWER_CAPACITY_MW | AK1: ATERIO_EST_TOT_POWER_CAPACITY_MW_LOWER | AL1: ATERIO_EST_TOT_POWER_CAPACITY_MW_UPPER | AM1: SELECTED_POWER_CAPACITY_MW | AN1: CRITICAL_IT_CAPACITY_MW | AO1: YEARLY_PUE | AP1: TOT_NUM_GENERATORS | AQ1: DATA_CENTER_ANNOUNCED_DATE | AR1: DATA_CENTER_CANCELLED_DATE | AS1: DATA_CENTER_PROJECT_WITHDRAWN_DATE | AT1: DATA_CENTER_CONSTRUCTION_START_DATE | AU1: LATEST_SATELLITE_PICTURE_DATE | AV1: PCT_CONSTRUCTION_STATUS | AW1: DATA_CENTER_ACTIVATION_DATE | AX1: ESTIMATED_ACTIVATION_DATE_ATERIO | AY1: ESTIMATED_ACTIVATION_DATE_PUBLIC_SOURCE | AZ1: ESTIMATED_ACTIVATION_DATE_PUBLIC_SOURCE_URL | BA1: ATERIO_ELECTRICAL_UTILITY_UID | BB1: UTILITY_NAME | BC1: UTILITY_CODE | BD1: UTILITY_PUBLIC_PRIVATE | BE1: UTILITY_TICKER_NAME | BF1: UTILITY_BLOOMBERG_TICKER_NAME | BG1: UTILITY_EXCHANGE_PROVIDER_TICKER_NAME | BH1: ATERIO_BAL_AUTH_UID | BI1: BAL_AUTH_ABBR | BJ1: BAL_AUTH_NAME | BK1: ATERIO_BAL_AUTH_SUBREGION_UID | BL1: BAL_AUTH_SUBREGION_CODE | BM1: BAL_AUTH_SUBREGION_NAME | BN1: ATERIO_POWER_GENERATION_PROJECT_UID | BO1: DATASHEET_URL | BP1: MAP_URL | BQ1: PROJECT_PERMIT_URL | BR1: CAPEX_URL | BS1: PROJECT_EXECUTION_LIKELIHOOD | BT1: NOTES | BU1: RECORD_CREATED_DATE | BV1: RECORD_UPDATED_DATE | BW1: UPDATED_AT
A2: 14c3ec08-1803-4368-ac7a-fbd879e635eb | B2: Southfield Data Center NW (DC2) | C2: 15471167-b182-4a84-9204-3befe56d5657 | D2: Southfield, 123NET Campus | E2: Active | I2: f22930d7-d032-4fc9-90dd-ca83628f7994 | J2: 123NET | K2: https://www.123.net | L2: Private | P2: https://graingp.com/ | T2: 24275 Northwestern Hwy, Southfield, MI, USA | U2: 48075 | V2: 26125 | W2: Oakland County | X2: Southfield | Y2: 74900 | Z2: MI | AA2: Michigan | AB2: US | AC2: United States | AD2: 42.467033 | AE2: -83.235 | AG2: 21000 | AH2: 8000 | AI2: 1 | AJ2: 1.06 | AK2: 1.01 | AL2: 1.11 | AM2: 1 | AW2: 39020 | BA2: 26749c83-6e33-400d-b547-24f87a25d36b | BB2: DTE Electric Company | BC2: 5109 | BD2: Public | BE2: DTE | BF2: DTE:US | BG2: NYSE:DTE | BH2: cead66ff-8552-43d5-b723-aeedd7318b2b | BI2: MISO | BJ2: Midcontinent Independent System Operator | BK2: 3733cb81-030b-4603-b6fb-0888ceb4bd68 | BL2: 27 | BM2: Zones 2 and 7 - MISO | BO2: https://www.123.net/data-center-colocation/ | BP2: https://maps.app.goo.gl/5Qw1wJUiGjfo4GHP9 | BU2: 45474 | BV2: 46120 | BW2: 46238
A3: 302036dd-074a-45de-92fb-15bc3540a4c7 | B3: CHIL1 MTC Data Center | E3: Cancelled | I3: cc7c624a-756c-4183-8d7a-f4cc9f13aa97 | J3: 1547 Critical Systems Realty | K3: https://www.1547realty.com | L3: Private | T3: 40 E Garfield Blvd, Chicago, IL, USA | U3: 60615 | V3: 17031 | W3: Cook County | X3: Chicago | Y3: 14000 | Z3: IL | AA3: Illinois | AB3: US | AC3: United States | AD3: 41.794888 | AE3: -87.62457 | AG3: 230000 | AH3: 230000 | AI3: 24 | AJ3: 34.63 | AK3: 33.02 | AL3: 36.31 | AM3: 24 | AR3: 45303 | BA3: 222a249b-639d-4c33-9bba-36724efea762 | BB3: Commonwealth Edison Co | BC3: 4110 | BD3: Private (Part of Exelon Corp) | BE3: EXC | BF3: EXC:US | BG3: NASDAQ:EXC | BH3: 35f051b0-f1ce-470d-81d2-ea5c0d197f3a | BI3: PJM | BJ3: PJM Interconnection | BK3: e84646c2-7438-4a4c-916e-953518bd940a | BL3: CE | BM3: Commonwealth Edison zone - PJM | BO3: https://www.1547realty.com/data-center/chicago-il-chil1/ | BP3: https://maps.app.goo.gl/2KTnfi5z8T6e9XGi8 | BS3: Low | BT3: [2025-02-12 JR] Additional Info: Data Center sqft and capacity updated._x000D_ [2026-01-05 AV] Additional Info: Following the purchase of the building in 2015, no construction activity was observed in the area. In 2024, it was announced that the building would be put up for sale. Status updated to Cancelled. | BU3: 45474 | BV3: 46120 | BW3: 46238
A4: 28ab55b6-0148-4b98-87ad-c0b4d8dd2a05 | B4: ORNY1 Orangeburg Data Center | E4: Active | I4: cc7c624a-756c-4183-8d7a-f4cc9f13aa97 | J4: 1547 Critical Systems Realty | K4: https://www.1547realty.com | L4: Private | T4: 1 Ramland Road South, Orangeburg, NY, USA | U4: 10962 | V4: 36087 | W4: Rockland County | X4: Orangeburg | Y4: 55167 | Z4: NY | AA4: New York | AB4: US | AC4: United States | AD4: 41.03341 | AE4: -73.9708 | AG4: 232000 | AH4: 232000 | AI4: 24 | AJ4: 23.16 | AK4: 22.09 | AL4: 24.29 | AM4: 24 | AW4: 42034 | BA4: 85d629c4-28b0-47db-b275-107564a0a5d6 | BB4: Orange & Rockland Utils Inc | BC4: 14154 | BD4: Private | BH4: ee53ff3c-b180-48a0-b3fb-50539e5f46a0 | BI4: NYIS | BJ4: New York Independent System Operator | BO4: https://www.1547realty.com/data-center/orangeburg-new-york-orny1/ | BP4: https://maps.app.goo.gl/i1zLybhEV7R2aaTp6 | BT4: [2025-02-12 JR] Additional Info: Data Center sqft and capacity updated | BU4: 45474 | BV4: 46120 | BW4: 46238
A5: c5fe22bd-0670-427c-ae03-5674b8e007ef | B5: MIWI1 Wells Building Data Center | E5: Active | I5: cc7c624a-756c-4183-8d7a-f4cc9f13aa97 | J5: 1547 Critical Systems Realty | K5: https://www.1547realty.com | L5: Private | T5: 324 East Wisconsin Avenue, Milwaukee, WI, USA | U5: 53202 | V5: 55079 | W5: Milwaukee County | X5: Milwaukee | Y5: 53000 | Z5: WI | AA5: Wisconsin | AB5: US | AC5: United States | AD5: 43.03904 | AE5: -87.90704 | AG5: 160000 | AH5: 5000 | AI5: 0.5 | AJ5: 0.6 | AK5: 0.57 | AL5: 0.63 | AM5: 0.5 | AW5: 44077 | BA5: 94a63322-5c22-4deb-b119-22fd3e409638 | BB5: Wisconsin Electric Power Co | BC5: 20847 | BD5: Public | BE5: WEC | BF5: WEC:US | BG5: NYSE:WEC | BH5: cead66ff-8552-43d5-b723-aeedd7318b2b | BI5: MISO | BJ5: Midcontinent Independent System Operator | BK5: 3733cb81-030b-4603-b6fb-0888ceb4bd68 | BL5: 27 | BM5: Zones 2 and 7 - MISO | BO5: https://www.1547realty.com/data-center/milwaukee-wi-miwi1/ | BP5: https://maps.app.goo.gl/CYGECo5FQo559uWJA | BT5: [2026-01-09 AV] Additional Info: The facility was already functioning as a carrier‑hotel/data‑center before 2020, but 1547's footprint at the site began with its acquisition and branded deployment in 2020. | BU5: 45474 | BV5: 46120 | BW5: 46238
A6: 18ae0d0f-6185-486c-9d33-77c155f34105 | B6: CH6 Chicago Data Center | E6: Active | I6: 6c053c05-6487-42e6-9ad7-5c5b73168dbd | J6: 365 Data Centers | K6: https://www.365datacenters.com | L6: Private | T6: 427 South LaSalle Street, Chicago, IL, USA | U6: 60605 | V6: 17031 | W6: Cook County | X6: Chicago | Y6: 14000 | Z6: IL | AA6: Illinois | AB6: US | AC6: United States | AD6: 41.876213 | AE6: -87.631454 | AG6: 10000 | AH6: 10000 | AI6: 1 | AJ6: 1.51 | AK6: 1.44 | AL6: 1.58 | AM6: 1 | AW6: 36526 | BA6: 222a249b-639d-4c33-9bba-36724efea762 | BB6: Commonwealth Edison Co | BC6: 4110 | BD6: Private (Part of Exelon Corp) | BE6: EXC | BF6: EXC:US | BG6: NASDAQ:EXC | BH6: 35f051b0-f1ce-470d-81d2-ea5c0d197f3a | BI6: PJM | BJ6: PJM Interconnection | BK6: e84646c2-7438-4a4c-916e-953518bd940a | BL6: CE | BM6: Commonwealth Edison zone - PJM | BO6: https://365datacenters.com/chicago-data-center/ | BP6: https://maps.app.goo.gl/UreXPxboudebAeQZ8 | BU6: 45474 | BV6: 46120 | BW6: 46238
A7: af48ab77-f0ea-4c39-a5f2-d5f913a2ecee | B7: PA1 Philadelphia Data Center | E7: Active | I7: 6c053c05-6487-42e6-9ad7-5c5b73168dbd | J7: 365 Data Centers | K7: https://www.365datacenters.com | L7: Private | T7: 1500 Spring Garden Street, Philadelphia, PA, USA | U7: 19130 | V7: 42101 | W7: Philadelphia County | X7: Philadelphia | Y7: 60000 | Z7: PA | AA7: Pennsylvania | AB7: US | AC7: United States | AD7: 39.962116 | AE7: -75.164055 | AG7: 135100 | AH7: 135100 | AI7: 10 | AJ7: 9.55 | AK7: 9.11 | AL7: 10.01 | AM7: 10 | AW7: 39232 | BA7: 52a226db-b188-418c-89dc-e9ec5727be9c | BB7: PECO Energy Co | BC7: 14940 | BD7: Public | BE7: EXC | BF7: EXC:US | BG7: NASDAQ:EXC | BH7: 35f051b0-f1ce-470d-81d2-ea5c0d197f3a | BI7: PJM | BJ7: PJM Interconnection | BK7: ce983ef3-0d1d-4bd4-ae46-013f5f1d08b9 | BL7: PE | BM7: PECO Energy zone - PJM | BO7: https://365datacenters.com/philadelphia-data-center-2/ | BP7: https://maps.app.goo.gl/QvhwLVEkm1Da9j6P9 | BU7: 45474 | BV7: 46120 | BW7: 46238
A8: 691cc6a7-fd17-4148-89ab-776a6f40e273 | B8: TX1 Richardson Data Center | E8: Active | I8: 6c053c05-6487-42e6-9ad7-5c5b73168dbd | J8: 365 Data Centers | K8: https://www.365datacenters.com | L8: Private | T8: 1001 East Campbell Road, Richardson, TX, USA | U8: 75081 | V8: 48113 | W8: Dallas County | X8: Richardson | Y8: 61796 | Z8: TX | AA8: Texas | AB8: US | AC8: United States | AD8: 32.976135 | AE8: -96.70743 | AG8: 75100 | AH8: 75100 | AI8: 6 | AJ8: 6.54 | AK8: 6.24 | AL8: 6.86 | AM8: 6 | AW8: 37467 | BA8: 1ebbb343-179f-4d9d-a878-d6b03846b4c4 | BB8: City of Garland - (TX) | BC8: 6958 | BD8: Public (Municipality) | BH8: 1fc90153-5419-4455-91f9-cee1dda4ed00 | BI8: ERCO | BJ8: Electric Reliability Council of Texas | BK8: 14cc320b-3a3d-47a9-83a4-e27eff5c1700 | BL8: NCEN | BM8: ERCO - North Central | BO8: https://365datacenters.com/richardson-data-center/ | BP8: https://maps.app.goo.gl/t6xwpcRShHoH4iDj6 | BU8: 45474 | BV8: 46120 | BW8: 46238
A9: dc213783-9242-4152-a4bf-46764dfc5687 | B9: CMH01 Columbus OH Data Center Phase 1 | C9: 9cef7090-d546-11f0-a3aa-3b201b9c9e6f | D9: CMH Columbus OH Data Center Campus | E9: Construction | F9: Y | I9: 254c3d2c-a09a-4b4f-9cb3-2006286f77b3 | J9: 5C Data Centers | K9: https://www.5cdatacenters.com/ | L9: Private | Q9: FirstEnergy | T9: 601 Benjamin Dr, Springfield, OH 45502, USA | U9: 45502 | V9: 39023 | W9: Clark County | X9: Springfield | Y9: 74118 | Z9: OH | AA9: Ohio | AB9: US | AC9: United States | AD9: 39.912987 | AE9: -83.723946 | AF9: 40 | AG9: 320000 | AH9: 320000 | AI9: 100 | AJ9: 42.96 | AK9: 40.97 | AL9: 45.05 | AM9: 100 | AN9: 77 | AQ9: 45462 | AT9: 45658 | AU9: 46145 | AV9: 0.95 | AW9: 46295 | AX9: 46295 | BH9: 35f051b0-f1ce-470d-81d2-ea5c0d197f3a | BI9: PJM | BJ9: PJM Interconnection | BK9: 48653d43-e0c7-46dd-baf2-6b598abf970d | BL9: ATSI | BM9: American Transmission Systems, Inc. zone - PJM | BO9: https://5c.ai/datacenters | BP9: https://maps.app.goo.gl/2gTERUfS4fVEqanM7 | BQ9: https://www.firstenergycorp.com/content/dam/corporate/transmission/Ohio/e-springfield-n-titus-cn.pdf | BS9: High | BT9: [2024-12-19 JR] Latest Satellite: 2024-10-29; Construction Status: Site Preparation; Estimated Active Date By: Aterio; Additional Info: 200MW of power capacity is secured and set for delivery to the site, with the first 100MW scheduled for Q1 2025_x000D_ [2025-12-09 FC] Construction: Roof installation is largely complete with active mechanical and exterior site work visible; generator installation largely completed._x000D_ [2026-03-11 SQ] Construction: Generator installation appears to be complete in the expansion site, there is some minor equipment installation on the original building and the structural connection between both buildings is also complete. Additional Info: 5C aquired a former data center and is planning to renovate it and construct an expansion to reach 200 MW. Activation date updated from 2026-05-30 to the end of Q2 2026. _x000D_ [2026-07-02 DS] Additional Info: Waiting for a new satellite image to confirm activation status._x000D_ [2026-07-07 JR] Construction: All equipment in place, heavy machinery visible on site still; Additional Info: Activation date updated from 2026-07-07 to Q3 2026._x000D_ [2026-07-08 JR] Additional Info: Sales team claimed "yes CMH01 is operational", likely partial activation full ramp-up possible for early Q3 based on construction progress. | BU9: 45614 | BV9: 46211 | BW9: 46238
A10: 5f8b34d4-0ae0-40c3-b9c0-03ad25db79c9 | B10: Perseus Phase I | C10: dee6bd70-dd19-11f0-8ff6-b30471a54151 | D10: Perseus Campus | E10: Announcement | F10: Y | H10: 800000000 | I10: 7014049a-e25f-4eb0-97c4-f4c7ec283b3b | J10: AVAIO Digital | K10: https://avaiodigital.com/ | L10: Private | Q10: PG&E | T10: 2232 Golf Club Rd, Pittsburg, CA, USA | U10: 94565 | V10: 6013 | W10: Contra Costa County | X10: Pittsburg | Y10: 57456 | Z10: CA | AA10: California | AB10: US | AC10: United States | AD10: 38.012894 | AE10: -121.90964 | AF10: 101 | AG10: 745771 | AH10: 745771 | AI10: 99 | AJ10: 67.42 | AK10: 64.29 | AL10: 70.7 | AM10: 99 | AQ10: 45638 | AU10: 46217 | AV10: 0 | AW10: 46568 | AX10: 47026 | AY10: 46568 | AZ10: https://www.avaiodigital.com/updates/avaio-digital-partners-achieves-major-milestone-for-pittsburg-technology-park-perseus-data-center-project | BA10: 625b7686-055b-46e1-a5a4-4e3dcaf631b4 | BB10: Pacific Gas & Electric Co. | BC10: 14328 | BD10: Public | BE10: PCG | BF10: PCG:US | BG10: NYSE:PCG | BH10: 2950a9eb-39ef-4949-96bd-ecefbf7db624 | BI10: CISO | BJ10: California Independent System Operator | BK10: 9bbe5250-047e-4a37-8434-4cda4fceb9e5 | BL10: PGAE | BM10: Pacific Gas and Electric | BO10: https://avaiodigital.com/avaio-digital-partners-achieves-major-milestone-for-pittsburg-technology-park-perseus-data-center-project/, https://www.prnewswire.com/news-releases/avaio-digital-marks-major-milestone-as-cec-approves-99mw-for-bay-area-data-center-project-perseus-302636094.html, https://www.pittsburgca.gov/home/showpublisheddocument/16451/638555442556300000 | BP10: https://maps.app.goo.gl/2rH1ADUVNz9V8iAE7 | BS10: High | BT10: [2025-12-19 FC] Additional Info: Updated co-ordinates, data sheet URL with proposed phased site plan, square footage from 347,740 and added to campus; project could scale up to 500MW delivered in multiple 99MW phases with phase 1 to be delivered by 2027 | BU10: 45643 | BV10: 46230 | BW10: 46238
A11: d60c1367-3801-4cf5-b4ba-992714428f47 | B11: NEO-01 Perkins Township Data Center | E11: Construction | I11: 3d55dfe8-9ebe-42f7-b66f-1d6fc81bf469 | J11: Aligned Data Centers | K11: https://www.aligneddc.com | L11: Private | P11: AI Infrastructure Partnership (AIP), MGX, and BlackRock’s Global Infrastructure Partners (GIP) | T11: 2509 Hayes Ave, Sandusky, OH | U11: 44870 | V11: 39043 | W11: Erie County | X11: Sandusky | Y11: 70380 | Z11: OH | AA11: Ohio | AB11: US | AC11: United States | AD11: 41.43104 | AE11: -82.71716 | AF11: 128 | AG11: 200000 | AH11: 200000 | AI11: 96 | AJ11: 32.5 | AK11: 30.99 | AL11: 34.08 | AM11: 96 | AN11: 72 | AP11: 42 | AT11: 45566 | AU11: 46156 | AV11: 0.9 | AW11: 46295 | AX11: 46295 | BA11: 6c6655b1-8b8e-45b1-bd02-146ed6379690 | BB11: Ohio Edison Co | BC11: 13998 | BD11: Public | BE11: FE | BF11: FE:US | BG11: NYSE:FE | BH11: 35f051b0-f1ce-470d-81d2-ea5c0d197f3a | BI11: PJM | BJ11: PJM Interconnection | BK11: 48653d43-e0c7-46dd-baf2-6b598abf970d | BL11: ATSI | BM11: American Transmission Systems, Inc. zone - PJM | BO11: https://aligneddc.com/ohio/ | BP11: https://maps.app.goo.gl/xHJQhwAU3VvfySt68 | BS11: High | BT11: [2024-12-19 JR] Latest Satellite: 2024-10-18; Construction Status: Site Preparation; Estimated Active Date By: Aterio_x000D_ [2025-08-01 JR] Construction: Shell complete with significant rooftop installations; generator and cooling equipment placement in progress._x000D_ [2025-10-06 DP] Construction: Roof nearly complete; cooling units being installed on west and north sections. Cranes active and surrounding groundwork ongoing._x000D_ [2026-02-02 JR] Construction: Building shell and roof are complete. Generators are partially installed along the perimeter, with multiple units still missing. Cranes remain on-site and active construction is visible, indicating ongoing equipment installation and the project is not yet fully commissioned; Additional Info: Activation date updated from 2026-01-30 to Q2 2026. Possible partial activation, but not full activation as of January 2026._x000D_ [2026-03-16 SQ] Additional Info: Satellite Image pending to confirm construction progress. _x000D_ [2026-05-19 SQ] Construction: The structure and roof of the data center building appear to be complete, with a large array of cooling equipment and generators installed throughout the facility; paving of the grounds is underway, and there is activity in the parking lot, suggesting that partial testing is being conducted in accordance with progress; Additional Info: Activation Date updated from 2026-06-30 to Q3 2026 | BU11: 45600 | BV11: 46202 | BW11: 46238
A12: 1caf3f25-38c7-4d1e-9e29-ac5fc05860d3 | B12: IAD04- Building 1 | C12: ec110aa8-6db5-4a1d-ab69-802992378f4b | D12: Aligned Frederick Campus | E12: Construction | F12: Y | I12: 3d55dfe8-9ebe-42f7-b66f-1d6fc81bf469 | J12: Aligned Data Centers | K12: https://www.aligneddc.com | L12: Private | P12: AI Infrastructure Partnership (AIP), MGX, and BlackRock’s Global Infrastructure Partners (GIP) | Q12: Turner Construction Company | T12: 5601 Manor Woods Road, Frederick, MD | U12: 21703 | V12: 24021 | W12: Frederick County | X12: Frederick | Y12: 30325 | Z12: MD | AA12: Maryland | AB12: US | AC12: United States | AD12: 39.33426 | AE12: -77.47308 | AF12: 75 | AG12: 450000 | AH12: 450000 | AI12: 72 | AJ12: 61.69 | AK12: 58.83 | AL12: 64.69 | AM12: 72 | AN12: 72 | AP12: 42 | AQ12: 45057 | AT12: 45672 | AU12: 46207 | AV12: 0.85 | AW12: 46325 | AX12: 46325 | BA12: cb3fad47-2ad9-4619-95a4-2e146884f783 | BB12: First Electric Coop Corp | BC12: 6342 | BH12: 35f051b0-f1ce-470d-81d2-ea5c0d197f3a | BI12: PJM | BJ12: PJM Interconnection | BK12: 4bb6bca9-55a9-4621-a4c2-dc6c51f58c5e | BL12: AP | BM12: Allegheny Power zone - PJM | BO12: https://aligneddc.com/maryland/, https://mde.maryland.gov/programs/permits/AirManagementPermits/Documents/Public-Review/Alt%20NSPS/AlignedDataCentersAirPermittoConstructApplication.pdf, https://www.datacenterknowledge.com/data-center-site-selection/why-frederick-county-is-important-for-the-nova-data-center-market | BP12: https://maps.app.goo.gl/nNqw33F93EkvcKgy9 | BQ12: https://mde.maryland.gov/programs/permits/AirManagementPermits/Documents/Public-Review/Alt%20NSPS/AlignedDataCentersAirPermittoConstructApplication.pdf, https://www.frederickcountymd.gov/ArchiveCenter/ViewFile/Item/15820 | BS12: High | BT12: [2024-12-19 JR] Latest Satellite: 2024-08-11; Construction Status: No Construction; Estimated Active Date By: Aterio_x000D_ [2024-12-19 JR] Additional Info: Stage Updated to Construction_x000D_ [2025-08-06 JR] Construction: Foundation completed; vertical construction underway._x000D_ [2025-10-09 DP] Construction: Building shell and roof partially completed, with cranes active and ongoing structural assembly. Foundation work and equipment placement visible on surrounding areas, indicating mid-stage development._x000D_ [2026-03-12 DS] Construction: Work underway on the equipment yard. Cooling vents being installed on the roof; Additional Info: Updated number of buildings in the campus from 7 to 4._x000D_ [2026-07-07 SQ] Construction: Vertical construction is now fully complete. The cooling towers have been fully installed, and the installation of the generators is nearing completion. Work on the building's exterior is currently ongoing. | BU12: 45614 | BV12: 46210 | BW12: 46238
A13: 83c7ee62-afb5-4d5f-bedf-b25ca38184fc | B13: AWS Central Expy Data Center | E13: Land Bank | I13: 00a5efa3-8d76-4878-a0d6-f90a60f8b647 | J13: Amazon AWS | K13: https://www.aws.amazon.com/compliance/data-center/data-centers/ | L13: Public | M13: AMZN | N13: AMZN:US | O13: NASDAQ: AMZN | T13: 960 Central Expy, Santa Clara, CA, USA | U13: 95050 | V13: 6085 | W13: Santa Clara County | X13: Santa Clara | Y13: 69084 | Z13: CA | AA13: California | AB13: US | AC13: United States | AD13: 37.372887 | AE13: -121.95424 | AJ13: 39.81 | AK13: 38.76 | AL13: 40.88 | AM13: 39.81 | AU13: 46149 | AV13: 0 | AW13: 46568 | BA13: 625b7686-055b-46e1-a5a4-4e3dcaf631b4 | BB13: Pacific Gas & Electric Co. | BC13: 14328 | BD13: Public | BE13: PCG | BF13: PCG:US | BG13: NYSE:PCG | BH13: 2950a9eb-39ef-4949-96bd-ecefbf7db624 | BI13: CISO | BJ13: California Independent System Operator | BK13: 9bbe5250-047e-4a37-8434-4cda4fceb9e5 | BL13: PGAE | BM13: Pacific Gas and Electric | BO13: https://www.mercurynews.com/2023/03/07/amazon-santa-clara-buy-sell-real-estate-owens-corning-build-tech/ | BP13: https://maps.app.goo.gl/sE1L4CiHG9G2ZRxX9 | BS13: Medium | BT13: [2025-12-19 FC] Additional Info: Updated status from Announcement | BU13: 45616 | BV13: 46219 | BW13: 46238
A14: 3542a6db-986b-4d40-93ac-862194e99e28 | B14: AWS Ezell Drive Data Center | E14: Announcement | I14: 00a5efa3-8d76-4878-a0d6-f90a60f8b647 | J14: Amazon AWS | K14: https://www.aws.amazon.com/compliance/data-center/data-centers/ | L14: Public | M14: AMZN | N14: AMZN:US | O14: NASDAQ: AMZN | T14: 1800-1898 Jo Dr, DeSoto, TX, USA | U14: 75115 | V14: 48113 | W14: Dallas County | X14: Desoto | Z14: TX | AA14: Texas | AB14: US | AC14: United States | AD14: 32.62468 | AE14: -96.86052 | AF14: 9 | AG14: 30000 | AH14: 30000 | AJ14: 7.1 | AK14: 6.91 | AL14: 7.29 | AM14: 7.1 | AQ14: 44819 | AU14: 46212 | AV14: 0 | AW14: 46629 | AY14: 45657 | BA14: 14246342-1edf-4a4e-825c-0bf93f13d201 | BB14: Oncor Electric Delivery Company LLC | BC14: 44372 | BH14: 1fc90153-5419-4455-91f9-cee1dda4ed00 | BI14: ERCO | BJ14: Electric Reliability Council of Texas | BK14: 14cc320b-3a3d-47a9-83a4-e27eff5c1700 | BL14: NCEN | BM14: ERCO - North Central | BO14: https://www.dallasnews.com/business/real-estate/2022/09/13/amazon-plans-new-data-center-in-southern-dallas-county/ | BP14: https://maps.app.goo.gl/VusXq4hV7wzgJJME9 | BQ14: https://www.tdlr.texas.gov/TABS/Search/Project/TABS2023000811 | BS14: Low | BT14: [2024-12-19 JR] Latest Satellite: 2023-11-13; Construction Status: No Construction; Estimated Active Date By: Aterio; Additional Info: Project Delayed_x000D_ [2025-05-27 JR] Construction: No construction activity as of latest satellite imagery. _x000D_ [2025-11-12 JR] Construction: No construction visible; Additional Info: Activation date updated from 2026-08-30_x000D_ [2026-04-08 JH] Construction: No visible construction activity observed on site. | BU14: 45637 | BV14: 46220 | BW14: 46238
A15: ecdeba1b-9e90-42a4-85c1-d34aff607d26 | B15: Amazon AWS IAD - 11200 Thomasson | E15: Active | I15: 00a5efa3-8d76-4878-a0d6-f90a60f8b647 | J15: Amazon AWS | K15: https://www.aws.amazon.com/compliance/data-center/data-centers/ | L15: Public | M15: AMZN | N15: AMZN:US | O15: NASDAQ: AMZN | T15: 11200 Thomasson Barn Road, Manassas, VA, USA | U15: 20109 | V15: 51153 | W15: Prince William County | X15: Manassas | Y15: 48952 | Z15: VA | AA15: Virginia | AB15: US | AC15: United States | AD15: 38.743847 | AE15: -77.53042 | AG15: 149404 | AH15: 149404 | AJ15: 35 | AK15: 34.08 | AL15: 35.94 | AM15: 35 | AN15: 30.43 | AO15: 1.15 | AP15: 16 | AW15: 43905 | BA15: 1f3c7b79-c506-4062-b210-2af9580f0d84 | BB15: City of Manassas - (VA) | BC15: 11560 | BD15: Private | BH15: 35f051b0-f1ce-470d-81d2-ea5c0d197f3a | BI15: PJM | BJ15: PJM Interconnection | BK15: 469a7dc0-fc5e-4f8e-8184-301f28134241 | BL15: DOM | BM15: Dominion Virginia Power zone - PJM | BP15: https://maps.app.goo.gl/6Q26m7kXGpTAEmbq6 | BT15: [2025-02-11JR] Additional Info: Owned by COPT _x000D_ [2025-02-28 JR] Additional Info: PUE is the average for Operational Global Data Center as of 2023_x000D_ [2025-04-29 JR] Additional Info: Selected power capacity updated based on number of generators observed in satellite imagery. | BU15: 45474 | BV15: 46219 | BW15: 46238
A16: 77ac6a16-efd6-49b8-bbfc-7a1e32626833 | B16: Amazon AWS IAD - 44150 Wade Dr | E16: Announcement | I16: 00a5efa3-8d76-4878-a0d6-f90a60f8b647 | J16: Amazon AWS | K16: https://www.aws.amazon.com/compliance/data-center/data-centers/ | L16: Public | M16: AMZN | N16: AMZN:US | O16: NASDAQ: AMZN | T16: 44150 Wade Dr, Chantilly, VA 20152, USA | U16: 20152 | V16: 51107 | W16: Loudoun County | X16: Chantilly | Y16: 14744 | Z16: VA | AA16: Virginia | AB16: US | AC16: United States | AD16: 38.920685 | AE16: -77.47298 | AF16: 24 | AG16: 350000 | AH16: 423575 | AJ16: 56.28 | AK16: 54.81 | AL16: 57.8 | AM16: 56.28 | AP16: 20 | AQ16: 45117 | AU16: 46193 | AV16: 0 | AW16: 46447 | AX16: 46447 | BA16: 498190ca-b66d-4a6a-becc-3657df8fca8d | BB16: Northern Virginia Elec Coop | BC16: 13640 | BD16: Private | BH16: 35f051b0-f1ce-470d-81d2-ea5c0d197f3a | BI16: PJM | BJ16: PJM Interconnection | BK16: 469a7dc0-fc5e-4f8e-8184-301f28134241 | BL16: DOM | BM16: Dominion Virginia Power zone - PJM | BO16: https://www.bisnow.com/washington-dc/news/deal-sheet/this-weeks-dc-deal-sheet-119715 | BP16: https://maps.app.goo.gl/dMX9UvX9i1crkizw8 | BQ16: https://loudouncountyvaeg.tylerhost.net/prod/selfservice#/plan/9bc502fd-3d1b-49b4-a765-b3da727ac11f?tab=attachments,https://loudoun.granicus.com/MetaViewer.php?view_id=78&event_id=3451&meta_id=221074#page=11&zoom=100,93,113 | BS16: High | BT16: [2024-12-19 JR] Latest Satellite: 2024-04-16; Construction Status: No Construction; Estimated Active Date By: Aterio; Additional Info: Land bought from Firefox_x000D_ [2025-04-29 JR] Construction: No vertical construction observed. Site appears cleared and partially graded. No active building activity at this stage._x000D_ [2025-12-30 AV] Additional Info: Activation date updated from 2026-09-30. No visible signs of construction. _x000D_ [2026-04-08 JH] Construction: No visible construction activity observed on site. | BU16: 45474 | BV16: 46219 | BW16: 46238
A17: 06bd1449-2708-4d9c-87f4-bef5f684c439 | B17: AWS NCTC Building 1 | C17: c3cef5b5-f06e-47d6-9e0c-a2fc2457d133 | D17: AWS Northeast Creek Tech Campus | E17: Construction | I17: 00a5efa3-8d76-4878-a0d6-f90a60f8b647 | J17: Amazon AWS | K17: https://www.aws.amazon.com/compliance/data-center/data-centers/ | L17: Public | M17: AMZN | N17: AMZN:US | O17: NASDAQ: AMZN | T17: X2MX+P5 Mineral, VA, USA | U17: 23117 | V17: 51109 | W17: Louisa County | X17: Mineral | Y17: 52120 | Z17: VA | AA17: Virginia | AB17: US | AC17: United States | AD17: 37.984306 | AE17: -77.95212 | AF17: 374 | AG17: 382000 | AH17: 382000 | AI17: 70 | AJ17: 39.2 | AK17: 38.17 | AL17: 40.25 | AM17: 70 | AQ17: 45600 | AT17: 45864 | AU17: 46186 | AV17: 0.15 | AW17: 46751 | AX17: 46751 | BA17: 6f92e568-ff47-4893-8e13-f98d40e662a4 | BB17: Rappahannock Electric Coop | BC17: 40228 | BD17: Private (Cooperative) | BH17: 35f051b0-f1ce-470d-81d2-ea5c0d197f3a | BI17: PJM | BJ17: PJM Interconnection | BK17: 469a7dc0-fc5e-4f8e-8184-301f28134241 | BL17: DOM | BM17: Dominion Virginia Power zone - PJM | BO17: https://www.nao.usace.army.mil/Media/Public-Notices/Article/3952905/nao-2024-01939-amazon-data-services-louisa-virginia/ | BP17: https://maps.app.goo.gl/MoCkLG935b63MWoe7 | BQ17: https://www.nao.usace.army.mil/Media/Public-Notices/Article/3952905/nao-2024-01939-amazon-data-services-louisa-virginia/ | BS17: High | BT17: [2024-03-12 JR] Latest Satellite: 2025-03-03; Construction Status: No Construction; Estimated Active Date By: AWS_x000D_ [2024-12-19 JR] Latest Satellite: 2021-10-21; Construction Status: No Construction; Estimated Active Date By: AWS_x000D_ [2025-09-07 DP] Construction: Significant land clearing and grading activity visible_x000D_ [2025-12-02 DP] Construction: Foundation work underway_x000D_ [2026-03-24 SQ] Construction: No significant progress to update percentage; Additional Info: Activation Date update from 2026-06-30 to Q4 2027._x000D_ [2026-05-28 AV] Construction: No significant progress to update percentage. _x000D_ [2026-06-25 SQ] Construction: No significant progress to update percentage. | BU17: 45636 | BV17: 46219 | BW17: 46238
A18: 21356727-827e-4d88-8a15-772459ff323c | B18: AWS Summit Crossing Building 1 | C18: ae37b109-2a22-4363-94f3-e00fae92adb8 | D18: AWS Summit Crossing Tech Campus | E18: Announcement | I18: 00a5efa3-8d76-4878-a0d6-f90a60f8b647 | J18: Amazon AWS | K18: https://www.aws.amazon.com/compliance/data-center/data-centers/ | L18: Public | M18: AMZN | N18: AMZN:US | O18: NASDAQ: AMZN | T18: 5HW9+VC Olive, VA, USA | U18: 22408 | V18: 51177 | W18: Spotsylvania County | X18: Fredericksburg | Y18: 29744 | Z18: VA | AA18: Virginia | AB18: US | AC18: United States | AD18: 38.197132 | AE18: -77.43137 | AF18: 231 | AG18: 300000 | AH18: 300000 | AJ18: 66 | AK18: 64.97 | AL18: 67.06 | AM18: 66 | AQ18: 45214 | AU18: 46206 | AV18: 0 | AW18: 47026 | AX18: 47026 | BA18: 5b0c2f7d-42e6-4e89-997c-39d2e368e019 | BB18: Virginia Electric & Power Co | BC18: 19876 | BD18: Public | BE18: D | BF18: D:US | BG18: NYSE:D | BH18: 35f051b0-f1ce-470d-81d2-ea5c0d197f3a | BI18: PJM | BJ18: PJM Interconnection | BK18: 469a7dc0-fc5e-4f8e-8184-301f28134241 | BL18: DOM | BM18: Dominion Virginia Power zone - PJM | BO18: https://fredericksburg.com/news/local/data-center-proposals-pile-up-in-spotsylvania/article_0b3a873c-ff26-11ed-97a1-df0bb17d1b49.html | BP18: https://maps.app.goo.gl/petKvnEPAhsxdXSu5 | BQ18: https://www.spotsylvania.va.us/DocumentCenter/View/33280/2nd-Submission-Narrative-?bidId= | BS18: Medium | BT18: [2025-04-01 JR] Additional Info: Correction made on Activation date and Stage based on new satellite image_x000D_ [2025-12-22 JR] Additional Info: Estimated Power Capacity Added._x000D_ [2025-12-30 AV] Additional Info: Activation date updated from 2026-08-30. No visible signs of construction._x000D_ [2026-04-16 JR] Additional Info: No construction visible; Activation date updated from 2027-03-31 to Q3 2028. | BU18: 45637 | BV18: 46219 | BW18: 46238
A19: e0996f61-ef80-43e2-a3ae-330e1da689ae | B19: Amazon AWS - Houchard Building 3 | C19: 7096adec-37f7-4126-9eb9-7376f4220ebe | D19: Dublin 1, AWS Campus | E19: Active | I19: 00a5efa3-8d76-4878-a0d6-f90a60f8b647 | J19: Amazon AWS | K19: https://www.aws.amazon.com/compliance/data-center/data-centers/ | L19: Public | M19: AMZN | N19: AMZN:US | O19: NASDAQ: AMZN | T19: 6830 Crosby Ct, Plain City, OH, USA | U19: 43064 | V19: 39159 | W19: Union County | X19: Plain City | Y19: 63030 | Z19: OH | AA19: Ohio | AB19: US | AC19: United States | AD19: 40.101833 | AE19: -83.19948 | AF19: 85 | AG19: 150500 | AH19: 150500 | AJ19: 22.5 | AK19: 21.91 | AL19: 23.11 | AM19: 22.5 | AN19: 19.57 | AO19: 1.15 | AP19: 11 | AW19: 44407 | BA19: 030eb1d3-5a7a-41c1-adf2-ff1890871e2f | BB19: Ohio Power Co | BC19: 14006 | BD19: Public | BE19: AEP | BF19: AEP:US | BG19: NASDAQ:AEP | BH19: 35f051b0-f1ce-470d-81d2-ea5c0d197f3a | BI19: PJM | BJ19: PJM Interconnection | BK19: f8f462a4-1283-4082-a7eb-2a242f708d96 | BL19: DAY | BM19: Dayton Power null zone - PJM | BO19: https://www.econdev.dublinohiousa.gov/2020/wp-content/uploads/2016/01/Crosby-Court-Job-Ready-Site-Dublin-Ohio-USA.pdf | BP19: https://maps.app.goo.gl/Ftb2AnGSFkRayDNy9 | BT19: [2024-12-19 JR] Additional Info: Area Estimated by Aterio_x000D_ [2025-02-28 JR] Additional Info: PUE is the average for Operational Global Data Center as of 2023_x000D_ [2025-04-29 JR] Additional Info: Selected power capacity updated based on number of generators observed in satellite imagery. | BU19: 45621 | BV19: 46219 | BW19: 46238
A20: 5a7a7d22-3174-4c6a-8494-d7f1645f00c9 | B20: AWS Mesa Data Center Building 1 | C20: 67056bad-e205-4c7e-8f8e-3cb3cf5ea0e9 | D20: E Pecos Rd, AWS Campus | E20: Construction | I20: 00a5efa3-8d76-4878-a0d6-f90a60f8b647 | J20: Amazon AWS | K20: https://www.aws.amazon.com/compliance/data-center/data-centers/ | L20: Public | M20: AMZN | N20: AMZN:US | O20: NASDAQ: AMZN | T20: 10464 E Pecos Rd, Mesa, AZ, USA | U20: 85212 | V20: 4013 | W20: Maricopa County | X20: Mesa | Y20: 46000 | Z20: AZ | AA20: Arizona | AB20: US | AC20: United States | AD20: 33.294785 | AE20: -111.60671 | AF20: 71 | AG20: 227000 | AH20: 227000 | AJ20: 93.5 | AK20: 91.98 | AL20: 95.06 | AM20: 93.5 | AP20: 36 | AQ20: 45196 | AT20: 45778 | AU20: 46209 | AV20: 0.85 | AW20: 46295 | AX20: 46295 | BA20: 5f1c3274-a117-4201-b548-6a9e4b37f693 | BB20: Salt River Project | BC20: 16572 | BD20: Private | BH20: 4f4fe9e0-cb99-459e-9c12-6621c6e60461 | BI20: SRP | BJ20: Salt River Project | BO20: https://www.bizjournals.com/phoenix/news/2023/09/26/amazon-multiple-data-centers-mesa-arizona.html | BP20: https://maps.app.goo.gl/YG9fCMehG9y6YXgi8 | BQ20: https://mesa.legistar.com/LegislationDetail.aspx?ID=6696112&GUID=FAD3140B-3E28-47F0-9B07-9529B14C6582&Options=&Search= | BS20: High | BT20: [2024-12-19 JR] Latest Satellite: 2024-02-13; Construction Status: No Construction; Estimated Active Date By: Aterio_x000D_ [2025-09-18 DP] Construction: Start foundation _x000D_ [2025-12-04 DP] Construction: Structural steel framing completed; roof installation begins; Additional Info: Activation date updated from 2027-03-30._x000D_ [2026-02-23 FC] Roof installation completed, generator yard being built out on the eastern section._x000D_ [2026-04-13 JR] Construction: Building shell and roof are complete. Equipment installation is underway along the eastern perimeter, with generator and electrical infrastructure pads populated_x000D_ [2026-05-12 JR] Construction: Nearly half of generators installed, cooling equipment installation on the roof underway._x000D_ [2026-07-20 JR] Construction: Generator installation progressing, 20 generators out of 36 in place; Additional Info: MW Capacity added based on number of generators and capacity filed. | BU20: 45616 | BV20: 46223 | BW20: 46238
A21: 02ee9e31-897b-44a1-b854-7d5abc85a61d | B21: Forest Lane Data Center 2 | C21: 7e4334e0-6d6a-11f0-998f-4de3ac37eead | D21: Forest Lane Data Center Campus | E21: Announcement | I21: 00a5efa3-8d76-4878-a0d6-f90a60f8b647 | J21: Amazon AWS | K21: https://www.aws.amazon.com/compliance/data-center/data-centers/ | L21: Public | M21: AMZN | N21: AMZN:US | O21: NASDAQ: AMZN | T21: 7J96+RWG Wildcat Corner, Virginia, USA | U21: 22405 | V21: 51179 | W21: Stafford County | X21: Fredericksburg | Y21: 29744 | Z21: VA | AA21: Virginia | AB21: US | AC21: United States | AD21: 38.269547 | AE21: -77.387665 | AF21: 844 | AG21: 355000 | AH21: 355000 | AJ21: 72.4 | AK21: 71.37 | AL21: 73.46 | AM21: 72.4 | AN21: 61 | AQ21: 45835 | AU21: 46216 | AV21: 0 | AW21: 47483 | AX21: 47483 | BH21: 35f051b0-f1ce-470d-81d2-ea5c0d197f3a | BI21: PJM | BJ21: PJM Interconnection | BK21: 469a7dc0-fc5e-4f8e-8184-301f28134241 | BL21: DOM | BM21: Dominion Virginia Power zone - PJM | BO21: https://staffordcova.portal.civicclerk.com/event/2607/files/attachment/27287 | BP21: https://maps.app.goo.gl/cByDrn57nPPPWvNq8 | BQ21: https://staffordcova.portal.civicclerk.com/event/2607/files/attachment/27287 | BS21: Medium | BT21: [2025-07-30 JR] Additional Info: Real Estate Pursuits 2 LC behind this project; Project on Review_x000D_ [2026-04-27 JR] Additional Info: Provider updated to Amazon AWS confirmed as part of "Kings Corridor Technology Campus" from Traffic Impact Assessment Studies; Power capacity added based on AWS standard designs; Activation date updated from 2028-09-15 to Q4 2029._x000D_ [2026-07-24 JR] Additional Info: MW Capacity udpated based on disclosed load letters. | BU21: 45868 | BV21: 46227 | BW21: 46238
A22: 66ef8500-4f41-4eaa-a2a6-5341e999f027 | B22: Forest Lane Data Center 3 | C22: 7e4334e0-6d6a-11f0-998f-4de3ac37eead | D22: Forest Lane Data Center Campus | E22: Announcement | I22: 00a5efa3-8d76-4878-a0d6-f90a60f8b647 | J22: Amazon AWS | K22: https://www.aws.amazon.com/compliance/data-center/data-centers/ | L22: Public | M22: AMZN | N22: AMZN:US | O22: NASDAQ: AMZN | T22: 7J96+RWG Wildcat Corner, Virginia, USA | U22: 22405 | V22: 51179 | W22: Stafford County | X22: Fredericksburg | Y22: 29744 | Z22: VA | AA22: Virginia | AB22: US | AC22: United States | AD22: 38.269547 | AE22: -77.387665 | AF22: 844 | AG22: 355000 | AH22: 355000 | AJ22: 72.4 | AK22: 71.37 | AL22: 73.46 | AM22: 72.4 | AN22: 61 | AQ22: 45835 | AU22: 46216 | AV22: 0 | AW22: 47573 | AX22: 47573 | BH22: 35f051b0-f1ce-470d-81d2-ea5c0d197f3a | BI22: PJM | BJ22: PJM Interconnection | BK22: 469a7dc0-fc5e-4f8e-8184-301f28134241 | BL22: DOM | BM22: Dominion Virginia Power zone - PJM | BO22: https://staffordcova.portal.civicclerk.com/event/2607/files/attachment/27287 | BP22: https://maps.app.goo.gl/cByDrn57nPPPWvNq8 | BQ22: https://staffordcova.portal.civicclerk.com/event/2607/files/attachment/27287 | BS22: Medium | BT22: [2025-07-30 JR] Additional Info: Real Estate Pursuits 2 LC behind this project; Project on Review_x000D_ [2026-04-27 JR] Additional Info: Provider updated to Amazon AWS confirmed as part of "Kings Corridor Technology Campus" from Traffic Impact Assessment Studies; Power capacity added based on AWS standard designs; Activation date updated from 2028-09-15 to Q1 2030._x000D_ [2026-07-24 JR] Additional Info: MW Capacity udpated based on disclosed load letters. | BU22: 45868 | BV22: 46227 | BW22: 46238
A23: c3bfdc49-52e2-48c9-ad90-2953696e2976 | B23: Amazon AWS CMH - Hayden Building 1 | C23: 79092d60-e59b-44bb-839d-f48936205ed3 | D23: Hilliard 1, AWS Campus | E23: Active | I23: 00a5efa3-8d76-4878-a0d6-f90a60f8b647 | J23: Amazon AWS | K23: https://www.aws.amazon.com/compliance/data-center/data-centers/ | L23: Public | M23: AMZN | N23: AMZN:US | O23: NASDAQ: AMZN | T23: 5113 Hayden Run Rd, Hilliard, OH 43026, USA | U23: 43026 | V23: 39049 | W23: Franklin County | X23: Hilliard | Y23: 35476 | Z23: OH | AA23: Ohio | AB23: US | AC23: United States | AD23: 40.061283 | AE23: -83.13506 | AG23: 154000 | AH23: 154000 | AJ23: 30 | AK23: 29.21 | AL23: 30.81 | AM23: 30 | AN23: 26.09 | AO23: 1.15 | AP23: 14 | AW23: 42551 | BA23: 6c6655b1-8b8e-45b1-bd02-146ed6379690 | BB23: Ohio Edison Co | BC23: 13998 | BD23: Public | BE23: FE | BF23: FE:US | BG23: NYSE:FE | BH23: 35f051b0-f1ce-470d-81d2-ea5c0d197f3a | BI23: PJM | BJ23: PJM Interconnection | BK23: b1618d6a-8bed-43db-bbf9-70933b83f636 | BL23: AEP | BM23: American Electric Power zone - PJM | BO23: https://www.aboutamazon.com/news/aws | BP23: https://maps.app.goo.gl/K36txvaRtMJn1F7u9 | BT23: [2025-02-28 JR] Additional Info: PUE is the average for Operational Global Data Center as of 2023_x000D_ [2025-04-29 JR] Additional Info: Selected power capacity updated based on number of generators observed in satellite imagery. | BU23: 45590 | BV23: 46219 | BW23: 46238
A24: 89fb1047-b044-4111-b113-7f85e3d75178 | B24: Amazon AWS IAD - 42139 Reeds Farm Building 2 | C24: d7ca5353-03b0-427f-a57e-ddcb337df386 | D24: John Mosby, AWS Campus | E24: Construction | I24: 00a5efa3-8d76-4878-a0d6-f90a60f8b647 | J24: Amazon AWS | K24: https://www.aws.amazon.com/compliance/data-center/data-centers/ | L24: Public | M24: AMZN | N24: AMZN:US | O24: NASDAQ: AMZN | Q24: Urban Ltd | T24: 42139 Reeds Farm Ln, Stone Ridge, VA, USA | U24: 20105 | V24: 51107 | W24: Loudoun County | X24: Aldie | Y24: 772 | Z24: VA | AA24: Virginia | AB24: US | AC24: United States | AD24: 38.942986 | AE24: -77.55044 | AG24: 245000 | AH24: 245000 | AJ24: 60 | AK24: 58.43 | AL24: 61.62 | AM24: 60 | AQ24: 44852 | AT24: 45681 | AU24: 46121 | AV24: 0.15 | AW24: 46842 | AX24: 46842 | BA24: 498190ca-b66d-4a6a-becc-3657df8fca8d | BB24: Northern Virginia Elec Coop | BC24: 13640 | BD24: Private | BH24: 35f051b0-f1ce-470d-81d2-ea5c0d197f3a | BI24: PJM | BJ24: PJM Interconnection | BK24: 469a7dc0-fc5e-4f8e-8184-301f28134241 | BL24: DOM | BM24: Dominion Virginia Power zone - PJM | BO24: https://www.bizjournals.com/washington/news/2022/10/17/loudoun-data-centers-amazon-dominion-energy.html | BP24: https://maps.app.goo.gl/rL4ih5Q4VB8Jjpjm8 | BS24: High | BT24: [2024-12-19 JR] Latest Satellite: 2024-04-29; Construction Status: Site Preparation; Estimated Active Date By: Aterio; Additional Info: Area Estimated by Aterio_x000D_ [2025-03-19 JR] Latest Satellite: 2025-02-24; Construction Status: Site Preparation; Estimated Active Date By: Aterio; Additional Info: Updated Activation Date, Construction delayed_x000D_ [2025-08-12 JR] Construction: Site Cleared, no land grading yet._x000D_ [2025-10-22 JR] Construction: Concrete foundation underway, no vertical construction yet. _x000D_ [2026-01-22 JR] Construction: Still no vertical construction; Additional Info: Activation date updated from 2026-08-30_x000D_ [2026-03-25 SQ] Construction: No significant progress to update porcentage; Additional Info: Activation Date updated from 2027-03-31 to Q1 2028. | BU24: 45616 | BV24: 46219 | BW24: 46238
A25: cdf85bb1-9175-4c31-b0f6-2375c071f5dc | B25: Amazon AWS - Beech Building 3 | C25: 5f9ca800-6806-11f0-905f-5301cba7d3ec | D25: Newton Ct, AWS Campus | E25: Active | I25: 00a5efa3-8d76-4878-a0d6-f90a60f8b647 | J25: Amazon AWS | K25: https://www.aws.amazon.com/compliance/data-center/data-centers/ | L25: Public | M25: AMZN | N25: AMZN:US | O25: NASDAQ: AMZN | T25: 2645-2655 Newton Ct, Johnstown, OH, USA | U25: 43031 | V25: 39089 | W25: Licking County | X25: Johnstown | Y25: 39340 | Z25: OH | AA25: Ohio | AB25: US | AC25: United States | AD25: 40.094166 | AE25: -82.73194 | AG25: 215500 | AH25: 215500 | AJ25: 60 | AK25: 58.43 | AL25: 61.62 | AM25: 60 | AN25: 51.28 | AP25: 26 | AT25: 45137 | AW25: 45611 | BA25: 030eb1d3-5a7a-41c1-adf2-ff1890871e2f | BB25: Ohio Power Co | BC25: 14006 | BD25: Public | BE25: AEP | BF25: AEP:US | BG25: NASDAQ:AEP | BH25: 35f051b0-f1ce-470d-81d2-ea5c0d197f3a | BI25: PJM | BJ25: PJM Interconnection | BK25: b1618d6a-8bed-43db-bbf9-70933b83f636 | BL25: AEP | BM25: American Electric Power zone - PJM | BO25: https://dis.puc.state.oh.us/CaseRecord.aspx?Caseno=25-0133&link=DIVA | BP25: https://maps.app.goo.gl/2bRLt9W5RmGKt5Ha8 | BT25: [2025-04-29 JR] Additional Info: Selected power capacity updated based on number of generators observed in satellite imagery. | BU25: 45474 | BV25: 46233 | BW25: 46238
A26: c841dc89-be6b-464e-9591-8c61dac08cf0 | B26: Amazon AWS - Potomac Building 2 | C26: 55a50504-03db-4e92-90b5-1e70a709b1dd | D26: Potomac, AWS Campus | E26: Construction | I26: 00a5efa3-8d76-4878-a0d6-f90a60f8b647 | J26: Amazon AWS | K26: https://www.aws.amazon.com/compliance/data-center/data-centers/ | L26: Public | M26: AMZN | N26: AMZN:US | O26: NASDAQ: AMZN | T26: Old Potomac Church Rd, Stafford, VA, USA | U26: 22554 | V26: 51179 | W26: Stafford County | X26: Stafford | Z26: VA | AA26: Virginia | AB26: US | AC26: United States | AD26: 38.41099 | AE26: -77.40478 | AF26: 50 | AG26: 255000 | AH26: 255000 | AJ26: 22.7 | AK26: 22.1 | AL26: 23.31 | AM26: 22.7 | AP26: 11 | AQ26: 45181 | AT26: 45870 | AU26: 46161 | AV26: 0.15 | AW26: 46751 | AX26: 46751 | BA26: 5b0c2f7d-42e6-4e89-997c-39d2e368e019 | BB26: Virginia Electric & Power Co | BC26: 19876 | BD26: Public | BE26: D | BF26: D:US | BG26: NYSE:D | BH26: 35f051b0-f1ce-470d-81d2-ea5c0d197f3a | BI26: PJM | BJ26: PJM Interconnection | BK26: 469a7dc0-fc5e-4f8e-8184-301f28134241 | BL26: DOM | BM26: Dominion Virginia Power zone - PJM | BO26: https://www.govtech.com/computing/stafford-county-va-to-hold-meeting-on-data-center-proposal | BP26: https://maps.app.goo.gl/DW8mQpFmpeXjA2fw8 | BQ26: https://staffordcova.portal.civicclerk.com/event/2494/files/attachment/27267 | BS26: High | BT26: [2024-12-19 JR] Latest Satellite: 2024-10-05; Construction Status: No Construction; Estimated Active Date By: Aterio_x000D_ [2025-04-07 JR] Additional Info: Project announced in 2023. Site shows minimal activity, indicating slower-than-expected construction progress._x000D_ [2025-09-29 JR] Construction: Foundation being poured and steel framing underway._x000D_ [2026-01-22 JR] Construction: Site cleared no progress since._x000D_ [2026-03-24 AV] Construction: Land grading still in progress. Additional Info: Activation date updated from 2027-03-30 to Q4 2027._x000D_ [2026-05-06 JR] Construction: No progress to update %._x000D_ [2026-06-05 JR] Construction: Foundation work being done, no vertical construction yet. | BU26: 45636 | BV26: 46219 | BW26: 46238
A27: 79b96a02-47a8-4029-a21e-4358f6ed9589 | B27: Data Center 1 | C27: 8e7ec2e0-c989-11f0-a883-9fe07aabef6d | D27: Rock House Road, AWS Campus | E27: Construction | I27: 00a5efa3-8d76-4878-a0d6-f90a60f8b647 | J27: Amazon AWS | K27: https://www.aws.amazon.com/compliance/data-center/data-centers/ | L27: Public | M27: AMZN | N27: AMZN:US | O27: NASDAQ: AMZN | Q27: Kimley-Horn | T27: 2317-2499 Echo Rd, Lithia Springs, GA, USA | U27: 30122 | V27: 13097 | W27: Douglas County | X27: Lithia Springs | Y27: 46832 | Z27: GA | AA27: Georgia | AB27: US | AC27: United States | AD27: 33.74364 | AE27: -84.60766 | AF27: 134 | AG27: 380000 | AH27: 380000 | AJ27: 41.25 | AK27: 40.18 | AL27: 42.34 | AM27: 41.25 | AP27: 17 | AQ27: 45645 | AT27: 45748 | AU27: 46152 | AV27: 0.15 | AW27: 46568 | AX27: 46568 | BA27: 435eef77-beb0-4620-9aae-8f86d110eb8c | BB27: Georgia Power Co | BC27: 7140 | BD27: Public | BE27: GPJA | BF27: GPB:US | BG27: NYSE:GPJA | BH27: fc5d245b-5d3e-4004-b00a-666a73bde91d | BI27: SOCO | BJ27: Southern Company | BO27: https://www.fox5atlanta.com/news/amazon-buys-118-acres-douglas-county-possible-data-center-amid-concerns-about-sustainability, https://www.aboutamazon.com/news/aws/aws-investment-georgia-ai-cloud-infrastructure | BP27: https://maps.app.goo.gl/p1GX4pKy5ouZGA788 | BQ27: https://documents.atlantaregional.com/Land%20Use/Reviews/ID5383/2023%20Rock%20House%20Road%20Data%20Center%20Site%20DRI%204078%20-%20Final%20Report.pdf, https://geos.epd.georgia.gov/GA/GEOS/Public/EnSuite/Shared/Pages/Util/ServerRptViewer.aspx?sr=/GovOnline_LG/RPT_GOVf1152&SUBMISSION_RID=917915&SUB_FORM_RID=880165 | BS27: High | BT27: [2024-12-19 JR] Additional Info: Landbank_x000D_ [2025-01-08 JR] Latest Satellite: N/A; Construction Status: No Construction; Estimated Active Date By: Aterio; Additional Info: Investment announced by AWS, previous Land Acquisition in Oct 2024._x000D_ [2025-11-24 DS] Construction: Foundation work visible on building 1, site clearing in progress for the campus; Additional Info: Number of buildings and size updated based on permit._x000D_ [2026-01-27 JR] Construction: Concrete slabs in place, no vertical construction yet_x000D_ [2026-05-12 JR] Construction: No significant progress to update %. | BU27: 45616 | BV27: 46219 | BW27: 46238
A28: c3b964b1-7bc3-4883-a908-94804d56b9e5 | B28: Amazon AWS IAD - Severn Building 1 | C28: 6c2c447a-bdb3-4761-98dd-1eb7f8ffe10c | D28: Severn, AWS Campus | E28: Active | I28: 00a5efa3-8d76-4878-a0d6-f90a60f8b647 | J28: Amazon AWS | K28: https://www.aws.amazon.com/compliance/data-center/data-centers/ | L28: Public | M28: AMZN | N28: AMZN:US | O28: NASDAQ: AMZN | T28: 45259 West Severn Way, Sterling, VA, USA | U28: 20166 | V28: 51107 | W28: Loudoun County | X28: Sterling | Y28: 75376 | Z28: VA | AA28: Virginia | AB28: US | AC28: United States | AD28: 39.021744 | AE28: -77.432785 | AG28: 78000 | AH28: 78000 | AJ28: 25 | AK28: 24.34 | AL28: 25.68 | AM28: 25 | AN28: 21.74 | AO28: 1.15 | AP28: 12 | AW28: 41090 | BA28: 5b0c2f7d-42e6-4e89-997c-39d2e368e019 | BB28: Virginia Electric & Power Co | BC28: 19876 | BD28: Public | BE28: D | BF28: D:US | BG28: NYSE:D | BH28: 35f051b0-f1ce-470d-81d2-ea5c0d197f3a | BI28: PJM | BJ28: PJM Interconnection | BK28: 469a7dc0-fc5e-4f8e-8184-301f28134241 | BL28: DOM | BM28: Dominion Virginia Power zone - PJM | BP28: https://maps.app.goo.gl/FrruYxLTuGt93Mrq7 | BT28: [2025-02-28 JR] Additional Info: PUE is the average for Operational Global Data Center as of 2023_x000D_ [2025-04-29 JR] Additional Info: Selected power capacity updated based on number of generators observed in satellite imagery. | BU28: 45474 | BV28: 46219 | BW28: 46238
A29: 55e23001-ee1c-4b82-956d-6149c43617e3 | B29: AWS - St. Olive Township Building 1 | C29: 0bf37f90-d88e-4b18-9973-d9152657ecad | D29: St. Joseph, AWS Campus - Project Rainier | E29: Active | F29: Y | H29: 11000000000 | I29: 00a5efa3-8d76-4878-a0d6-f90a60f8b647 | J29: Amazon AWS | K29: https://www.aws.amazon.com/compliance/data-center/data-centers/ | L29: Public | M29: AMZN | N29: AMZN:US | O29: NASDAQ: AMZN | S29: Anthropic | T29: 55001-55499 Elderberry Rd, New Carlisle, IN, USA | U29: 46552 | V29: 18141 | W29: St. Joseph County | X29: New Carlisle | Y29: 52704 | Z29: IN | AA29: Indiana | AB29: US | AC29: United States | AD29: 41.692 | AE29: -86.463 | AF29: 870 | AG29: 216000 | AH29: 216000 | AI29: 65 | AJ29: 64.85 | AK29: 63.15 | AL29: 66.6 | AM29: 65 | AP29: 26 | AQ29: 45107 | AT29: 45139 | AU29: 45926 | AV29: 1 | AW29: 45853 | BA29: bb57dbed-2ea2-42a0-9a18-5d34071b64a6 | BB29: Indiana Michigan Power Co | BC29: 9324 | BD29: Public | BE29: AEP | BF29: AEP:US | BG29: NASDAQ:AEP | BH29: 35f051b0-f1ce-470d-81d2-ea5c0d197f3a | BI29: PJM | BJ29: PJM Interconnection | BO29: https://www.sbrchamber.com/pages/aws/, https://www.renewableenergyworld.com/energy-business/policy-and-regulation/midwest-utility-reaches-deal-with-tech-giants-on-data-centers/ | BP29: https://maps.app.goo.gl/4NwJLWtLod1EiXb96 | BQ29: https://caats.idem.in.gov/sourceDetail.xhtml?sourceId=141-00642,https://permits.air.idem.in.gov/48888f.pdf | BT29: [2025-01-27 JR] Additional Info: Stage Updated to Active_x000D_ [2025-05-27 JR] Construction: Exterior and roof fully completed, with all cooling units and generators installed. No visible parking lot activity suggests the facility is not yet operational. Final-stage work underway; Additional Info: Stage updated based on recent satellite imagery_x000D_ [2025-09-26 JR] Construction: Satellite imagery confirms the facility structure is complete with parking lot activity suggesting is operating; Additional Info: Stage updated to Active._x000D_ [2025-10-29 JR] Additional Info: Activation date updated from 2025-06-30._x000D_ [2026-05-14 AV] Additional Info: The Balancing Authority has been updated from MISO to PJM, according to information from Indiana Michigan Power, the utility that supplies power for the project; they state that they are part of the regional monitoring system operated by PJM. | BU29: 45611 | BV29: 46219 | BW29: 46238
A30: 3c73a072-1cf9-45e2-b271-73af2364d9ac | B30: Amazon AWS - 8158 Sudley Rd Building 4 | C30: 945d06f8-7f1b-4515-990f-60162fe860ea | D30: Sudley Rd, AWS Campus | E30: Not Approved/Withdrawn | I30: 00a5efa3-8d76-4878-a0d6-f90a60f8b647 | J30: Amazon AWS | K30: https://www.aws.amazon.com/compliance/data-center/data-centers/ | L30: Public | M30: AMZN | N30: AMZN:US | O30: NASDAQ: AMZN | T30: Historic District, 8158 Sudley Rd, Manassas, VA, USA | U30: 20109 | V30: 51153 | W30: Prince William County | X30: Manassas | Y30: 48952 | Z30: VA | AA30: Virginia | AB30: US | AC30: United States | AD30: 38.776455 | AE30: -77.51033 | AG30: 250000 | AH30: 250000 | AJ30: 67 | AK30: 65.24 | AL30: 68.8 | AM30: 67 | AQ30: 44381 | AS30: 44895 | AU30: 46223 | AV30: 0 | BA30: 498190ca-b66d-4a6a-becc-3657df8fca8d | BB30: Northern Virginia Elec Coop | BC30: 13640 | BD30: Private | BH30: 35f051b0-f1ce-470d-81d2-ea5c0d197f3a | BI30: PJM | BJ30: PJM Interconnection | BK30: 469a7dc0-fc5e-4f8e-8184-301f28134241 | BL30: DOM | BM30: Dominion Virginia Power zone - PJM | BO30: https://egcss.pwcgov.org/SelfService#/plan/d4b5eaad-adc6-4bb2-a237-01b9a66daf3f,https://eservice.pwcgov.org/planning/documents/SUP2021-00030.pdf | BP30: https://maps.app.goo.gl/ThZth3zYZVHut8xD8 | BQ30: https://eservice.pwcgov.org/planning/documents/SUP2021-00030.pdf | BS30: Low | BU30: 45616 | BV30: 46227 | BW30: 46238
A31: 88854ca9-8834-44d1-9074-b975066da547 | B31: Amazon AWS IAD - 4100 Westfax | C31: 44bfc3fc-ef41-4d21-9674-3fd4a7a27221 | D31: Westfax, AWS Campus | E31: Active | I31: 00a5efa3-8d76-4878-a0d6-f90a60f8b647 | J31: Amazon AWS | K31: https://www.aws.amazon.com/compliance/data-center/data-centers/ | L31: Public | M31: AMZN | N31: AMZN:US | O31: NASDAQ: AMZN | T31: 4100B Westfax Dr, 20151 Chantilly, Virginia | U31: 20151 | V31: 51059 | W31: Fairfax County | X31: Chantilly | Y31: 14744 | Z31: VA | AA31: Virginia | AB31: US | AC31: United States | AD31: 38.899643 | AE31: -77.45352 | AG31: 95000 | AH31: 95000 | AJ31: 17.5 | AK31: 17.04 | AL31: 17.97 | AM31: 17.5 | AN31: 15.22 | AO31: 1.15 | AP31: 9 | AW31: 41075 | BA31: 498190ca-b66d-4a6a-becc-3657df8fca8d | BB31: Northern Virginia Elec Coop | BC31: 13640 | BD31: Private | BH31: 35f051b0-f1ce-470d-81d2-ea5c0d197f3a | BI31: PJM | BJ31: PJM Interconnection | BK31: 469a7dc0-fc5e-4f8e-8184-301f28134241 | BL31: DOM | BM31: Dominion Virginia Power zone - PJM | BO31: https://www.fairfaxcounty.gov/planning-development/sites/planning-development/files/Assets/Documents/PDF/data-centers-report.pdf | BP31: https://maps.app.goo.gl/UtL82DK3Tbb13rKW7 | BT31: [2025-02-28 JR] Additional Info: PUE is the average for Operational Global Data Center as of 2023_x000D_ [2025-04-29 JR] Additional Info: Selected power capacity updated based on number of generators observed in satellite imagery. | BU31: 45474 | BV31: 46219 | BW31: 46238
A32: 0426f94e-6b7f-49de-adff-f04211eba271 | B32: Reno Data Center Building 1 | C32: cdb00e63-8f2e-49ca-97fd-5d53e02bfda5 | D32: Reno, Apple Campus | E32: Active | I32: 32fa7692-aaff-460b-890f-a0797415841b | J32: Apple Inc. | L32: Public | M32: AAPL | N32: AAPL:US | O32: NASDAQ: AAPL | T32: 21905 Reno Technology Pkwy E, Sparks, NV , USA | U32: 89434 | V32: 32031 | W32: Washoe County | X32: Sparks | Y32: 68400 | Z32: NV | AA32: Nevada | AB32: US | AC32: United States | AD32: 39.566376 | AE32: -119.54829 | AF32: 172 | AG32: 450000 | AH32: 450000 | AJ32: 54.56 | AK32: 52.03 | AL32: 57.22 | AM32: 54.56 | AP32: 12 | AT32: 41440 | AW32: 42750 | BA32: 757f0377-d9c2-4069-b8b0-8b1c2df30d5d | BB32: Sierra Pacific Power Co | BC32: 17166 | BD32: Private (Subsidiary of Berkshire Hathaway Energy) | BH32: 20d89abf-59f0-4305-a19c-cdd6e1ef572d | BI32: NEVP | BJ32: NV Energy | BO32: https://www.apple.com/ca/newsroom/ | BP32: https://maps.app.goo.gl/3JX5FuSDF6fcj5N39 | BQ32: https://www.nnph.org/files/air-quality/public-notices/notice-of-proposed-action/2025/250613_Apple_Inc._AAIR16-0082%20_Application.pdf | BT32: [2025-02-25 JR] Additional Info: Expansions plans announced, part of a $500 Billion investment plan_x000D_ [2025-12-29 FC] Additional Info: Updated air quality permit. Building 300MW Sunol substation. | BU32: 45474 | BV32: 46219 | BW32: 46238
A33: 316e8bab-7c45-4e57-86c0-a91a286af7a7 | B33: Waukee IA Data Center Building 2 | C33: ce35927e-90b9-4486-90b9-a9f9dc0357c6 | D33: Waukee, Apple IA Campus | E33: Announcement | I33: 32fa7692-aaff-460b-890f-a0797415841b | J33: Apple Inc. | L33: Public | M33: AAPL | N33: AAPL:US | O33: NASDAQ: AAPL | T33: J39G+X7J Waukee, Iowa | U33: 50263 | V33: 19049 | W33: Dallas County | X33: Waukee | Y33: 82695 | Z33: IA | AA33: Iowa | AB33: US | AC33: United States | AD33: 41.62028 | AE33: -93.92701 | AG33: 200000 | AH33: 200000 | AJ33: 45.93 | AK33: 43.8 | AL33: 48.16 | AM33: 45.93 | AQ33: 43002 | AU33: 46174 | AV33: 0 | AW33: 46934 | AX33: 46934 | BA33: d2db9308-fed1-4c79-997e-4042e507ae54 | BB33: MidAmerican Energy Co | BC33: 12341 | BD33: Private | BH33: cead66ff-8552-43d5-b723-aeedd7318b2b | BI33: MISO | BJ33: Midcontinent Independent System Operator | BK33: 9219d51e-40e9-48fc-8e60-2853a2960fc5 | BL33: 35 | BM33: Zones 3 and 5 - MISO | BO33: https://www.apple.com/pl/newsroom/2017/08/apples-next-us-data-center-will-be-built-in-iowa/ | BP33: https://maps.app.goo.gl/WTkvVn4uuzV8TSc96 | BS33: High | BT33: [2024-12-19 JR] Latest Satellite: 2024-11-07; Construction Status: No Construction; Estimated Active Date By: Aterio_x000D_ [2025-02-25 JR] Additional Info: Expansions plans announced, part of a $500 Billion investment plan_x000D_ [2025-12-10 DS] Additional Info: Updated activation date from 2026-03-15 since there is no active construction._x000D_ [2026-03-13 SQ] Additional Info: Activation Date update from 2027-03-15 to Q2 2028 | BU33: 45474 | BV33: 46219 | BW33: 46238
A34: 00371327-8827-4ad4-8197-b3b4fa7fe7c6 | B34: Waukee IA Data Center Building 1 | C34: ce35927e-90b9-4486-90b9-a9f9dc0357c6 | D34: Waukee, Apple IA Campus | E34: Active | I34: 32fa7692-aaff-460b-890f-a0797415841b | J34: Apple Inc. | L34: Public | M34: AAPL | N34: AAPL:US | O34: NASDAQ: AAPL | T34: J39G+X7J Waukee, Iowa | U34: 50263 | V34: 19049 | W34: Dallas County | X34: Waukee | Y34: 82695 | Z34: IA | AA34: Iowa | AB34: US | AC34: United States | AD34: 41.61696 | AE34: -93.92482 | AG34: 290000 | AH34: 290000 | AJ34: 29.87 | AK34: 28.49 | AL34: 31.32 | AM34: 29.87 | AQ34: 43002 | AT34: 44910 | AW34: 45306 | BA34: d2db9308-fed1-4c79-997e-4042e507ae54 | BB34: MidAmerican Energy Co | BC34: 12341 | BD34: Private | BH34: cead66ff-8552-43d5-b723-aeedd7318b2b | BI34: MISO | BJ34: Midcontinent Independent System Operator | BK34: 9219d51e-40e9-48fc-8e60-2853a2960fc5 | BL34: 35 | BM34: Zones 3 and 5 - MISO | BO34: https://www.apple.com/pl/newsroom/2017/08/apples-next-us-data-center-will-be-built-in-iowa/ | BP34: https://maps.app.goo.gl/WTkvVn4uuzV8TSc96 | BT34: [2025-02-25 JR] Additional Info: Expansions plans announced, part of a $500 Billion investment plan | BU34: 45474 | BV34: 46219 | BW34: 46238
A35: a11eed04-a5f3-4bdd-8f37-075825956809 | B35: Amazon AWS IAD - John Marshall 2 Building 4 | C35: 9d4da2e7-a600-454c-83a8-876d68e9839f | D35: Village Technology Park | E35: Delayed | I35: f2e8c736-1cf2-48f2-b835-cbcdc912f50e | J35: Black Chamber | K35: https://blackchambergroup.com/ | L35: Private | S35: Amazon AWS | T35: 14435 John Marshall Hwy, Gainesville, VA, USA | U35: 20155 | V35: 51153 | W35: Prince William County | X35: Gainesville | Y35: 30176 | Z35: VA | AA35: Virginia | AB35: US | AC35: United States | AD35: 38.799885 | AE35: -77.62007 | AF35: 45.5 | AG35: 255000 | AH35: 255000 | AI35: 60 | AJ35: 36.78 | AK35: 35.07 | AL35: 38.57 | AM35: 60 | AN35: 52 | AQ35: 44946 | AT35: 45442 | AU35: 46175 | AV35: 0.85 | AW35: 46660 | AX35: 46660 | BA35: 5b0c2f7d-42e6-4e89-997c-39d2e368e019 | BB35: Virginia Electric & Power Co | BC35: 19876 | BD35: Public | BE35: D | BF35: D:US | BG35: NYSE:D | BH35: 35f051b0-f1ce-470d-81d2-ea5c0d197f3a | BI35: PJM | BJ35: PJM Interconnection | BK35: 469a7dc0-fc5e-4f8e-8184-301f28134241 | BL35: DOM | BM35: Dominion Virginia Power zone - PJM | BP35: https://maps.app.goo.gl/TfpQEU2tM8NPFU246 | BQ35: https://eservice.pwcgov.org/planning/documents/REZ2020-00024.pdf,https://eservice.pwcgov.org/documents/bocs/agendas/2021/0615/14-D.pdf | BS35: High | BT35: [2024-12-19 JR] Latest Satellite: 2024-04-29; Construction Status: Construction 10%; Estimated Active Date By: Aterio; Additional Info: Area Estimated by Aterio_x000D_ [2025-01-16 JR] Additional Info: Project owned by Black Chamber_x000D_ [2025-05-02 JR] Construction: All four buildings appear structurally complete. Recent satellite imagery confirms only one is active. No visible signs of equipment installation or commissioning in the remaining three. Project appears delayed or paused beyond initial expectations._x000D_ [2025-09-15 JR] Additional Info: Still no activity on equipment installation, activation date updated from 2025-10-30_x000D_ [2026-01-08 JR] Construction: No activity visible, equipment haven't been installed still; Additional Info: Activation Date updated from 2026-01-01._x000D_ [2026-02-12 JR] Additional Information: The provider name has been updated to match the asset owner rather than the end user._x000D_ [2026-03-17 JR] Construction: No generators installed still. No construction activity visible; Additional Info: Activation Date updated from 2026-06-30 to Q3 2027._x000D_ [2026-06-17 JR] Construction: Significant car parking lot activity suggesting construction about to restart. Status Mantained._x000D_ | BU35: 45590 | BV35: 46210 | BW35: 46238
A36: 56b8d270-042c-41ef-b635-f5925f97d787 | B36: Cal Ethos Data Center Building 3 | C36: be834e69-6a49-411a-a38d-6f3732ab6db2 | D36: Lithium Valley, CalEthos Campus | E36: Announcement | F36: Y | I36: cc9add2a-7f08-41d7-a08b-35f62fb41655 | J36: CalEthos | K36: https://calethos.com/ | L36: Private | T36: Imperial County, California | U36: 92233 | V36: 6025 | W36: Imperial County | X36: Calipatria | Y36: 9878 | Z36: CA | AA36: California | AB36: US | AC36: United States | AD36: 33.176605 | AE36: -115.52333 | AF36: 100 | AG36: 200000 | AH36: 200000 | AI36: 84 | AJ36: 36.6 | AK36: 34.9 | AL36: 38.38 | AM36: 84 | AQ36: 45267 | AU36: 46211 | AV36: 0 | AW36: 46660 | AX36: 46660 | BA36: f640ca27-1f27-4e22-b561-64d11ebade41 | BB36: Imperial Irrigation District | BC36: 9216 | BH36: 2950a9eb-39ef-4949-96bd-ecefbf7db624 | BI36: CISO | BJ36: California Independent System Operator | BK36: bca9875d-2947-4bea-b1e6-5efaf46382f0 | BL36: SCE | BM36: Southern California Edison - CISO | BO36: https://calethos.com/calethos-completes-the-first-phase-of-development-on-a-planned-300mw-clean-energy-powered-data-center-campus-in-southern-california/,https://imperialcounty.org/wp-content/uploads/2025/02/February25DraftLVSP_combined.pdf, https://www.sec.gov/ix?doc=/Archives/edgar/data/0001174891/000149315225023306/form10-q.htm#fact-identifier-556 | BP36: https://maps.app.goo.gl/PQsAcMYHKP4kHcCn8 | BS36: High | BT36: [2024-12-19 JR] Latest Satellite: 2024-02-02; Construction Status: No Construction; Estimated Active Date By: Aterio; Power source: Solar power, geothermal; Additional Info: The data center will be powered by 100 percent geothermal and solar energy._x000D_ [2025-11-13 AV]: Additional Info: Construction has not started. Activation date updated from 2026-03-31._x000D_ [2025-12-17 FC] Additional Info: Updated total capacity from 300MW to 420MW and distributed among estimated number of buildings; added recent 8K filing | BU36: 45614 | BV36: 46230 | BW36: 46238
A37: db5541db-8139-4e8f-8564-0e592cf4ee49 | B37: TPA1 Tampa Data Center | E37: Active | I37: 8d42255d-b8b4-474e-bab6-890f808f2aa6 | J37: Centersquare | K37: https://www.centersquaredc.com | L37: Private | P37: Brookfield | T37: 9310 Florida Palm Drive, Tampa, FL, USA | U37: 33619 | V37: 12057 | W37: Hillsborough County | X37: Tampa | Y37: 71000 | Z37: FL | AA37: Florida | AB37: US | AC37: United States | AD37: 27.945324 | AE37: -82.3512 | AG37: 100000 | AH37: 100000 | AI37: 12 | AJ37: 10.6 | AK37: 10.1 | AL37: 11.11 | AM37: 12 | AP37: 7 | AW37: 37011 | BA37: 17326afc-4fb8-4762-a557-bed2e9cf035b | BB37: Tampa Electric Co | BC37: 18454 | BD37: Public | BE37: EMA | BF37: EMA:CN | BG37: TSE:EMA | BH37: 23ffd9d1-86ba-4c60-b795-aec19afd3a10 | BI37: TEC | BJ37: Tampa Electric | BO37: https://centersquaredc.com/hubfs/CenterSquare/docs/Centersquare-TPA-SpecSheet.pdf | BP37: https://maps.app.goo.gl/vgyxnp8X5iTPx88bA | BU37: 45474 | BV37: 46120 | BW37: 46238
A38: 298cca0f-2671-4a1e-acd9-3ea4a35fe0c2 | B38: BOS4 Waltham Data Center Campus | E38: Active | I38: 8d42255d-b8b4-474e-bab6-890f808f2aa6 | J38: Centersquare | K38: https://www.centersquaredc.com | L38: Private | P38: Brookfield | T38: 486 Arsenal Way, Watertown, MA, USA | U38: 2472 | V38: 25017 | W38: Middlesex County | X38: Watertown | Z38: MA | AA38: Massachusetts | AB38: US | AC38: United States | AD38: 42.366096 | AE38: -71.15936 | AG38: 201590 | AH38: 201590 | AI38: 15 | AJ38: 16.86 | AK38: 16.07 | AL38: 17.67 | AM38: 15 | AT38: 36923 | AW38: 37406 | BH38: 1164f15f-eb65-4d74-9a7e-72f721f4080f | BI38: ISNE | BJ38: ISO New England | BK38: f6648419-87f7-4033-9984-dae4c5376c5e | BL38: 4008 | BM38: ISNE - Northeast Mass. | BO38: https://centersquaredc.com/hubfs/CenterSquare/docs/Centersquare-BOS-SpecSheet.pdf | BP38: https://maps.app.goo.gl/x7fWMQE5qQQDPvA57 | BU38: 45474 | BV38: 46120 | BW38: 46238
A39: 8bb748c9-8fc6-4229-b206-37cc6ce8ff49 | B39: COL4-S Columbus Data Center | C39: 64ce618e-991d-4a23-be87-b07e189dde18 | D39: Columbus, Cologix Campus | E39: Active | I39: 464d9ff8-e3fa-4a1f-98fc-a729d4896f05 | J39: Cologix | K39: https://www.cologix.com | L39: Private | T39: 7500 Alta View Boulevard, Columbus, OH, USA | U39: 43085 | V39: 39049 | W39: Franklin County | X39: Columbus | Y39: 18000 | Z39: OH | AA39: Ohio | AB39: US | AC39: United States | AD39: 40.118446 | AE39: -82.999374 | AG39: 256000 | AH39: 256000 | AI39: 50 | AJ39: 33.65 | AK39: 32.09 | AL39: 35.28 | AM39: 50 | AO39: 1.25 | AP39: 25 | AT39: 45047 | AW39: 45536 | BA39: ec0c98b2-a379-4b98-b41b-89a6507bdc42 | BB39: City of Westerville - (OH) | BC39: 20477 | BD39: Public (Municipality) | BH39: 35f051b0-f1ce-470d-81d2-ea5c0d197f3a | BI39: PJM | BJ39: PJM Interconnection | BK39: b1618d6a-8bed-43db-bbf9-70933b83f636 | BL39: AEP | BM39: American Electric Power zone - PJM | BO39: https://cologix.com/wp-content/uploads/2023/09/COL4-HYPER-Data-Center-Spec-Sheet.pdf | BP39: https://maps.app.goo.gl/kky5ssoZQwFUMvMh9 | BU39: 45474 | BV39: 46230 | BW39: 46238
A40: d40ce920-2468-11f0-ad1d-d192baecfac4 | B40: Van Data Center | E40: Announcement | F40: Y | I40: 00fee91b-e84a-40b8-bd70-5fe87d3d93bd | J40: Company Not Disclosed | L40: Private | Q40: Belltown Power | T40: 4141 FM1995, Van, TX 75790, USA | U40: 75790 | V40: 48467 | W40: Van Zandt County | X40: Van | Y40: 74912 | Z40: TX | AA40: Texas | AB40: US | AC40: United States | AD40: 32.495937 | AE40: -95.63311 | AI40: 140 | AM40: 140 | AQ40: 45772 | AU40: 46202 | AV40: 0 | AW40: 47208 | AX40: 47208 | BA40: 14246342-1edf-4a4e-825c-0bf93f13d201 | BB40: Oncor Electric Delivery Company LLC | BC40: 44372 | BH40: 1fc90153-5419-4455-91f9-cee1dda4ed00 | BI40: ERCO | BJ40: Electric Reliability Council of Texas | BK40: 0dd36674-66fb-4ce3-b35e-1dd789fd0bbc | BL40: EAST | BM40: ERCO - East | BO40: https://belltownpower.com/us/belltown-power-projects/ | BP40: https://maps.app.goo.gl/sQcerNhPmgw8XRKr9 | BS40: Medium | BT40: [2025-04-28 JR] Additional Info: Belltown Power behind this project | BU40: 45775 | BV40: 46204 | BW40: 46238
A41: 912a5618-5337-451e-827d-53488b803a4e | B41: Balico LLC Data Center 2 | C41: 79e16210-5dab-11f0-aa7a-3f0352f32252 | D41: Balico LLC Data Center Campus | E41: Not Approved/Withdrawn | G41: Y | H41: 8800000000 | I41: 00fee91b-e84a-40b8-bd70-5fe87d3d93bd | J41: Company Not Disclosed | L41: Private | T41: 953 Co Rd 691, Chatham, VA, USA | U41: 24531 | V41: 51143 | W41: Pittsylvania County | X41: Chatham | Y41: 15000 | Z41: VA | AA41: Virginia | AB41: US | AC41: United States | AD41: 36.84591 | AE41: -79.33594 | AF41: 747 | AG41: 396000 | AH41: 396000 | AJ41: 61.61 | AK41: 58.76 | AL41: 64.61 | AM41: 61.61 | AQ41: 45593 | AS41: 45754 | AW41: 46934 | BA41: aad96398-bfaf-414f-8e4c-bf369c73e5da | BB41: Appalachian Power Co | BC41: 733 | BH41: 35f051b0-f1ce-470d-81d2-ea5c0d197f3a | BI41: PJM | BJ41: PJM Interconnection | BK41: 469a7dc0-fc5e-4f8e-8184-301f28134241 | BL41: DOM | BM41: Dominion Virginia Power zone - PJM | BN41: f4676150-9723-4d88-a35a-b2e85575a6a3 | BO41: https://virginiabusiness.com/proposed-8-8b-pittsylvania-data-center-campus-hits-roadblock/ | BP41: https://maps.app.goo.gl/6kqE8NcohZLdbsB89 | BS41: Low | BT41: [2025-01-13 JR] Latest Satellite: [N/A]; Construction Status: No Construction; Additional Info: Waiting for Approval_x000D_ [2025-02-27 JR] BTM: 300 MW; Power Source: Natural Gas_x000D_ [2025-07-10 JR] Additional Info: Pittsylvania County supervisors denied Balico’s rezoning request and blocked its withdrawal. The developer must wait one year before reapplying. | BU41: 45670 | BV41: 46202 | BW41: 46238
A42: 6ce834b4-afd0-492c-94a1-cc40c3bc66f9 | B42: Bells Ferry Data Center 2 | C42: bfbd8c80-4c5f-11f0-b5f9-7d80e43fd947 | D42: Campus Data Center Bells Ferry Marietta | E42: Announcement | I42: 00fee91b-e84a-40b8-bd70-5fe87d3d93bd | J42: Company Not Disclosed | L42: Private | P42: Grincap | T42: 1751 Bells Ferry Rd, Marietta, GA 30066, USA | U42: 30066 | V42: 13067 | W42: Cobb County | X42: Marietta | Y42: 49756 | Z42: GA | AA42: Georgia | AB42: US | AC42: United States | AD42: 33.994244 | AE42: -84.55368 | AG42: 347200 | AH42: 133600 | AI42: 36 | AJ42: 32.19 | AK42: 30.7 | AL42: 33.76 | AM42: 36 | AN42: 24 | AQ42: 45800 | AU42: 46207 | AV42: 0 | AW42: 47117 | AX42: 47117 | BH42: fc5d245b-5d3e-4004-b00a-666a73bde91d | BI42: SOCO | BJ42: Southern Company | BO42: https://www.mdjonline.com/news/local/marietta-approves-data-center-on-bells-ferry/article_ebbc4bef-8253-4071-b112-3dc91100c89d.html,https://www.mariettaga.gov/AgendaCenter/ViewFile/Item/5786?fileID=57354,https://citizenportal.ai/Search/View?dp=1&key=3741363-a116ad4db664026a5cce5f69b7edbef2&start=1844&end=2763 | BP42: https://maps.app.goo.gl/39s8izXTqrGPZqui6 | BQ42: https://www.mariettaga.gov/AgendaCenter/ViewFile/Item/5786?fileID=57354 | BS42: High | BT42: [2025-06-18 DP] Additional Info: MMM Acquisitions LLC behind this project._x000D_ [2026-05-19 JH] Additional Info: Activation Date updated from 2027-11-30 to Q4 2028 | BU42: 45826 | BV42: 46230 | BW42: 46238
A43: 3d6be780-4c55-4bc1-a503-564148f111aa | B43: Sailfish Digital Ventures Campus E Data Center 2 | C43: af3a69e5-4ae5-4c11-bc83-6afd159a284f | D43: Comanche Circle | E43: Announcement | G43: Y | I43: 00fee91b-e84a-40b8-bd70-5fe87d3d93bd | J43: Company Not Disclosed | L43: Private | T43: 6760-6780 FM 51, Tolar, TX, USA | U43: 76476 | V43: 48221 | W43: Hood County | X43: Tolar | Y43: 73268 | Z43: TX | AA43: Texas | AB43: US | AC43: United States | AD43: 32.287563 | AE43: -97.87922 | AF43: 2600 | AG43: 450000 | AH43: 450000 | AI43: 100 | AJ43: 66.15 | AK43: 63.08 | AL43: 69.36 | AM43: 100 | AQ43: 45678 | AU43: 46207 | AV43: 0 | AW43: 47756 | AX43: 47756 | AY43: 47118 | AZ43: https://becoration.com/sailfish-digital-ventures-launches-comanche-circle-a-2600-acre-data-center-community-in-the-dallas-metro/,https://becoration.com/sailfish-digital-ventures-launches-comanche-circle-a-2600-acre-data-center-community-in-the-dallas-metro/,https://hoodcountytx.documents-on-demand.com/Document/576d9938-63cd-419e-acb5-5bbc6af4ebe4/Comanche%20Circle%20Preliminary%20Traffic%20Due%20Diligence.pdf | BA43: e3162791-f814-4b28-a33e-beccc8f93039 | BB43: United Electric Coop Service Inc - (TX) | BC43: 19490 | BH43: 1fc90153-5419-4455-91f9-cee1dda4ed00 | BI43: ERCO | BJ43: Electric Reliability Council of Texas | BK43: 14cc320b-3a3d-47a9-83a4-e27eff5c1700 | BL43: NCEN | BM43: ERCO - North Central | BO43: https://www.linkedin.com/posts/ryansailfish_ptc25-datacenters-hyperscalers-activity-7287223617375858689-F5CL/,https://citizenportal.ai/articles/7014269/Hood-County-hears-residents-concerns-and-readies-legal-work-to-regulate-incoming-data-centers-and-power-plants,https://thetechcapital.com/sailfish-digital-ventures-unveils-2600-acre-data-centre-community-in-dallas/,https://www.keranews.org/government/2026-06-09/hood-county-approves-comanche-circle-data-center-without-conditions-after-contentious-meeting | BP43: https://maps.app.goo.gl/ja1vjmLqPHHksag98 | BQ43: https://www.tceq.texas.gov/assets/public/permitting/air/reports/applications/398373-ac.pdf,https://cohoodtxus-my.sharepoint.com/personal/blampert_hoodcounty_texas_gov/_layouts/15/onedrive.aspx?id=%2Fpersonal%2Fblampert%5Fhoodcounty%5Ftexas%5Fgov%2FDocuments%2FPUBLIC%20AGENDAS%2F2026%2F01%2E13%2E2026%20Public%20Agenda%2F01%2E13%2E2026%20Public%20Backup%2FIX%2EA%2E2%2Ee%2EComanche%20Circle%20%2D%20Concept%20Plan%2Epdf&parent=%2Fpersonal%2Fblampert%5Fhoodcounty%5Ftexas%5Fgov%2FDocuments%2FPUBLIC%20AGENDAS%2F2026%2F01%2E13%2E2026%20Public%20Agenda%2F01%2E13%2E2026%20Public%20Backup&ga=1 | BS43: High | BT43: [2025-01-21 JR] Latest Satellite:[N/A]; Construction Status: No Construction; Estimated Active Date By: Developer; Power Source: Nuclear; Additional Info: Location Details to be updated, Area Estimated by Aterio. Comanche Peak Nuclear Power Plant to provide the Power_x000D_ [2025-01-23 JR] Additional Info: Sailfish Digital Ventures behind this project._x000D_ [2025-09-11 DP] BTM: Power: 600 MW Source: Natural gas, Solar, SMRs_x000D_ [2026-01-15 JR] Additional Info: The Hood County Comanche Circle data center proposal received conditional approval from county commissioners. Project likelihood upgrade from Medium to High._x000D_ [2026-06-11 JH] Additional Info: Hood County Commissioners Court voted 3-1 on June 9, 2026 to approve the Comanche Circle concept plan without conditions, allowing the project to advance to the site development plan review phase._x000D_ [2026-06-25 AV] Additional Info: Given that the concept plan was just approved on June 2026, the construction is yet to begin, making the 2027 operational target not plausible. Activation date updated from 2028-11-30 to Q3 2030. | BU43: 45679 | BV43: 46220 | BW43: 46238
A44: 0cf3cee7-6bc0-48d9-a6b5-d5c155d71e0f | B44: GWV Data Center 4 | C44: 48d92990-731e-11f0-94fd-276165592f34 | D44: GWV Data Center Campus | E44: Announcement | I44: 00fee91b-e84a-40b8-bd70-5fe87d3d93bd | J44: Company Not Disclosed | L44: Private | T44: 1136 Kellogg Mill Rd, Stafford, VA 22554, USA | U44: 22554 | V44: 51179 | W44: Stafford County | X44: Stafford | Z44: VA | AA44: Virginia | AB44: US | AC44: United States | AD44: 38.418736 | AE44: -77.44836 | AF44: 1042 | AH44: 412737 | AJ44: 61.99 | AK44: 59.11 | AL44: 65.01 | AM44: 61.99 | AQ44: 45580 | AU44: 46216 | AV44: 0 | AW44: 47482 | AX44: 47482 | BH44: 35f051b0-f1ce-470d-81d2-ea5c0d197f3a | BI44: PJM | BJ44: PJM Interconnection | BK44: 469a7dc0-fc5e-4f8e-8184-301f28134241 | BL44: DOM | BM44: Dominion Virginia Power zone - PJM | BO44: https://staffordcountyva.gov/government/departments_p-z/planning_and_zoning/long_range/rezonings,_cups,_comp_plan_amendments/development_review_meetings_new_applications.php | BP44: https://maps.app.goo.gl/4SumL2ciTB4pt7jJ6 | BQ44: https://cdn.staffordcountyva.gov/Planning%20and%20Zoning/Development%20Review%20Meetings-Applications/December%202024/GWV%20Data%20Center%20Reclass/3-%20Impact%20Statement%20(10-15-24)%20-%20GWV%20Data%20Center.pdf | BS44: Medium | BT44: [2025-08-06 JR] Additional Info: The Garrett Companies behind this development, project In review_x000D_ [2026-06-30 DS] Additional Info: Updated estimated activation date from 2028-06-01 to 2029-12-30. | BU44: 45875 | BV44: 46217 | BW44: 46238
A45: 1c31dc19-cc88-4518-a01b-05a2f8445d59 | B45: Hancock Cty MegaSite Data Center 2 | C45: 36305490-2151-11f0-88d2-6735b8e9da9c | D45: Hancock County MegaSite | E45: Not Approved/Withdrawn | I45: 00fee91b-e84a-40b8-bd70-5fe87d3d93bd | J45: Company Not Disclosed | L45: Private | T45: 3400 W 500 N, McCordsville, IN 46055, USA | U45: 46055 | V45: 18059 | W45: Hancock County | X45: McCordsville | Y45: 45648 | Z45: IN | AA45: Indiana | AB45: US | AC45: United States | AD45: 39.857494 | AE45: -85.8682 | AQ45: 45744 | AS45: 45790 | AW45: 48731 | BH45: cead66ff-8552-43d5-b723-aeedd7318b2b | BI45: MISO | BJ45: Midcontinent Independent System Operator | BK45: db5c3610-9541-4fce-8b84-9ebdae7451f4 | BL45: 6 | BM45: Zone 6 - MISO | BO45: https://www.hancockin.gov/DocumentCenter/View/1940/Hancock-County-MegaSite-PUD---Preliminary-Plan---3282025,https://www.greenfieldreporter.com/2025/05/13/statement-from-surge-development/ | BP45: https://maps.app.goo.gl/HT6eeoCSBkXySVgf6 | BS45: Low | BT45: [2025-04-24] Additional Info: Surge Development behind this project. Highly likely this would be a Google Campus due to the images in the submission plans._x000D_ [2025-05-19 JR] Additional Info: The developer has decided to formally withdraw the current zoning request. | BU45: 45771 | BV45: 46120 | BW45: 46238
A46: c69be86e-dd3d-413d-8459-36d369a5e81b | B46: Hypergrid AI Data Center 21 | C46: da3a3e80-5373-11f0-856b-bd065fb7a39b | D46: HyperGrid Data Center Campus | E46: Announcement | F46: Y | G46: Y | I46: 00fee91b-e84a-40b8-bd70-5fe87d3d93bd | J46: Company Not Disclosed | L46: Private | Q46: Fermi America, Hyundai E&C | R46: Macquarie Asset Management, MVM EGI | T46: 89FQ+6PC Amarillo, Texas, USA | U46: 79068 | V46: 48065 | W46: Carson County | X46: Panhandle | Y46: 54960 | Z46: TX | AA46: Texas | AB46: US | AC46: United States | AD46: 35.317142 | AE46: -101.60523 | AF46: 5769 | AH46: 400000 | AI46: 250 | AJ46: 57.55 | AK46: 54.88 | AL46: 60.35 | AM46: 250 | AQ46: 45834 | AU46: 46230 | AV46: 0 | AW46: 48579 | AX46: 48579 | BA46: 98094d71-7688-49b8-9a5a-0a2443f3a8e3 | BB46: Southwestern Public Service Co | BC46: 17718 | BD46: Public | BE46: XEL | BF46: XEL:US | BG46: NASDAQ:XEL | BH46: 6b0bfc20-3ceb-4b9b-a50c-902a490a7db9 | BI46: SWPP | BJ46: Southwest Power Pool | BN46: 869d075d-a069-59cf-81ee-4ef41daf4198 | BO46: https://amarillotribune.org/2025/06/26/breaking-advanced-nuclear-energy-ai-campus-hypergrid-coming-to-amarillo/,https://www.world-nuclear-news.org/articles/fermi-america-hyundai-ec-team-up-for-texan-reactors,https://www.prnewswire.com/news-releases/fermi-america-and-mvm-egi-announce-water-saving-hybrid-cooling-agreement-for-worlds-largest-private-energy-grid-delivering-on-promises-made-to-protect-west-texas-water-resources-302628904.html,https://app.quotemedia.com/data/downloadFiling?webmasterId=102691&ref=319641038&type=PDF&cdn=4252e262ac8486a79e9ba109796598ab&formType=8-K&formDescription=Current+report+pursuant+to+Section+13+or+15%28d%29&dateFiled=2025-12-12&cik=2071778 | BP46: https://maps.app.goo.gl/WxPuN2YZE7z1sT447 | BQ46: https://www.nrc.gov/docs/ML2516/ML25169A396.pdf,https://www.tceq.texas.gov/assets/public/permitting/air/reports/applications/396274-ac.pdf | BS46: Low | BT46: [2025-06-27 JR] BTM: To be powered in a mix of nuclear, gas, solar, battery storage; Additional Info: Fermi America behind this project_x000D_ [2025-09-10 JR] Additional Info: Fermi America signed an MoU with Hyundai Engineering & Construction to plan and develop the nuclear component of its private grid, set to become the world’s largest AI-dedicated energy system._x000D_ [2026-01-28 AV] Additional Info: Activation date updated from 2029-09-01._x000D_ [2026-04-14 JR] Additional Info: Project facing delays; Activation date updated from 2029-06-01 to Q4 2032. | BU46: 45835 | BV46: 46231 | BW46: 46238
A47: 34158b94-b5c6-4233-913d-583cf75be9ff | B47: Hypergrid AI Data Center 5 | C47: da3a3e80-5373-11f0-856b-bd065fb7a39b | D47: HyperGrid Data Center Campus | E47: Announcement | F47: Y | G47: Y | I47: 00fee91b-e84a-40b8-bd70-5fe87d3d93bd | J47: Company Not Disclosed | L47: Private | Q47: Fermi America, Hyundai E&C | R47: Macquarie Asset Management, MVM EGI | T47: 89FQ+6PC Amarillo, Texas, USA | U47: 79068 | V47: 48065 | W47: Carson County | X47: Panhandle | Y47: 54960 | Z47: TX | AA47: Texas | AB47: US | AC47: United States | AD47: 35.317142 | AE47: -101.60523 | AF47: 5769 | AH47: 400000 | AI47: 250 | AJ47: 57.55 | AK47: 54.88 | AL47: 60.35 | AM47: 250 | AQ47: 45834 | AU47: 46230 | AV47: 0 | AW47: 47391 | AX47: 47391 | BA47: 98094d71-7688-49b8-9a5a-0a2443f3a8e3 | BB47: Southwestern Public Service Co | BC47: 17718 | BD47: Public | BE47: XEL | BF47: XEL:US | BG47: NASDAQ:XEL | BH47: 6b0bfc20-3ceb-4b9b-a50c-902a490a7db9 | BI47: SWPP | BJ47: Southwest Power Pool | BN47: 869d075d-a069-59cf-81ee-4ef41daf4198 | BO47: https://amarillotribune.org/2025/06/26/breaking-advanced-nuclear-energy-ai-campus-hypergrid-coming-to-amarillo/,https://www.world-nuclear-news.org/articles/fermi-america-hyundai-ec-team-up-for-texan-reactors,https://www.prnewswire.com/news-releases/fermi-america-and-mvm-egi-announce-water-saving-hybrid-cooling-agreement-for-worlds-largest-private-energy-grid-delivering-on-promises-made-to-protect-west-texas-water-resources-302628904.html,https://app.quotemedia.com/data/downloadFiling?webmasterId=102691&ref=319641038&type=PDF&cdn=4252e262ac8486a79e9ba109796598ab&formType=8-K&formDescription=Current+report+pursuant+to+Section+13+or+15%28d%29&dateFiled=2025-12-12&cik=2071778 | BP47: https://maps.app.goo.gl/WxPuN2YZE7z1sT447 | BQ47: https://www.nrc.gov/docs/ML2516/ML25169A396.pdf,https://www.tceq.texas.gov/assets/public/permitting/air/reports/applications/396274-ac.pdf | BS47: Low | BT47: [2025-06-27 JR] BTM: To be powered in a mix of nuclear, gas, solar, battery storage; Additional Info: Fermi America behind this project_x000D_ [2025-09-10 JR] Additional Info: Fermi America signed an MoU with Hyundai Engineering & Construction to plan and develop the nuclear component of its private grid, set to become the world’s largest AI-dedicated energy system._x000D_ [2026-01-28 AV] Additional Info: Activation date updated from 2027-01-01._x000D_ [2026-04-14 JR] Additional Info: Project facing delays; Activation date updated from 2027-06-01 to Q3 2029. | BU47: 45835 | BV47: 46231 | BW47: 46238
A48: 0f981e6f-7ab2-4c04-814f-6615043f0e95 | B48: Karis Acquisitions DeKalb Project Building 1 | C48: 48ad6670-c5a3-11f0-a02d-59d07397f0fa | D48: Karis Acquisitions DeKalb Campus | E48: Announcement | I48: 00fee91b-e84a-40b8-bd70-5fe87d3d93bd | J48: Company Not Disclosed | L48: Private | T48: Peace Rd, DeKalb, IL | U48: 60115 | V48: 17037 | W48: Dekalb County | X48: Dekalb | Z48: IL | AA48: Illinois | AB48: US | AC48: United States | AD48: 41.894753 | AE48: -88.72397 | AF48: 132 | AG48: 250000 | AH48: 250000 | AI48: 60 | AJ48: 49.36 | AK48: 47.07 | AL48: 51.76 | AM48: 60 | AQ48: 45495 | AU48: 46205 | AV48: 0 | AW48: 46736 | BA48: 222a249b-639d-4c33-9bba-36724efea762 | BB48: Commonwealth Edison Co | BC48: 4110 | BD48: Private (Part of Exelon Corp) | BE48: EXC | BF48: EXC:US | BG48: NASDAQ:EXC | BH48: 35f051b0-f1ce-470d-81d2-ea5c0d197f3a | BI48: PJM | BJ48: PJM Interconnection | BK48: e84646c2-7438-4a4c-916e-953518bd940a | BL48: CE | BM48: Commonwealth Edison zone - PJM | BO48: https://www.stwnewspress.com/news/city-moves-forward-in-approval-process-for-possible-data-center-campus/article_b46b6616-460e-11ef-ad4a-ffec327049cd.html | BP48: https://maps.app.goo.gl/yH3cHrz6AdKfTxrB9 | BS48: Low | BT48: [2026-07-25 JR] Additional Info: No recent fillings since 2024, Likelihood updated to Low. Capacity added based on 2024 fillings. | BU48: 45615 | BV48: 46230 | BW48: 46238
A49: 14ab4cf3-8f93-459f-8c24-88f3657d14ce | B49: Beech Building 1 | C49: 36b8805c-5d7c-4c47-ae82-0bd96b0c1928 | D49: New Albany Tech Park | E49: Announcement | G49: Y | I49: 00fee91b-e84a-40b8-bd70-5fe87d3d93bd | J49: Company Not Disclosed | L49: Private | T49: 3026-3050 Co Hwy 26, Johnstown, OH 43031 | U49: 43031 | V49: 39089 | W49: Licking County | X49: Johnstown | Y49: 39340 | Z49: OH | AA49: Ohio | AB49: US | AC49: United States | AD49: 40.100773 | AE49: -82.72356 | AG49: 414725 | AH49: 414725 | AJ49: 60.64 | AK49: 57.83 | AL49: 63.59 | AM49: 60.64 | AQ49: 44952 | AU49: 46205 | AV49: 0 | AW49: 46476 | AX49: 46476 | BA49: 030eb1d3-5a7a-41c1-adf2-ff1890871e2f | BB49: Ohio Power Co | BC49: 14006 | BD49: Public | BE49: AEP | BF49: AEP:US | BG49: NASDAQ:AEP | BH49: 35f051b0-f1ce-470d-81d2-ea5c0d197f3a | BI49: PJM | BJ49: PJM Interconnection | BK49: b1618d6a-8bed-43db-bbf9-70933b83f636 | BL49: AEP | BM49: American Electric Power zone - PJM | BO49: https://edocpub.epa.ohio.gov/publicportal/ViewDocument.aspx?docid=2151724,https://dis.puc.state.oh.us/CaseRecord.aspx?Caseno=25-0133&link=DIVA7 | BP49: https://maps.app.goo.gl/frZPpbuBPo5NYYmF9 | BS49: High | BT49: [2024-12-19 JR] Latest Satellite: 2024-10-09; Construction Status: Site Preparation; Estimated Active Date By: Aterio_x000D_ [2025-01-20 JR] BTM: Fuel Cell Power; Additional Info: Proposed by AEP_x000D_ [2025-07-23 JR] Additional Info: Originally identified as a data center, but it is now confirmed to be an Intel manufacturing facility under construction. Record updated to reflect correct project address._x000D_ [2025-11-12 JR] Construction: No construction visible; Additional Info: Activation date updated from 2026-03-30 | BU49: 45631 | BV49: 46224 | BW49: 46238
A50: 280072c8-9ac7-4ebb-984a-f978c6845713 | B50: Potomac Creek Data Center 2 | C50: 4013bb90-7323-11f0-bdb4-f5958a56ba32 | D50: Potomac Creek Campus | E50: Announcement | I50: 00fee91b-e84a-40b8-bd70-5fe87d3d93bd | J50: Company Not Disclosed | L50: Private | T50: 158 Musante Ln, Stafford, VA 22554, USA | U50: 22554 | V50: 51179 | W50: Stafford County | X50: Stafford | Z50: VA | AA50: Virginia | AB50: US | AC50: United States | AD50: 38.37449 | AE50: -77.43672 | AF50: 99 | AH50: 325000 | AJ50: 64.77 | AK50: 61.77 | AL50: 67.92 | AM50: 64.77 | AQ50: 45576 | AU50: 46204 | AV50: 0 | AW50: 46645 | AX50: 46645 | BH50: 35f051b0-f1ce-470d-81d2-ea5c0d197f3a | BI50: PJM | BJ50: PJM Interconnection | BK50: 469a7dc0-fc5e-4f8e-8184-301f28134241 | BL50: DOM | BM50: Dominion Virginia Power zone - PJM | BO50: https://staffordcountyva.gov/government/departments_p-z/planning_and_zoning/long_range/rezonings,_cups,_comp_plan_amendments/development_review_meetings_new_applications.php | BP50: https://maps.app.goo.gl/cQ5VU87vHqqE2jyt6 | BQ50: https://cdn.staffordcountyva.gov/Planning%20and%20Zoning/Development%20Review%20Meetings-Applications/February%202025/Potomac%20Creek%20Rezoning/4%20-%20Generalized%20Development%20Plan%20(9-4-24)%20-%20Potomac%20Creek%20Campus.pdf | BS50: Medium | BT50: [2025-08-07] Additional Info: Elm Street Development behind this project, Project under review_x000D_ [2026-04-22 JH] Construction: No visible construction activity observed on site._x000D_ [2026-07-14 JH] Additional Info: The project was paused after discovery of a 200-year-old cemetery believed to contain graves of enslaved individuals. The Board deferred a final decision, giving the developer 6–8 weeks to conduct archaeological and genealogical research before revisiting the case in approximately two months. | BU50: 45875 | BV50: 46224 | BW50: 46238
A51: 82b46cad-f34d-4c23-9397-9f681745f221 | B51: Project Cardinal Data Center 4 | C51: cf200f90-08d0-11f0-a8ef-3197c5e8f560 | D51: Project Cardinal Data Center Campus | E51: Announcement | I51: 00fee91b-e84a-40b8-bd70-5fe87d3d93bd | J51: Company Not Disclosed | L51: Private | T51: 10321 Galena Rd, Yorkville, IL 60560, USA | U51: 60560 | V51: 17093 | W51: Kendall County | X51: Yorkville | Y51: 84038 | Z51: IL | AA51: Illinois | AB51: US | AC51: United States | AD51: 41.713676 | AE51: -88.45592 | AF51: 1037 | AH51: 172727 | AI51: 144 | AJ51: 30.66 | AK51: 29.24 | AL51: 32.15 | AM51: 144 | AQ51: 45735 | AU51: 46216 | AV51: 0 | AW51: 47664 | AX51: 47664 | BH51: 35f051b0-f1ce-470d-81d2-ea5c0d197f3a | BI51: PJM | BJ51: PJM Interconnection | BK51: e84646c2-7438-4a4c-916e-953518bd940a | BL51: CE | BM51: Commonwealth Edison zone - PJM | BO51: https://www.yorkville.il.us/906/Project-Cardinal-Data-Center-Campus-Anne | BP51: https://maps.app.goo.gl/aw2FQT4epqWThHRHA | BQ51: https://www.yorkville.il.us/906/Project-Cardinal-Data-Center-Campus-Anne,https://www.yorkville.il.us/DocumentCenter/View/11734/Project-Cardinal-Site-Plan-82625?bidId= | BS51: Medium | BT51: [2025-03-24 JR] Additional Info: Galena & 47th, LLC, MPLIV10, LLC, Sanjay and Sameer Gupta, Dale L. Konicek, LLC, and The Konicek Family Limited Partnership Behind this project | BU51: 45740 | BV51: 46218 | BW51: 46238
A52: 399ed007-2622-4fb6-96d4-77ada65c945c | B52: Project Turbo - DC2 | C52: 40187c20-79ea-11f0-b122-4bfc80ab2cb9 | D52: Project Turbo | E52: Announcement | H52: 1200000000 | I52: 00fee91b-e84a-40b8-bd70-5fe87d3d93bd | J52: Company Not Disclosed | L52: Private | T52: 2400 O'Kelly Rd, Gainesville, GA 30507, USA | U52: 30507 | V52: 13139 | W52: Hall County | X52: Gainesville | Y52: 31908 | Z52: GA | AA52: Georgia | AB52: US | AC52: United States | AD52: 34.22433 | AE52: -83.78057 | AG52: 300000 | AH52: 300000 | AJ52: 58.92 | AK52: 56.18 | AL52: 61.78 | AM52: 58.92 | AQ52: 45883 | AU52: 46205 | AV52: 0 | AW52: 46905 | AX52: 46905 | BA52: 435eef77-beb0-4620-9aae-8f86d110eb8c | BB52: Georgia Power Co | BC52: 7140 | BD52: Public | BE52: GPJA | BF52: GPB:US | BG52: NYSE:GPJA | BH52: fc5d245b-5d3e-4004-b00a-666a73bde91d | BI52: SOCO | BJ52: Southern Company | BO52: https://www.bizjournals.com/atlanta/news/2025/08/14/hall-county-data-center.html,https://projectturbollc.com/,https://accesswdun.com/news/proposed-data-center-developers-host-town-hall-ahead-of-thursdays-commission-vote | BP52: https://maps.app.goo.gl/BfWYVC7FnQCvCCqm9 | BQ52: https://apps.dca.ga.gov/DRI/AppSummary.aspx?driid=4522 | BS52: Medium | BT52: [2025-08-15 DP] Additional Info: Number of buildings and more details undisclosed_x000D_ [2025-11-25 JR] Additional Info: Project scope updated to 3 buildings from 4 | BU52: 45884 | BV52: 46230 | BW52: 46238
A53: 82c17240-8266-4c85-ad58-c98311863505 | B53: Delaware Data Center 6 | C53: 49ce17c0-5e60-11f0-a63f-3570276c3e86 | D53: Project Washington | E53: Not Approved/Withdrawn | I53: 00fee91b-e84a-40b8-bd70-5fe87d3d93bd | J53: Company Not Disclosed | L53: Private | R53: Starwood Capital Group | T53: J956+Q28 Bear, Delaware, USA | U53: 19720 | V53: 10003 | W53: New Castle County | X53: New Castle | Y53: 50800 | Z53: DE | AA53: Delaware | AB53: US | AC53: United States | AD53: 39.599567 | AE53: -75.64486 | AF53: 580 | AG53: 500000 | AH53: 500000 | AI53: 72 | AJ53: 72 | AK53: 68.58 | AL53: 75.59 | AM53: 72 | AQ53: 45847 | AS53: 46057 | AT53: 46249 | AU53: 46066 | AV53: 0 | AW53: 46858 | BA53: fe2043ac-466c-4d77-a6f5-e48a2d5e4d13 | BB53: Delmarva Power | BC53: 5027 | BD53: Public | BE53: EXC | BF53: EXC:US | BG53: NASDAQ:EXC | BH53: 35f051b0-f1ce-470d-81d2-ea5c0d197f3a | BI53: PJM | BJ53: PJM Interconnection | BK53: 1cd4a7ea-9f74-498e-8e4f-292b3c0ff5b9 | BL53: DPL | BM53: Delmarva Power null zone - PJM | BO53: https://www.bizjournals.com/philadelphia/news/2025/07/09/data-center-delaware-new-castle-starwood-digital.html,https://www3.newcastlede.gov/project/details/default.aspx?ProjectKey=826803 | BP53: https://maps.app.goo.gl/7dRGUEmuzgzjFgC17 | BQ53: https://www3.newcastlede.gov/project/details/default.aspx?ProjectKey=826789,https://www3.newcastlede.gov/project/details/default.aspx?ProjectKey=826803,https://projwashington.com/wp-content/uploads/2025/11/Project-Washington-Overview.pdf | BS53: Low | BT53: [2025-07-11 DP] Additional Info: STARWOOD CAPITAL GROUP MANAGEMENT LLC is behind this project_x000D_ [2026-03-02 JH] Additional Info: Project scope updated from 11 buildings to 10. The project status has been changed from announced to Not Approved Withdrawn because the state government has classified it as heavy polluting industry, so the likelihood has been changed to low. | BU53: 45849 | BV53: 46120 | BW53: 46238
A54: 2c88b8b7-c829-4a1e-a80e-676f4f6e757b | B54: Red Oak IV Dallas/Fort Worth | C54: 6d4bd14d-c689-4793-82bc-dbcb6032d4c9 | D54: Red Oak, Compass Campus | E54: Active | G54: Y | I54: 4d36f563-c7d0-41cd-b223-910670510228 | J54: Compass Datacenters | K54: https://www.compassdatacenters.com/ | L54: Private | P54: Brookfield Infrastructure Partners L.P. | S54: Microsoft | T54: 441 Austin Boulevard, Red Oak, TX | U54: 75154 | V54: 48139 | W54: Ellis County | X54: Red Oak | Y54: 61196 | Z54: TX | AA54: Texas | AB54: US | AC54: United States | AD54: 32.544346 | AE54: -96.80234 | AF54: 600 | AG54: 244000 | AH54: 244000 | AJ54: 25.64 | AK54: 24.45 | AL54: 26.89 | AM54: 25.64 | AP54: 36 | AQ54: 43599 | AT54: 45168 | AW54: 45595 | BA54: 14246342-1edf-4a4e-825c-0bf93f13d201 | BB54: Oncor Electric Delivery Company LLC | BC54: 44372 | BH54: 1fc90153-5419-4455-91f9-cee1dda4ed00 | BI54: ERCO | BJ54: Electric Reliability Council of Texas | BK54: 14cc320b-3a3d-47a9-83a4-e27eff5c1700 | BL54: NCEN | BM54: ERCO - North Central | BO54: https://www.compassdatacenters.com/news/compass-datacenters-begins-construction-on-75mw-data-center-campus-in-northern-virginia/,https://comptroller.texas.gov/taxes/data-centers/data-center-lists.php | BP54: https://maps.app.goo.gl/rqPHBDGVexa6n41o7 | BQ54: https://www.tceq.texas.gov/assets/public/permitting/air/reports/applications/37072-ac.pdf | BT54: [2024-12-19 JR] Latest Satellite: 2024-02-18; Construction Status: Construction 60%; Estimated Active Date By: Microsoft; Additional Info: Occupied by Microsoft_x000D_ [2025-01-07 JR] Additional Info: Stage Updated to Active_x000D_ [2025-09-11 DP] BTM: Speculation of an electrical generation system_x000D_ [2026-01-07 JR] Additional Info: Tax Data suggest Microsoft is leasing this campus._x000D_ [2026-02-20 DS] Additional Info: Updated number of buildings in the campus from 11 to 10 based on the air permit. | BU54: 45555 | BV54: 46120 | BW54: 46238
A55: ffe8422d-2d52-4416-8fa7-6184cb57afb9 | B55: Red Oak III Dallas/Fort Worth | C55: 6d4bd14d-c689-4793-82bc-dbcb6032d4c9 | D55: Red Oak, Compass Campus | E55: Active | G55: Y | I55: 4d36f563-c7d0-41cd-b223-910670510228 | J55: Compass Datacenters | K55: https://www.compassdatacenters.com/ | L55: Private | P55: Brookfield Infrastructure Partners L.P. | S55: Microsoft | T55: 481 N Austin Boulevard, Red Oak, TX | U55: 75154 | V55: 48139 | W55: Ellis County | X55: Red Oak | Y55: 61196 | Z55: TX | AA55: Texas | AB55: US | AC55: United States | AD55: 32.541523 | AE55: -96.802216 | AF55: 600 | AG55: 244000 | AH55: 244000 | AJ55: 25.64 | AK55: 24.45 | AL55: 26.89 | AM55: 25.64 | AP55: 38 | AQ55: 43599 | AT55: 44711 | AW55: 45107 | BA55: 14246342-1edf-4a4e-825c-0bf93f13d201 | BB55: Oncor Electric Delivery Company LLC | BC55: 44372 | BH55: 1fc90153-5419-4455-91f9-cee1dda4ed00 | BI55: ERCO | BJ55: Electric Reliability Council of Texas | BK55: 14cc320b-3a3d-47a9-83a4-e27eff5c1700 | BL55: NCEN | BM55: ERCO - North Central | BO55: https://www.compassdatacenters.com/news/compass-datacenters-begins-construction-on-75mw-data-center-campus-in-northern-virginia/,https://comptroller.texas.gov/taxes/data-centers/data-center-lists.php | BP55: https://maps.app.goo.gl/ZMZZkh9mAoLmYcnr8 | BQ55: https://www.tceq.texas.gov/assets/public/permitting/air/reports/applications/37072-ac.pdf | BT55: [2025-09-11 DP] BTM: Speculation of an electrical generation system_x000D_ [2026-01-07 JR] Additional Info: Tax Data suggest Microsoft is leasing this campus._x000D_ [2026-02-20 DS] Additional Info: Updated number of buildings in the campus from 11 to 10 based on the air permit. | BU55: 45555 | BV55: 46120 | BW55: 46238
A56: 9643ebc3-a6f9-426f-998f-1abc1c934f66 | B56: Dalton 2 - HPC Data Center | C56: 2aad8770-05cf-11f0-ae2d-8b22d6e45096 | D56: Core Scientific Dalton Campus | E56: Construction | I56: ddd8207f-ea0b-4aa7-925c-c3de48d0cda7 | J56: Core Scientific | K56: https://corescientific.com/ | L56: Public | M56: CORZ | N56: CORZ:US | O56: NASDAQ: CORZ | S56: CoreWeave | T56: 2205 Industrial South Rd, Dalton, GA 30721, United States | U56: 30721 | V56: 13313 | W56: Whitfield County | X56: Dalton | Y56: 21380 | Z56: GA | AA56: Georgia | AB56: US | AC56: United States | AD56: 34.697464 | AE56: -84.941864 | AG56: 250000 | AH56: 250000 | AI56: 145 | AJ56: 37.07 | AK56: 35.35 | AL56: 38.87 | AM56: 145 | AN56: 145 | AQ56: 45663 | AT56: 45778 | AU56: 46145 | AV56: 0.85 | AW56: 46477 | AX56: 46477 | AY56: 46477 | AZ56: https://finance.yahoo.com/quote/CORZ/earnings/CORZ-Q1-2026-earnings_call-578210.html | BH56: fc5d245b-5d3e-4004-b00a-666a73bde91d | BI56: SOCO | BJ56: Southern Company | BO56: https://corescientific.com/high-density-data-centers/dalton-ga-dnn1-2/, https://newschannel9.com/news/local/ai-data-center-to-occupy-10-acres-in-dalton-residents-worry-about-noise-and-disruption?photo=2 | BP56: https://maps.app.goo.gl/ZEXSQchSkdanB3HA7 | BS56: High | BT56: [2025-03-20 JR] Additional Info: Crypto data center converted to HPC Data Center_x000D_ [2026-03-06 DS] Additional Info: Campus details updated following corrections. The number of buildings has been revised from 5 to 3, and the capacity has been adjusted to reflect the disclosed figures from Core Scientific. The stage for Building 2 has been updated from Active to Construction. The building is being leased to CoreWeave. The estimated activation date has also been updated. | BU56: 45736 | BV56: 46202 | BW56: 46238
A57: 016a5328-50c1-4c65-bec6-14b56e528d5c | B57: SV9 Santa Clara Data Center | C57: 4551a132-90ef-4f4d-a488-a107cc88d93b | D57: CoreSite Santa Clara Campus | E57: Active | F57: Y | I57: ae69b1cb-8978-4d09-8925-88054b9a64a6 | J57: CoreSite | K57: https://www.coresite.com | L57: Private | P57: American Tower | T57: 2915 Stender Way, Santa Clara, CA | U57: 95054 | V57: 6085 | W57: Santa Clara County | X57: Santa Clara | Y57: 69084 | Z57: CA | AA57: California | AB57: US | AC57: United States | AD57: 37.37505 | AE57: -121.96986 | AG57: 240000 | AH57: 240000 | AI57: 34 | AJ57: 27.96 | AK57: 26.66 | AL57: 29.32 | AM57: 34 | AQ57: 45039 | AT57: 45047 | AW57: 45839 | BA57: 625b7686-055b-46e1-a5a4-4e3dcaf631b4 | BB57: Pacific Gas & Electric Co. | BC57: 14328 | BD57: Public | BE57: PCG | BF57: PCG:US | BG57: NYSE:PCG | BH57: 2950a9eb-39ef-4949-96bd-ecefbf7db624 | BI57: CISO | BJ57: California Independent System Operator | BK57: 9bbe5250-047e-4a37-8434-4cda4fceb9e5 | BL57: PGAE | BM57: Pacific Gas and Electric | BO57: https://www.coresite.com/hubfs/621d381a1dcae640fbe934e1_CoreSite-SV9-Presale-Brochure.pdf?__hstc=222326596.27595b1e361c5e057cdcf378d33509c4.1727669434384.1727748559681.1727749699683.6&__hssc=222326596.29195.1727748559681&__hsfp=81399884&hsutk=27595b1e361c5e057cdcf378d33509c4&contentType=standard-page | BP57: https://maps.app.goo.gl/8WG2oDu7zDSTgVk76 | BT57: [2024-12-19 JR] Latest Satellite: 2024-10-04; Construction Status: Construction 70%; Estimated Active Date By: Aterio; Additional Info: CoreSite’s SV9 data center is certified as part of the NVIDIA DGX-Ready Data Center program_x000D_ [2025-07-04 JR] Construction: Building and equipment partially in place with active parking lot use; site appears operational but likely not at full capacity. | BU57: 45615 | BV57: 46120 | BW57: 46238
A58: 10d5c18a-af45-40e9-8216-03b01736d628 | B58: DE3 Denver Data Center Building 3 | C58: 6f8f4a79-89e7-426a-9b15-b4fb25e4bc41 | D58: Denver DE3, Coresite Campus | E58: Announcement | I58: ae69b1cb-8978-4d09-8925-88054b9a64a6 | J58: CoreSite | K58: https://www.coresite.com | L58: Private | P58: American Tower | Q58: DPR Construction | R58: Stonepeak, American Tower | T58: 4900 Race St, Denver, CO, USA | U58: 80216 | V58: 8031 | W58: Denver County | X58: Denver | Y58: 20000 | Z58: CO | AA58: Colorado | AB58: US | AC58: United States | AD58: 39.787563 | AE58: -104.96175 | AG58: 112000 | AH58: 112000 | AI58: 21 | AJ58: 21.11 | AK58: 20.13 | AL58: 22.14 | AM58: 21 | AN58: 21 | AQ58: 45272 | AU58: 46216 | AV58: 0 | AW58: 47391 | AX58: 47391 | BA58: e9461aa4-9d9f-4b2b-99f7-a98a4ddae350 | BB58: Public Service Co of Colorado | BC58: 15466 | BD58: Public | BE58: XEL | BF58: XEL:US | BG58: NASDAQ:XEL | BH58: 2b7577ed-7734-4df0-a6b1-d8289badb9de | BI58: PSCO | BJ58: Xcel Energy (Colorado) | BO58: https://www.coresite.com/hubfs/CoreSite-Presale-DE3.pdf | BP58: https://maps.app.goo.gl/Dcren5WmhzmPzw4s9 | BS58: Medium | BT58: [2024-12-19 JR] Latest Satellite: 2024-11-10; Construction Status: Site Preparation; Estimated Active Date By: Aterio; Additional Info: This is a joint venture with Stonepeak that will own 85% of DE3_x000D_ [2025-10-30 DP] Construction: No visible changes since the last satellite image from 2025-10-2._x000D_ [2025-12-15 FC] Construction: No visible change in latest satellite image; Additional Info: Updating estimated activation date from 2026-05-31. Updated data sheet URL. Adding Stonepeak, DPR Construction and Xcel Energy as involved companies._x000D_ [2026-02-19 AV] Construction: No progress in construction, the area is being used as a parking lot. Additional Info: Activation Date updated from 2027-06-30 to Q2 2028._x000D_ [2026-07-20 JR] Construction: No visible progress; Additional Info: Activation Date updated from 2028-03-30 to Q3 2029. Stage reverted to Announcement to match phased construction. | BU58: 45615 | BV58: 46223 | BW58: 46238
A59: 6e819526-9e02-4921-8fc1-c4b6737120e9 | B59: Kincora Data Center | E59: Announcement | I59: b3de30b8-60e5-4243-b865-f77708cb01f2 | J59: Corscale | K59: https://corscale.com/ | L59: Private | P59: Patrinely Group | Q59: Kimley-Horn | T59: 45950 Russell Branch Pkwy, Sterling, VA | U59: 20166 | V59: 51107 | W59: Loudoun County | X59: Sterling | Y59: 75376 | Z59: VA | AA59: Virginia | AB59: US | AC59: United States | AD59: 39.037174 | AE59: -77.435265 | AH59: 500000 | AI59: 80 | AM59: 80 | AN59: 80 | AQ59: 44614 | AU59: 46231 | AV59: 0 | AW59: 47208 | AX59: 47208 | BH59: 35f051b0-f1ce-470d-81d2-ea5c0d197f3a | BI59: PJM | BJ59: PJM Interconnection | BK59: 469a7dc0-fc5e-4f8e-8184-301f28134241 | BL59: DOM | BM59: Dominion Virginia Power zone - PJM | BO59: https://www.datacenterfrontier.com/hyperscale/article/11427580/corscale-launches-its-data-center-platform-with-northern-virginia-campus,https://corscale.com/,https://loudouncountyvaeg.tylerhost.net/prod/selfservice#/plan/F79A57A3-38E2-4887-BD02-B5B691CD8ABF?tab=attachments | BP59: https://maps.app.goo.gl/EqdEeZdqsiy63ohy7 | BS59: Medium | BT59: [2024-12-19 JR] Latest Satellite: 2024-11-02; Construction Status: No Construction; Estimated Active Date By: Aterio; Additional Info: Project Delayed_x000D_ [2025-09-18 YK] Additional Info: Activation Date Updated._x000D_ [2026-04-08 JH] Construction: No visible construction activity observed on site._x000D_ [2026-07-28 JH] Additional Info: Activation date updated from 2027-08-31 to Q1 2029. | BU59: 45615 | BV59: 46232 | BW59: 46238
A60: 24ec6395-3dbd-4858-8d0e-61e933fc4a2b | B60: Gainesville Crossing Building 1 | C60: 8d833c08-4e23-4ff7-96dd-c336620315da | D60: Gainesville, Corescale Campus | E60: Active | I60: b3de30b8-60e5-4243-b865-f77708cb01f2 | J60: Corscale | K60: https://corscale.com/ | L60: Private | P60: Patrinely Group | R60: Blue Owl Capital | T60: 13760 University Blvd, Gainesville, VA | U60: 20155 | V60: 51153 | W60: Prince William County | X60: Gainesville | Y60: 30176 | Z60: VA | AA60: Virginia | AB60: US | AC60: United States | AD60: 38.802563 | AE60: -77.58256 | AF60: 130 | AG60: 470000 | AH60: 470000 | AI60: 72 | AJ60: 54.38 | AK60: 51.85 | AL60: 57.02 | AM60: 72 | AP60: 64 | AT60: 44470 | AW60: 45413 | BH60: 35f051b0-f1ce-470d-81d2-ea5c0d197f3a | BI60: PJM | BJ60: PJM Interconnection | BK60: 469a7dc0-fc5e-4f8e-8184-301f28134241 | BL60: DOM | BM60: Dominion Virginia Power zone - PJM | BO60: https://corscale.com/press-releases/corscale-begins-construction-on-its-second-building-at-gainesville-crossing-campus/,https://www.prnewswire.com/news-releases/newmark-arranges-975-million-financing-for-mission-critical-data-center-in-northern-virginia-302794227.html | BP60: https://maps.app.goo.gl/FyRWQMNZNPjr5ueQ7 | BT60: [2026-06-12 JH] Additional Info: Blue Owl Capital provided $975M in balance sheet financing for the project. | BU60: 45474 | BV60: 46185 | BW60: 46238
A61: 7bc58e79-d3bb-4943-bdb0-c0587fba5b27 | B61: CHI4 Chicago Aurora Data Center 1 | C61: af2950e8-4e38-4753-ba57-5745a964fcb2 | D61: Aurora 1, CyrusOne Campus | E61: Active | I61: e4c9daa2-cda6-420e-aa0d-3af89c5d7fec | J61: CyrusOne | K61: https://www.cyrusone.com | L61: Private | P61: KKR | T61: Illinois Prairie Path - Batavia Spur, Aurora, IL, USA | U61: 60502 | V61: 17043 | W61: Dupage County | X61: Aurora | Y61: 3012 | Z61: IL | AA61: Illinois | AB61: US | AC61: United States | AD61: 41.80247 | AE61: -88.24756 | AG61: 411175 | AH61: 411175 | AJ61: 50 | AK61: 47.72 | AL61: 52.4 | AM61: 50 | AN61: 40 | AP61: 22 | AQ61: 45567 | AT61: 45580 | AU61: 46064 | AV61: 1 | AW61: 46064 | BA61: 222a249b-639d-4c33-9bba-36724efea762 | BB61: Commonwealth Edison Co | BC61: 4110 | BD61: Private (Part of Exelon Corp) | BE61: EXC | BF61: EXC:US | BG61: NASDAQ:EXC | BH61: 35f051b0-f1ce-470d-81d2-ea5c0d197f3a | BI61: PJM | BJ61: PJM Interconnection | BK61: e84646c2-7438-4a4c-916e-953518bd940a | BL61: CE | BM61: Commonwealth Edison zone - PJM | BO61: https://www.cyrusone.com/resources/press-releases/cyrusone-breaks-ground-on-new-data-center-in-aurora_x000D_ -https://www.cyrusone.com/media-coverage-press-releases/cyrusone-breaks-ground-on-new-data-center-in-aurora_x000D_ https://gov-pritzker-newsroom.prezly.com/gov-pritzker-celebrates-new-cyrusone-data-center-groundbreaking | BP61: https://maps.app.goo.gl/KwyGikXa8fH5X4Vr5 | BT61: [2024-12-19 JR] Latest Satellite: 2024-08-26; Construction Status: Site Preparation; Estimated Active Date By: Aterio_x000D_ [2025-06-27 JR] Construction: Roof installation is partially complete; structural work progressing across different sections. Equipment staging and groundwork visible._x000D_ [2025-11-10 DP] Construction: Roof completed, generator and cooling equipment in place, crane work visible outside the building; Additional Info: Activation Date updated from 2025-11-30; Facility Space and Critical IT updated._x000D_ [2026-01-08 DS] Additional Info: Waiting for more recent Satellite Imagery to Confirm Activation._x000D_ [2026-01-19 DS] Construction: Exterior site work still pending, parking lot looks unfinished, most likely in/near commissioning phase; Additional Info: Updated activation date from 2025-12-15._x000D_ [2026-02-26 SQ] Construction: There is a lot of activity in the parking lot which suggest the activation of the building. Additional Info: Stage updated to Active. | BU61: 45615 | BV61: 46202 | BW61: 46238
A62: b11101b1-7c35-48eb-acb0-8feb6aeb7a66 | B62: PHX9 - Phoenix Data Center | C62: f3672a71-2215-40ca-bba8-f8f845647bc1 | D62: Chandler, CyrusOne Campus | E62: Announcement | I62: e4c9daa2-cda6-420e-aa0d-3af89c5d7fec | J62: CyrusOne | K62: https://www.cyrusone.com | L62: Private | P62: KKR | T62: 2335 South Ellis Street, Chandler, AZ, USA | U62: 85286 | V62: 4013 | W62: Maricopa County | X62: Chandler | Y62: 12000 | Z62: AZ | AA62: Arizona | AB62: US | AC62: United States | AD62: 33.273266 | AE62: -111.88338 | AF62: 85 | AI62: 36 | AM62: 36 | AU62: 46117 | AV62: 0.1 | AW62: 46508 | AX62: 46508 | BA62: 5f1c3274-a117-4201-b548-6a9e4b37f693 | BB62: Salt River Project | BC62: 16572 | BD62: Private | BH62: 4f4fe9e0-cb99-459e-9c12-6621c6e60461 | BI62: SRP | BJ62: Salt River Project | BO62: https://www.cyrusone.com/data-centers/north-america/arizona/phx1-phx8-phoenix | BP62: https://maps.app.goo.gl/aN1jcWrJ3CfMMR9c8 | BS62: Low | BT62: [2024-12-19 JR] Latest Satellite: 2024-11-14; Construction Status: Site Preparation; Estimated Active Date By: Aterio_x000D_ [2025-11-20 DS] Additional Info: Updated the activation date since there's no construction activity on-ground._x000D_ [2026-04-17 JH] Construction: No further progress observed. | BU62: 45615 | BV62: 46202 | BW62: 46238
A63: 2f0d4f13-1841-49a9-ae8a-5954132c1e64 | B63: PHX1- Phoenix Data Center | C63: f3672a71-2215-40ca-bba8-f8f845647bc1 | D63: Chandler, CyrusOne Campus | E63: Active | I63: e4c9daa2-cda6-420e-aa0d-3af89c5d7fec | J63: CyrusOne | K63: https://www.cyrusone.com | L63: Private | P63: KKR | T63: 2335 South Ellis Street, Chandler, AZ, USA | U63: 85286 | V63: 4013 | W63: Maricopa County | X63: Chandler | Y63: 12000 | Z63: AZ | AA63: Arizona | AB63: US | AC63: United States | AD63: 33.270977 | AE63: -111.88178 | AF63: 85 | AG63: 101470 | AH63: 101470 | AJ63: 8.24 | AK63: 7.86 | AL63: 8.64 | AM63: 8.24 | AP63: 8 | AT63: 41061 | AW63: 41365 | BA63: 5f1c3274-a117-4201-b548-6a9e4b37f693 | BB63: Salt River Project | BC63: 16572 | BD63: Private | BH63: 4f4fe9e0-cb99-459e-9c12-6621c6e60461 | BI63: SRP | BJ63: Salt River Project | BO63: https://www.cyrusone.com/data-centers/north-america/arizona/phx1-phx8-phoenix | BP63: https://maps.app.goo.gl/dcCEmLPcWMvmdGQ56 | BU63: 45474 | BV63: 46101 | BW63: 46238
A64: bc656a87-3b2f-427f-8066-7f587a0d5a46 | B64: BUILDING 1A | C64: 8a38ee50-7965-11f0-8054-c9b858f791a4 | D64: CyrusOne Broadlands Campus | E64: Announcement | I64: e4c9daa2-cda6-420e-aa0d-3af89c5d7fec | J64: CyrusOne | K64: https://www.cyrusone.com | L64: Private | T64: 2FMH+56R Broadlands, Virginia, USA | U64: 20148 | V64: 51107 | W64: Loudoun County | X64: Ashburn | Y64: 3320 | Z64: VA | AA64: Virginia | AB64: US | AC64: United States | AD64: 39.03299 | AE64: -77.52199 | AF64: 57.6 | AH64: 276543 | AJ64: 49.42 | AK64: 47.13 | AL64: 51.82 | AM64: 49.42 | AQ64: 45130 | AU64: 46216 | AV64: 0 | AW64: 46539 | AX64: 46539 | BH64: 35f051b0-f1ce-470d-81d2-ea5c0d197f3a | BI64: PJM | BJ64: PJM Interconnection | BK64: 469a7dc0-fc5e-4f8e-8184-301f28134241 | BL64: DOM | BM64: Dominion Virginia Power zone - PJM | BO64: https://loudouncountyvaeg.tylerhost.net/prod/selfservice#/plan/A3CFB06B-5F39-4218-A8C5-D494E4ABAB9B?tab=contacts | BP64: https://maps.app.goo.gl/CsWAfQ9drFYNKkt69 | BQ64: https://loudouncountyvaeg.tylerhost.net/prod/selfservice#/plan/A3CFB06B-5F39-4218-A8C5-D494E4ABAB9B?tab=attachments | BS64: High | BT64: [2025-08-14 JR] Additional Info: Project under review, Conditional Approval _x000D_ [2026-04-22 JH] Construction: No visible construction activity observed on site. | BU64: 45883 | BV64: 46220 | BW64: 46238
A65: 9ec7725a-a369-4b54-975f-ee4d624ca536 | B65: Mesa Data Center Building 3 | C65: c0b3b599-1972-4e8d-b87b-ccb4105c1913 | D65: Mesa, CyrusOne Campus | E65: Announcement | F65: Y | I65: e4c9daa2-cda6-420e-aa0d-3af89c5d7fec | J65: CyrusOne | K65: https://www.cyrusone.com | L65: Private | P65: KKR | T65: 3221 S 96th St, Mesa, AZ 85212, USA | U65: 85212 | V65: 4013 | W65: Maricopa County | X65: Mesa | Y65: 46000 | Z65: AZ | AA65: Arizona | AB65: US | AC65: United States | AD65: 33.355816 | AE65: -111.62356 | AF65: 62 | AG65: 286530 | AH65: 286530 | AJ65: 50 | AK65: 47.72 | AL65: 52.39 | AM65: 50 | AQ65: 45252 | AU65: 46123 | AV65: 0 | AW65: 46752 | AX65: 46752 | BA65: 5f1c3274-a117-4201-b548-6a9e4b37f693 | BB65: Salt River Project | BC65: 16572 | BD65: Private | BH65: 4f4fe9e0-cb99-459e-9c12-6621c6e60461 | BI65: SRP | BJ65: Salt River Project | BO65: - https://www.bizjournals.com/phoenix/news/2023/11/21/cyrusone-large-data-center-mesa-campus.html_x000D_ - https://www.bizjournals.com/phoenix/news/2024/07/08/cyrusone-mesa-data-center-project.html | BP65: https://maps.app.goo.gl/y42LEhtgWwGwY9AUA | BS65: High | BT65: [2024-12-19 JR] Latest Satellite: 2024-11-01; Construction Status: No Construction; Estimated Active Date By: Aterio_x000D_ [2026-01-26 AV] Additional Info: Coordinates updated to match exact location. No visible signs of construction, activation date updated from 2026-06-30. | BU65: 45615 | BV65: 46202 | BW65: 46238
A66: e31eaab0-bb14-4fff-8dc9-07bf539af449 | B66: SAT2 San Antonio Data Center Building 2 | C66: 03457ba9-d04b-4e1f-a568-3af71cd7ab4f | D66: Westover Hills, Cyrusone Campus | E66: Active | F66: Y | I66: e4c9daa2-cda6-420e-aa0d-3af89c5d7fec | J66: CyrusOne | K66: https://www.cyrusone.com | L66: Private | P66: KKR | T66: 9655 Raba Dr, San Antonio, TX, USA | U66: 78251 | V66: 48029 | W66: Bexar County | X66: San Antonio | Y66: 65000 | Z66: TX | AA66: Texas | AB66: US | AC66: United States | AD66: 29.470829 | AE66: -98.670616 | AG66: 91800 | AH66: 97000 | AI66: 12 | AJ66: 6.82 | AK66: 6.5 | AL66: 7.15 | AM66: 12 | AP66: 8 | AT66: 42581 | AW66: 43132 | BA66: 7c503ef1-bc0f-4637-851d-466013cab44b | BB66: City of San Antonio - (TX) | BC66: 16604 | BD66: Public (Municipality) | BH66: 1fc90153-5419-4455-91f9-cee1dda4ed00 | BI66: ERCO | BJ66: Electric Reliability Council of Texas | BK66: e58fa18f-c7a0-44ba-9420-671c9e6c8d4f | BL66: SCEN | BM66: ERCO - South Central | BO66: https://documents.cyrusone.com/wp-content/uploads/2023/06/2022-SAT2_San-Antonio.pdf | BP66: https://maps.app.goo.gl/nL89pAP5Ta7CYbXx8 | BU66: 45474 | BV66: 46120 | BW66: 46238
A67: d89c20a4-25ad-49ca-9128-ab38199b579c | B67: Birmingham BHM1 Data Center | E67: Active | F67: Y | I67: 0609b950-8755-4146-8088-a60bf450bef8 | J67: DC BLOX | K67: https://www.dcblox.com | L67: Private | P67: Bain Capital Credit, Post Road Group | Q67: Alabama Power | T67: 433 6th Street, Birmingham, AL, USA | U67: 35214 | V67: 1073 | W67: Jefferson County | X67: Birmingham | Y67: 7000 | Z67: AL | AA67: Alabama | AB67: US | AC67: United States | AD67: 33.500683 | AE67: -86.82082 | AF67: 30.5 | AG67: 31000 | AH67: 31000 | AI67: 7.4 | AJ67: 4.02 | AK67: 3.83 | AL67: 4.21 | AM67: 7.4 | AN67: 7.4 | AP67: 6 | AT67: 43250 | AW67: 43617 | BA67: 72e94fed-c3a6-44dd-a382-e4796c46cfec | BB67: Alabama Power Co | BC67: 195 | BD67: Private | BH67: fc5d245b-5d3e-4004-b00a-666a73bde91d | BI67: SOCO | BJ67: Southern Company | BO67: https://www.dcblox.com/data-centers/birmingham/, https://www.dcblox.com/dc-blox-expands-birmingham-data-center-to-empower-hpc/ | BP67: https://maps.app.goo.gl/9T1D9x5EaUJKV5Z89 | BT67: [2025-01-21 FC] Additional Info: Existing building can support up to 36 HPC racks up to 2.4MW more power. Updating AI flag to Y and power capacity from 5MW. | BU67: 45474 | BV67: 46202 | BW67: 46238
A68: 9cf482c0-c64e-4487-afff-877d19594837 | B68: Huntsville, Alabama Data Center 2 | E68: Active | I68: 0609b950-8755-4146-8088-a60bf450bef8 | J68: DC BLOX | K68: https://www.dcblox.com | L68: Private | P68: Bain Capital Credit, Post Road Group | T68: 333 Diamond Dr NW, Huntsville, AL 35806, USA | U68: 35806 | V68: 1089 | W68: Madison County | X68: Huntsville | Y68: 37000 | Z68: AL | AA68: Alabama | AB68: US | AC68: United States | AD68: 34.709587 | AE68: -86.69316 | AI68: 5 | AM68: 5 | AP68: 2 | AQ68: 45631 | AT68: 45689 | AU68: 45967 | AV68: 1 | AW68: 45991 | BA68: 0881cabb-dc5e-4a18-adc5-ca3b61f080b8 | BB68: City of Huntsville - (AL) | BC68: 9094 | BD68: Public (Municipality) | BH68: 0a62fbf5-37bd-4c63-b8f8-25625976e565 | BI68: TVA | BJ68: Tennessee Valley Authority | BO68: https://www.dcblox.com/dc-blox-4-southeast-hyperscale-edge-node-data-centers/ | BP68: https://maps.app.goo.gl/7GeG8rbcdBGf4MW28 | BT68: [2025-08-08 JR] Construction: Foundations poured, start of vertical construction_x000D_ [2025-11-06 DP] Construction: There are no traces of recent construction or related activity, suggesting the building is in an active or commissioning stage; Additional Info: Stage updated to Active._x000D_ [2025-12-08] Additional Info: Activation Date Corrected. | BU68: 45636 | BV68: 45999 | BW68: 46238
A69: b23fc897-3816-4c7b-8b57-e178f9682edd | B69: New Castle Delaware Data Center | E69: Active | I69: 5e51007d-db31-415d-884c-2e3ed001a83a | J69: DaSTOR, LLC | K69: https://www.dastorllc.com | L69: Private | T69: 3 Boulden Circle, New Castle, DE, USA | U69: 19720 | V69: 10003 | W69: New Castle County | X69: New Castle | Y69: 50800 | Z69: DE | AA69: Delaware | AB69: US | AC69: United States | AD69: 39.68703 | AE69: -75.57451 | AH69: 60000 | AI69: 8 | AJ69: 2.67 | AK69: 2.55 | AL69: 2.8 | AM69: 8 | AW69: 39051 | BA69: fe2043ac-466c-4d77-a6f5-e48a2d5e4d13 | BB69: Delmarva Power | BC69: 5027 | BD69: Public | BE69: EXC | BF69: EXC:US | BG69: NASDAQ:EXC | BH69: 35f051b0-f1ce-470d-81d2-ea5c0d197f3a | BI69: PJM | BJ69: PJM Interconnection | BK69: 1cd4a7ea-9f74-498e-8e4f-292b3c0ff5b9 | BL69: DPL | BM69: Delmarva Power null zone - PJM | BO69: https://dastorllc.com/3-boulden-circle-new-castle-de/ | BP69: https://maps.app.goo.gl/zxsqJm3Z3tYVxkQw9 | BU69: 45474 | BV69: 46120 | BW69: 46238
A70: 69ddcdda-8fcd-45a9-a6af-caca12226128 | B70: HOU3 -Westway Park III Data Center | E70: Active | I70: 05f89b15-a287-4618-8564-9a4f737a6b0c | J70: DataBank | K70: https://www.databank.com | L70: Private | P70: Digital Bridge Group, AustralianSuper, Swiss Life Asset Management | T70: 11003 Corporate Centre Dr, Houston, TX 77041, USA | U70: 77041 | V70: 48201 | W70: Harris County | X70: Houston | Y70: 35000 | Z70: TX | AA70: Texas | AB70: US | AC70: United States | AD70: 29.84406 | AE70: -95.560356 | AG70: 162000 | AH70: 41860 | AI70: 4.5 | AJ70: 4.71 | AK70: 4.49 | AL70: 4.94 | AM70: 4.5 | AN70: 4.5 | AT70: 41759 | AW70: 42399 | BA70: 866548e1-693d-4b06-930a-a745e5f943d5 | BB70: CenterPoint Energy | BC70: 8901 | BD70: Public | BE70: CNP | BF70: CNP:US | BG70: NYSE:CNP | BH70: 1fc90153-5419-4455-91f9-cee1dda4ed00 | BI70: ERCO | BJ70: Electric Reliability Council of Texas | BK70: 8ff5a335-763a-412f-9874-2292edb5ce7b | BL70: COAS | BM70: ERCO - Coast | BO70: https://www.databank.com/data-centers/houston/westway-park-campus/11003-corporate-centre-dr/,https://www.bizjournals.com/houston/news/2026/05/13/databank-plans-largest-solar-array-in-houston.html | BP70: https://maps.app.goo.gl/UqceAVXrZP9Gwxra8 | BT70: [2026-05-13 JH] Additional Info: DataBank plans to install 3.15 MW of rooftop solar at its Houston data center, expected to generate 4.5 million kWh annually over 25 years. | BU70: 45474 | BV70: 46202 | BW70: 46238
A71: f9993610-f08f-42bd-a744-2246b2cde3dd | B71: HOU5 -Houston Galleria Data Center | E71: Active | I71: 05f89b15-a287-4618-8564-9a4f737a6b0c | J71: DataBank | K71: https://www.databank.com | L71: Private | P71: Digital Bridge Group, AustralianSuper, Swiss Life Asset Management | T71: 4201 Southwest Freeway, Houston, TX 77027, USA | U71: 77027 | V71: 48201 | W71: Harris County | X71: Houston | Y71: 35000 | Z71: TX | AA71: Texas | AB71: US | AC71: United States | AD71: 29.728128 | AE71: -95.44511 | AG71: 112000 | AH71: 64400 | AI71: 5.25 | AJ71: 6.09 | AK71: 5.81 | AL71: 6.39 | AM71: 5.25 | AN71: 5.25 | AW71: 40575 | BA71: 866548e1-693d-4b06-930a-a745e5f943d5 | BB71: CenterPoint Energy | BC71: 8901 | BD71: Public | BE71: CNP | BF71: CNP:US | BG71: NYSE:CNP | BH71: 1fc90153-5419-4455-91f9-cee1dda4ed00 | BI71: ERCO | BJ71: Electric Reliability Council of Texas | BK71: 8ff5a335-763a-412f-9874-2292edb5ce7b | BL71: COAS | BM71: ERCO - Coast | BO71: https://www.databank.com/data-centers/houston/4201-southwest-freeway/ , https://datacentremagazine.com/data-centres/databank-acquires-four-cyrusone-data-centres-for-us-670mn | BP71: https://maps.app.goo.gl/hgnqpnvYT4Zodmyu9 | BU71: 45474 | BV71: 46202 | BW71: 46238
A72: b089feb5-3250-4756-87af-3a44f084e48b | B72: DFW8 - Plano II Data Center | C72: 500ee4c4-332e-4e1d-b123-d422d11726c8 | D72: DataBank Plano Campus | E72: Construction | I72: 05f89b15-a287-4618-8564-9a4f737a6b0c | J72: DataBank | K72: https://www.databank.com | L72: Private | P72: Digital Bridge Group, AustralianSuper, Swiss Life Asset Management | T72: 8375 Dominion Pkwy, Plano, TX, USA | U72: 75024 | V72: 48085 | W72: Collin County | X72: Plano | Y72: 58016 | Z72: TX | AA72: Texas | AB72: US | AC72: United States | AD72: 33.087 | AE72: -96.816 | AF72: 16 | AG72: 144000 | AH72: 126000 | AI72: 40 | AJ72: 33.05 | AK72: 31.52 | AL72: 34.66 | AM72: 40 | AN72: 40 | AP72: 18 | AT72: 45474 | AU72: 46059 | AV72: 0.95 | AW72: 46203 | AX72: 46203 | BA72: ef600df2-b943-4233-9ec9-0a59020aa7c7 | BB72: Denton County Elec Coop, Inc | BC72: 5078 | BD72: Private (Cooperative) | BH72: 1fc90153-5419-4455-91f9-cee1dda4ed00 | BI72: ERCO | BJ72: Electric Reliability Council of Texas | BK72: 14cc320b-3a3d-47a9-83a4-e27eff5c1700 | BL72: NCEN | BM72: ERCO - North Central | BO72: https://www.databank.com/data-centers/dallas/plano-campus/ | BP72: https://maps.app.goo.gl/SoHtJZ8GR4dt9F359 | BS72: High | BT72: [2025-01-27 JR] Latest Satellite: [N/A]; Construction Status: Construction 70%; Estimated Active Date By: Aterio; Additional Info: Updated Stage to highlight the expansion, construction update provided by DataBank_x000D_ [2025-05-12 JR] Construction: Vertical construction complete. Roof installed; generator and cooling infrastructure placement still in progress. _x000D_ [2025-10-27 DP] Construction: Cooling equipment and generators being placed; installation of rooftop cooling systems and generators near to complete._x000D_ [2025-11-27 DP] Contruction: No major construction progress; several generators and cooling towers are still not installed._x000D_ [2026-01-08 JR] Construction: Equipment installation still underway, 9 out of 18 generators installed and cooling towers missing on the roof. Parking lot completed but no car activity; Additional Info: Activation Date updated from 2025-12-15._x000D_ [2026-02-27 AV] Construction: There is still visible machinery outside the building, there appears to be some cooling equipment that is pending for installation. Additional Info: Activation date updated from 2026-03-01 to Q2 2026. _x000D_ [2026-06-09 SQ] Construction: Satellite pending to confirm activation_x000D_ [2026-07-02 SQ] Construction: Waiting for satellite imagery to confirm activation. | BU72: 45474 | BV72: 46205 | BW72: 46238
A73: 46d96745-af85-4292-b3ca-d313f002539c | B73: Silicon Valley SJC11 Data Center | E73: Active | I73: c941e192-2144-4d4a-be65-3ba8f1958721 | J73: Digital Realty | K73: https://www.digitalrealty.com | L73: Public | M73: DLR | N73: DLR:US | O73: NYSE: DLR | T73: 3011 Lafayette Street, Santa Clara, CA, USA | U73: 95054 | V73: 6085 | W73: Santa Clara County | X73: Santa Clara | Y73: 69084 | Z73: CA | AA73: California | AB73: US | AC73: United States | AD73: 37.376286 | AE73: -121.94846 | AG73: 46000 | AH73: 90800 | AI73: 9 | AJ73: 9.66 | AK73: 9.21 | AL73: 10.13 | AM73: 9 | AP73: 6 | AT73: 39385 | AW73: 39629 | BA73: 625b7686-055b-46e1-a5a4-4e3dcaf631b4 | BB73: Pacific Gas & Electric Co. | BC73: 14328 | BD73: Public | BE73: PCG | BF73: PCG:US | BG73: NYSE:PCG | BH73: 2950a9eb-39ef-4949-96bd-ecefbf7db624 | BI73: CISO | BJ73: California Independent System Operator | BK73: 9bbe5250-047e-4a37-8434-4cda4fceb9e5 | BL73: PGAE | BM73: Pacific Gas and Electric | BO73: https://www.digitalrealty.com/data-centers/americas/silicon-valley/sjc11 | BP73: https://maps.app.goo.gl/xouoFzxqgQHWJcy97 | BU73: 45474 | BV73: 46219 | BW73: 46238
A74: 9ffa2f5d-ea18-4060-b4f7-52cc49867bed | B74: E Cermak Rd Chicago Data Center | E74: Announcement | I74: c941e192-2144-4d4a-be65-3ba8f1958721 | J74: Digital Realty | K74: https://www.digitalrealty.com | L74: Public | M74: DLR | N74: DLR:US | O74: NYSE: DLR | T74: 330 East Cermak Road, Chicago, IL, USA | U74: 60616 | V74: 17031 | W74: Cook County | X74: Chicago | Y74: 14000 | Z74: IL | AA74: Illinois | AB74: US | AC74: United States | AD74: 41.853245 | AE74: -87.619675 | AG74: 698000 | AH74: 698000 | AI74: 54 | AJ74: 74.02 | AK74: 70.58 | AL74: 77.62 | AM74: 54 | AQ74: 45473 | AU74: 46211 | AV74: 0 | AW74: 46568 | BA74: 222a249b-639d-4c33-9bba-36724efea762 | BB74: Commonwealth Edison Co | BC74: 4110 | BD74: Private (Part of Exelon Corp) | BE74: EXC | BF74: EXC:US | BG74: NASDAQ:EXC | BH74: 35f051b0-f1ce-470d-81d2-ea5c0d197f3a | BI74: PJM | BJ74: PJM Interconnection | BK74: e84646c2-7438-4a4c-916e-953518bd940a | BL74: CE | BM74: Commonwealth Edison zone - PJM | BO74: https://www.digitalrealty.com/about/projects/digital-cermak , https://www.archideas.com/digital-realty-poised-expand/ | BP74: https://maps.app.goo.gl/2geykzTHC9gDwS6d9 | BS74: Medium | BT74: [2025-10-22 AV] Construction: Data center planned in an existing building. There is no visibility into the start of the construction project._x000D_ [2025-11-13 AV]: Additional Info: Construction has not started. Activation date updated from 2026-06-30. | BU74: 45555 | BV74: 46220 | BW74: 46238
A75: 300e7c04-f741-4c18-a773-9f040da6d2c8 | B75: Boston BOS13 Data Center | E75: Active | I75: c941e192-2144-4d4a-be65-3ba8f1958721 | J75: Digital Realty | K75: https://www.digitalrealty.com | L75: Public | M75: DLR | N75: DLR:US | O75: NYSE: DLR | T75: 55 Middlesex Turnpike, Bedford, MA, USA | U75: 1730 | V75: 25017 | W75: Middlesex County | X75: Bedford | Z75: MA | AA75: Massachusetts | AB75: US | AC75: United States | AD75: 42.512444 | AE75: -71.23675 | AG75: 106000 | AH75: 106000 | AI75: 10 | AJ75: 11.08 | AK75: 10.57 | AL75: 11.62 | AM75: 10 | AP75: 6 | AW75: 36737 | BH75: 1164f15f-eb65-4d74-9a7e-72f721f4080f | BI75: ISNE | BJ75: ISO New England | BK75: f6648419-87f7-4033-9984-dae4c5376c5e | BL75: 4008 | BM75: ISNE - Northeast Mass. | BO75: https://www.digitalrealty.com/data-centers/americas/boston/bos13 | BP75: https://maps.app.goo.gl/qJ9GRq97Wu623zG78 | BU75: 45474 | BV75: 46219 | BW75: 46238
A76: e079ecc9-d297-40ce-8982-44a46ee1b184 | B76: Northern Virginia IAD12 Data Center | C76: 84f34345-e47e-43a1-bae8-b9bd1046cd7c | D76: Ashburn, Digital Realty Campus | E76: Active | I76: c941e192-2144-4d4a-be65-3ba8f1958721 | J76: Digital Realty | K76: https://www.digitalrealty.com | L76: Public | M76: DLR | N76: DLR:US | O76: NYSE: DLR | T76: 43881 Devin Shafron Drive bldg b, Ashburn, VA, USA | U76: 20147 | V76: 51107 | W76: Loudoun County | X76: Ashburn | Y76: 3320 | Z76: VA | AA76: Virginia | AB76: US | AC76: United States | AD76: 39.002117 | AE76: -77.483284 | AG76: 180000 | AH76: 180000 | AI76: 16 | AJ76: 15.46 | AK76: 14.74 | AL76: 16.21 | AM76: 16 | AP76: 12 | AW76: 38806 | BA76: 5b0c2f7d-42e6-4e89-997c-39d2e368e019 | BB76: Virginia Electric & Power Co | BC76: 19876 | BD76: Public | BE76: D | BF76: D:US | BG76: NYSE:D | BH76: 35f051b0-f1ce-470d-81d2-ea5c0d197f3a | BI76: PJM | BJ76: PJM Interconnection | BK76: 469a7dc0-fc5e-4f8e-8184-301f28134241 | BL76: DOM | BM76: Dominion Virginia Power zone - PJM | BO76: https://go2.digitalrealty.com/rs/087-YZJ-646/images/DS_Digital_Realty_2308_IAD12_Property_factsheet_EN.pdf?_ga=2.148986294.1073793901.1727886547-1341700026.1727394287&_gac=1.84391019.1727887875.Cj0KCQjw3vO3BhCqARIsAEWblcBxapY2NVKSNjqnEQ4acucDHklYwED1OS9Gd_jJHF-oEGAepBDgnPwaAgb9EALw_wcB | BP76: https://maps.app.goo.gl/yBMqFFcHYBzXdxJ98 | BU76: 45474 | BV76: 46219 | BW76: 46238
A77: 3d3eacb4-09b4-47d4-b0f8-57ac55ef4e5b | B77: New York EWR20 Data Center | C77: e8b03c04-17dc-4672-b682-d2a66686277f | D77: Clifton, Digital Realty Campus | E77: Active | I77: c941e192-2144-4d4a-be65-3ba8f1958721 | J77: Digital Realty | K77: https://www.digitalrealty.com | L77: Public | M77: DLR | N77: DLR:US | O77: NYSE: DLR | T77: 100 Delawanna Avenue, Clifton, NJ, USA | U77: 7014 | V77: 34031 | W77: Passaic County | X77: Clifton | Y77: 13690 | Z77: NJ | AA77: New Jersey | AB77: US | AC77: United States | AD77: 40.82995 | AE77: -74.126656 | AG77: 183000 | AH77: 183000 | AI77: 11 | AJ77: 14.09 | AK77: 13.44 | AL77: 14.77 | AM77: 11 | AP77: 2 | AT77: 39963 | AW77: 40328 | BA77: 6a880b5e-420e-45a7-bf47-291dc8873a78 | BB77: Public Service Elec & Gas Co | BC77: 15477 | BD77: Public | BE77: PEG | BF77: PEG:US | BG77: NYSE:PEG | BH77: 35f051b0-f1ce-470d-81d2-ea5c0d197f3a | BI77: PJM | BJ77: PJM Interconnection | BK77: 786a8dc9-a42b-451b-8ae9-1e4ef532e3ba | BL77: RECO | BM77: Rockland Electric (East) zone - PJM | BO77: https://www.digitalrealty.com/data-centers/americas/new-york/ewr20 | BP77: https://maps.app.goo.gl/fLMRCsvLcYEcyoP99 | BU77: 45474 | BV77: 46219 | BW77: 46238
A78: 05bfdf8e-12f1-430b-89e6-709f245cc029 | B78: Data Center 1 | C78: bda06ff0-29d0-11f0-82cd-25e7d375563e | D78: Digital Dulles | E78: Announcement | I78: c941e192-2144-4d4a-be65-3ba8f1958721 | J78: Digital Realty | K78: https://www.digitalrealty.com | L78: Public | M78: DLR | N78: DLR:US | O78: NYSE: DLR | Q78: Urban Ltd | T78: Digital Dulles Dr, Dulles, VA 20166, USA | U78: 20166 | V78: 51107 | W78: Loudoun County | X78: Sterling | Y78: 75376 | Z78: VA | AA78: Virginia | AB78: US | AC78: United States | AD78: 38.954277 | AE78: -77.490295 | AF78: 433 | AH78: 645000 | AI78: 80 | AJ78: 70.78 | AK78: 67.5 | AL78: 74.22 | AM78: 80 | AQ78: 44022 | AU78: 46154 | AV78: 0 | AW78: 46934 | AX78: 46934 | BH78: 35f051b0-f1ce-470d-81d2-ea5c0d197f3a | BI78: PJM | BJ78: PJM Interconnection | BK78: 469a7dc0-fc5e-4f8e-8184-301f28134241 | BL78: DOM | BM78: Dominion Virginia Power zone - PJM | BO78: https://www.nao.usace.army.mil/Media/Public-Notices/Article/2277654/nao-2006-07410/ | BP78: https://maps.app.goo.gl/DSgU9DzgHeqGMytm9 | BQ78: https://loudouncountyvaeg.tylerhost.net/prod/selfservice#/plan/922d1750-253b-44dc-8857-bdcff5e78c3f?tab=attachments,https://usace.contentdm.oclc.org/utils/getfile/collection/p16021coll7/id/14773, https://www.nao.usace.army.mil/Media/Public-Notices/Article/4371433/nao-2006-07410-vmrc-dulles-digital-loudoun-county-virginia/, https://www.deq.virginia.gov/home/showpublisheddocument/32403/638989963113270000, https://webapps.mrc.virginia.gov/public/habitat/getADD.php?id=129719 | BS78: High | BT78: [2025-05-05 JR] Additional Info: Permit documents show 11 data centers planned for the site, but only 2 are currently registered. Project scope has been updated to reflect full development plans._x000D_ [2026-01-07 FC] Additional Info: Updated location and sqft and permit URL and published power capacity from filing._x000D_ [2026-03-11 SQ] Additional Info: No construction visible, activation date updated from 2027-09-15 to Q2 2028. | BU78: 45782 | BV78: 46219 | BW78: 46238
A79: c3810378-f342-478c-89ed-eab720a41f5f | B79: Garland Data Center Building 1 | C79: ff25cdbf-54d5-4b87-bfa7-dfdc38694dbf | D79: Garland, Digital Realty Campus | E79: Active | I79: c941e192-2144-4d4a-be65-3ba8f1958721 | J79: Digital Realty | K79: https://www.digitalrealty.com | L79: Public | M79: DLR | N79: DLR:US | O79: NYSE: DLR | T79: 1505 Ferris Rd, Garland, TX, USA | U79: 75044 | V79: 48113 | W79: Dallas County | X79: Garland | Y79: 29000 | Z79: TX | AA79: Texas | AB79: US | AC79: United States | AD79: 32.974545 | AE79: -96.65019 | AF79: 45 | AG79: 180000 | AH79: 180000 | AI79: 16 | AJ79: 16.26 | AK79: 15.51 | AL79: 17.05 | AM79: 16 | AP79: 9 | AQ79: 43038 | AT79: 44895 | AW79: 45641 | BA79: 1ebbb343-179f-4d9d-a878-d6b03846b4c4 | BB79: City of Garland - (TX) | BC79: 6958 | BD79: Public (Municipality) | BH79: 1fc90153-5419-4455-91f9-cee1dda4ed00 | BI79: ERCO | BJ79: Electric Reliability Council of Texas | BK79: 14cc320b-3a3d-47a9-83a4-e27eff5c1700 | BL79: NCEN | BM79: ERCO - North Central | BO79: https://www.govtech.com/analytics/two-dallas-fort-worth-data-center-projects-gett-underway | BP79: https://maps.app.goo.gl/LSwGCuc3b46CFAHL7 | BQ79: https://www.tdlr.texas.gov/TABS/Search/Project/TABS2026018121 | BT79: [2024-12-19 JR] Latest Satellite: 2024-09-26; Construction Status: Construction 80%; Estimated Active Date By: Aterio; Additional Info: Area Estimated by Aterio. Mitsubishi Corp with 65% equity interest_x000D_ [2025-01-07 JR] Additional Info: Stage Updated to Active | BU79: 45590 | BV79: 46219 | BW79: 46238
A80: faf4cf85-ce15-4db8-b191-39d2e56a1310 | B80: Northern Virginia ACC6 Data Center | C80: 2f7b3389-81e3-419e-b940-5fbd88c1126d | D80: Hastings Dr, Digital Realty Campus | E80: Active | I80: c941e192-2144-4d4a-be65-3ba8f1958721 | J80: Digital Realty | K80: https://www.digitalrealty.com | L80: Public | M80: DLR | N80: DLR:US | O80: NYSE: DLR | T80: 44461 Chilum Place, Ashburn, VA, USA | U80: 20147 | V80: 51107 | W80: Loudoun County | X80: Ashburn | Y80: 3320 | Z80: VA | AA80: Virginia | AB80: US | AC80: United States | AD80: 39.021114 | AE80: -77.46367 | AG80: 222300 | AH80: 222300 | AI80: 54 | AJ80: 24.29 | AK80: 23.16 | AL80: 25.47 | AM80: 54 | AT80: 40420 | AW80: 41059 | BA80: 5b0c2f7d-42e6-4e89-997c-39d2e368e019 | BB80: Virginia Electric & Power Co | BC80: 19876 | BD80: Public | BE80: D | BF80: D:US | BG80: NYSE:D | BH80: 35f051b0-f1ce-470d-81d2-ea5c0d197f3a | BI80: PJM | BJ80: PJM Interconnection | BK80: 469a7dc0-fc5e-4f8e-8184-301f28134241 | BL80: DOM | BM80: Dominion Virginia Power zone - PJM | BO80: https://www.digitalrealty.com/data-centers/americas/northern-virginia/acc6 | BP80: https://maps.app.goo.gl/kwuY6MixFidjogPR8 | BU80: 45474 | BV80: 46219 | BW80: 46238
